Workbook

Sheet CS
A1: Lv | B1: スキル名 | C1: ルビ | D1: 系統 | E1: 行動 | F1: HP消費 | G1: AP消費 | H1: データ | I1: 効果 | J1: 効果説明 | K1: 取得条件 | L1: 出力確認 | M1: ダブり確認 | N1: アニメ | O1: 戦闘ルール | P1: 盾装備でデメリットは威力が下がる、軽減値が増える。 | Q1: モンク シーフ レンジャー スカウト ウィザード アルケミスト イリュージョニスト エレメント・マスター クレリック ビショップ プリースト パラディン ゴブリン オーガ トレント インプ エンジェル ソードマスター スピアマスター ブロウマスター シールドマスター ソードセイント スピアセイント ブロウセイント シールドセイント
B2: 1:初級 1 2:下級 23 3:中級 34 4:上級 56 5:下級神 7 6:中級神 89 7:上級神 10 | C2: 35 55 75 95 115 145 175 攻撃追加+1 攻撃回数:2 2倍加 など | D2: 条件 条件系統 | H2: 指揮 戦術 威圧 看破 索敵 隠密 生存 罠設置 農耕 伐採 採掘 錬成 統率 交渉 政治 信仰 | J2: 範囲について 単体,全体,縦,ライン 前後ろ縦を選択してダメージ,周囲(同じ列のみ) 効果に「連鎖」があると周囲に50%ダメージ | K2: 3.魔法強化 3.射程 4倍速 4.魔法極強化 4.三重 | M2: 回復:35 魔力105~210 10.5~21 | N2: 回復:115 魔力565~1130 34.5~69 | T2: 0.3
B3: 微5~10 小11~20 中21~35 大36~50 極51~ | C3: 〇〇の接続 で魔法取得 〇〇魔法強化 | I3: 攻撃手段:魔法 特殊:攻撃 | J3: 攻撃手段:魔法 特殊:攻撃 | K3: 属性: ロール: 技能: スキル:|
J4: =IFERROR(LET(_xlpm.v, VLOOKUP($I4,'用語辞書'!$A:$B,COLUMN('用語辞書'!B$1),FALSE), IF(_xlpm.v=0,"",_xlpm.v) ),"") | L4: =IF(OR(COUNTIF('クラス'!$A$1:$A$1267,$B4)>0,$B4="",$M4=""),"",True)
J5: =IFERROR(LET(_xlpm.v, VLOOKUP($I5,'用語辞書'!$A:$B,COLUMN('用語辞書'!B$1),FALSE), IF(_xlpm.v=0,"",_xlpm.v) ),"") | L5: =IF(OR(COUNTIF('クラス'!$A$1:$A$1267,$B5)>0,$B5="",$M5=""),"",True)
J6: =IFERROR(LET(_xlpm.v, VLOOKUP($I6,'用語辞書'!$A:$B,COLUMN('用語辞書'!B$1),FALSE), IF(_xlpm.v=0,"",_xlpm.v) ),"") | L6: =IF(OR(COUNTIF('クラス'!$A$1:$A$1267,$B6)>0,$B6="",$M6=""),"",True) | M6: =IF(COUNTIF($B$1:$C5, $B6), "", "存在しない") -> 存在しない
C7: ="------------基礎技 ------------" -> ------------基礎技 ------------ | J7: =IFERROR(LET(_xlpm.v, VLOOKUP($I7,'用語辞書'!$A:$B,COLUMN('用語辞書'!B$1),FALSE), IF(_xlpm.v=0,"",_xlpm.v) ),"") | L7: =IF(OR(COUNTIF('クラス'!$A$1:$A$1267,$B7)>0,$B7="",$M7=""),"",True) | M7: =IF(COUNTIF($B$1:$C6, $B7), "", "存在しない") -> 存在しない
B8: 肉体攻撃 | D8: 系統 | E8: スキルタイプ | F8: HP消費 | G8: AP消費 | H8: 効果 | J8: =IFERROR(LET(_xlpm.v, VLOOKUP($I8,'用語辞書'!$A:$B,COLUMN('用語辞書'!B$1),FALSE), IF(_xlpm.v=0,"",_xlpm.v) ),"") | L8: =IF(OR(COUNTIF('クラス'!$A$1:$A$1267,$B8)>0,$B8="",$M8=""),"",True) -> TRUE | M8: =IF(COUNTIF($B$1:$C7, $B8), "", "存在しない") -> 存在しない
A9: 1 | B9: 角 | E9: A | G9: 60 | H9: 攻撃手段:角 物理+25 判定:攻撃 | J9: =IFERROR(LET(_xlpm.v, VLOOKUP($I9,'用語辞書'!$A:$B,COLUMN('用語辞書'!B$1),FALSE), IF(_xlpm.v=0,"",_xlpm.v) ),"") | L9: =IF(OR(COUNTIF('クラス'!$A$1:$A$1267,$B9)>0,$B9="",$M9=""),"",True) -> TRUE | M9: =IF(COUNTIF($B$1:$C8, $B9), "", "存在しない") -> 存在しない | N9: 角
A10: 2 | B10: 牙 | E10: A | G10: 30 | H10: 攻撃手段:牙 物理+20 判定:攻撃 | J10: =IFERROR(LET(_xlpm.v, VLOOKUP($I10,'用語辞書'!$A:$B,COLUMN('用語辞書'!B$1),FALSE), IF(_xlpm.v=0,"",_xlpm.v) ),"") | L10: =IF(OR(COUNTIF('クラス'!$A$1:$A$1267,$B10)>0,$B10="",$M10=""),"",True) -> TRUE | M10: =IF(COUNTIF($B$1:$C9, $B10), "", "存在しない") -> 存在しない | N10: 牙
A11: 3 | B11: 爪 | E11: A | G11: 40 | H11: 攻撃手段:爪 物理+15 攻撃回数:2 判定:攻撃 | J11: =IFERROR(LET(_xlpm.v, VLOOKUP($I11,'用語辞書'!$A:$B,COLUMN('用語辞書'!B$1),FALSE), IF(_xlpm.v=0,"",_xlpm.v) ),"") | L11: =IF(OR(COUNTIF('クラス'!$A$1:$A$1267,$B11)>0,$B11="",$M11=""),"",True) -> TRUE | M11: =IF(COUNTIF($B$1:$C10, $B11), "", "存在しない") -> 存在しない | N11: 爪
A12: 4 | B12: 尾 | E12: A | G12: 20 | H12: 攻撃手段:尾 物理+15 判定:攻撃 | J12: =IFERROR(LET(_xlpm.v, VLOOKUP($I12,'用語辞書'!$A:$B,COLUMN('用語辞書'!B$1),FALSE), IF(_xlpm.v=0,"",_xlpm.v) ),"") | L12: =IF(OR(COUNTIF('クラス'!$A$1:$A$1267,$B12)>0,$B12="",$M12=""),"",True) -> TRUE | M12: =IF(COUNTIF($B$1:$C11, $B12), "", "存在しない") -> 存在しない | N12: 尾
A13: 5 | B13: 尾針 | E13: A | G13: 20 | H13: 攻撃手段:尾 物理+25 判定:攻撃 | J13: =IFERROR(LET(_xlpm.v, VLOOKUP($I13,'用語辞書'!$A:$B,COLUMN('用語辞書'!B$1),FALSE), IF(_xlpm.v=0,"",_xlpm.v) ),"") | L13: =IF(OR(COUNTIF('クラス'!$A$1:$A$1267,$B13)>0,$B13="",$M13=""),"",True) -> TRUE | M13: =IF(COUNTIF($B$1:$C12, $B13), "", "存在しない") -> 存在しない
A14: 6 | B14: 尾の巻き付き | E14: A | G14: 70 | H14: 攻撃手段:尾 物理+10 拘束+30 判定:攻撃 | J14: =IFERROR(LET(_xlpm.v, VLOOKUP($I14,'用語辞書'!$A:$B,COLUMN('用語辞書'!B$1),FALSE), IF(_xlpm.v=0,"",_xlpm.v) ),"") | L14: =IF(OR(COUNTIF('クラス'!$A$1:$A$1267,$B14)>0,$B14="",$M14=""),"",True) -> TRUE | M14: =IF(COUNTIF($B$1:$C13, $B14), "", "存在しない") -> 存在しない
A15: 7 | B15: 翼 | E15: A | G15: 40 | H15: 攻撃手段:翼 物理+10 ガード+15 攻撃回数:2 判定:攻撃 | J15: =IFERROR(LET(_xlpm.v, VLOOKUP($I15,'用語辞書'!$A:$B,COLUMN('用語辞書'!B$1),FALSE), IF(_xlpm.v=0,"",_xlpm.v) ),"") | L15: =IF(OR(COUNTIF('クラス'!$A$1:$A$1267,$B15)>0,$B15="",$M15=""),"",True) -> TRUE | M15: =IF(COUNTIF($B$1:$C14, $B15), "", "存在しない") -> 存在しない
A16: 8 | J16: =IFERROR(LET(_xlpm.v, VLOOKUP($I16,'用語辞書'!$A:$B,COLUMN('用語辞書'!B$1),FALSE), IF(_xlpm.v=0,"",_xlpm.v) ),"") | L16: =IF(OR(COUNTIF('クラス'!$A$1:$A$1267,$B16)>0,$B16="",$M16=""),"",True) | M16: =IF(COUNTIF($B$1:$C15, $B16), "", "存在しない") -> 存在しない
A17: 9 | B17: 突撃 | J17: =IFERROR(LET(_xlpm.v, VLOOKUP($I17,'用語辞書'!$A:$B,COLUMN('用語辞書'!B$1),FALSE), IF(_xlpm.v=0,"",_xlpm.v) ),"") | L17: =IF(OR(COUNTIF('クラス'!$A$1:$A$1267,$B17)>0,$B17="",$M17=""),"",True) -> TRUE | M17: =IF(COUNTIF($B$1:$C16, $B17), "", "存在しない") -> 存在しない | N17: #VALUE!
A18: 10 | J18: =IFERROR(LET(_xlpm.v, VLOOKUP($I18,'用語辞書'!$A:$B,COLUMN('用語辞書'!B$1),FALSE), IF(_xlpm.v=0,"",_xlpm.v) ),"") | L18: =IF(OR(COUNTIF('クラス'!$A$1:$A$1267,$B18)>0,$B18="",$M18=""),"",True) | M18: =IF(COUNTIF($B$1:$C17, $B18), "", "存在しない") -> 存在しない
J19: =IFERROR(LET(_xlpm.v, VLOOKUP($I19,'用語辞書'!$A:$B,COLUMN('用語辞書'!B$1),FALSE), IF(_xlpm.v=0,"",_xlpm.v) ),"") | L19: =IF(OR(COUNTIF('クラス'!$A$1:$A$1267,$B19)>0,$B19="",$M19=""),"",True) | M19: =IF(COUNTIF($B$1:$C18, $B19), "", "存在しない") -> 存在しない
J20: =IFERROR(LET(_xlpm.v, VLOOKUP($I20,'用語辞書'!$A:$B,COLUMN('用語辞書'!B$1),FALSE), IF(_xlpm.v=0,"",_xlpm.v) ),"") | L20: =IF(OR(COUNTIF('クラス'!$A$1:$A$1267,$B20)>0,$B20="",$M20=""),"",True) | M20: =IF(COUNTIF($B$1:$C19, $B20), "", "存在しない") -> 存在しない
C21: ="------------ 薬 ------------" -> ------------ 薬 ------------ | J21: =IFERROR(LET(_xlpm.v, VLOOKUP($I21,'用語辞書'!$A:$B,COLUMN('用語辞書'!B$1),FALSE), IF(_xlpm.v=0,"",_xlpm.v) ),"") | L21: =IF(OR(COUNTIF('クラス'!$A$1:$A$1267,$B21)>0,$B21="",$M21=""),"",True) | M21: =IF(COUNTIF($B$1:$C19, $B21), "", "存在しない") -> 存在しない
A22: 1 | B22: 薬草 | H22: 再生+5 効果時間6t | J22: =IFERROR(LET(_xlpm.v, VLOOKUP($I22,'用語辞書'!$A:$B,COLUMN('用語辞書'!B$1),FALSE), IF(_xlpm.v=0,"",_xlpm.v) ),"") | L22: =IF(OR(COUNTIF('クラス'!$A$1:$A$1267,$B22)>0,$B22="",$M22=""),"",True) -> TRUE | M22: =IF(COUNTIF($B$1:$C20, $B22), "", "存在しない") -> 存在しない
A23: 2 | B23: 水薬 | H23: 回復+20 再生+5 効果時間6t | J23: =IFERROR(LET(_xlpm.v, VLOOKUP($I23,'用語辞書'!$A:$B,COLUMN('用語辞書'!B$1),FALSE), IF(_xlpm.v=0,"",_xlpm.v) ),"") | L23: =IF(OR(COUNTIF('クラス'!$A$1:$A$1267,$B23)>0,$B23="",$M23=""),"",True) -> TRUE | M23: =IF(COUNTIF($B$1:$C21, $B23), "", "存在しない") -> 存在しない
A24: 3 | J24: =IFERROR(LET(_xlpm.v, VLOOKUP($I24,'用語辞書'!$A:$B,COLUMN('用語辞書'!B$1),FALSE), IF(_xlpm.v=0,"",_xlpm.v) ),"") | L24: =IF(OR(COUNTIF('クラス'!$A$1:$A$1267,$B24)>0,$B24="",$M24=""),"",True) | M24: =IF(COUNTIF($B$1:$C22, $B24), "", "存在しない") -> 存在しない
A25: 4 | J25: =IFERROR(LET(_xlpm.v, VLOOKUP($I25,'用語辞書'!$A:$B,COLUMN('用語辞書'!B$1),FALSE), IF(_xlpm.v=0,"",_xlpm.v) ),"") | L25: =IF(OR(COUNTIF('クラス'!$A$1:$A$1267,$B25)>0,$B25="",$M25=""),"",True) | M25: =IF(COUNTIF($B$1:$C23, $B25), "", "存在しない") -> 存在しない
A26: 5 | B26: 霊薬 | H26: 回復+80 | J26: =IFERROR(LET(_xlpm.v, VLOOKUP($I26,'用語辞書'!$A:$B,COLUMN('用語辞書'!B$1),FALSE), IF(_xlpm.v=0,"",_xlpm.v) ),"") | L26: =IF(OR(COUNTIF('クラス'!$A$1:$A$1267,$B26)>0,$B26="",$M26=""),"",True) -> TRUE | M26: =IF(COUNTIF($B$1:$C24, $B26), "", "存在しない") -> 存在しない
A27: 6 | J27: =IFERROR(LET(_xlpm.v, VLOOKUP($I27,'用語辞書'!$A:$B,COLUMN('用語辞書'!B$1),FALSE), IF(_xlpm.v=0,"",_xlpm.v) ),"") | L27: =IF(OR(COUNTIF('クラス'!$A$1:$A$1267,$B27)>0,$B27="",$M27=""),"",True) | M27: =IF(COUNTIF($B$1:$C25, $B27), "", "存在しない") -> 存在しない
A28: 7 | J28: =IFERROR(LET(_xlpm.v, VLOOKUP($I28,'用語辞書'!$A:$B,COLUMN('用語辞書'!B$1),FALSE), IF(_xlpm.v=0,"",_xlpm.v) ),"") | L28: =IF(OR(COUNTIF('クラス'!$A$1:$A$1267,$B28)>0,$B28="",$M28=""),"",True) | M28: =IF(COUNTIF($B$1:$C26, $B28), "", "存在しない") -> 存在しない
A29: 8 | J29: =IFERROR(LET(_xlpm.v, VLOOKUP($I29,'用語辞書'!$A:$B,COLUMN('用語辞書'!B$1),FALSE), IF(_xlpm.v=0,"",_xlpm.v) ),"") | L29: =IF(OR(COUNTIF('クラス'!$A$1:$A$1267,$B29)>0,$B29="",$M29=""),"",True) | M29: =IF(COUNTIF($B$1:$C27, $B29), "", "存在しない") -> 存在しない
J30: =IFERROR(LET(_xlpm.v, VLOOKUP($I30,'用語辞書'!$A:$B,COLUMN('用語辞書'!B$1),FALSE), IF(_xlpm.v=0,"",_xlpm.v) ),"") | L30: =IF(OR(COUNTIF('クラス'!$A$1:$A$1267,$B30)>0,$B30="",$M30=""),"",True) | M30: =IF(COUNTIF($B$1:$C28, $B30), "", "存在しない") -> 存在しない
J31: =IFERROR(LET(_xlpm.v, VLOOKUP($I31,'用語辞書'!$A:$B,COLUMN('用語辞書'!B$1),FALSE), IF(_xlpm.v=0,"",_xlpm.v) ),"") | L31: =IF(OR(COUNTIF('クラス'!$A$1:$A$1267,$B31)>0,$B31="",$M31=""),"",True) | M31: =IF(COUNTIF($B$1:$C29, $B31), "", "存在しない") -> 存在しない
J32: =IFERROR(LET(_xlpm.v, VLOOKUP($I32,'用語辞書'!$A:$B,COLUMN('用語辞書'!B$1),FALSE), IF(_xlpm.v=0,"",_xlpm.v) ),"") | L32: =IF(OR(COUNTIF('クラス'!$A$1:$A$1267,$B32)>0,$B32="",$M32=""),"",True) | M32: =IF(COUNTIF($B$1:$C30, $B32), "", "存在しない") -> 存在しない
J33: =IFERROR(LET(_xlpm.v, VLOOKUP($I33,'用語辞書'!$A:$B,COLUMN('用語辞書'!B$1),FALSE), IF(_xlpm.v=0,"",_xlpm.v) ),"") | L33: =IF(OR(COUNTIF('クラス'!$A$1:$A$1267,$B33)>0,$B33="",$M33=""),"",True) | M33: =IF(COUNTIF($B$1:$C31, $B33), "", "存在しない") -> 存在しない
L34: =IF(OR(COUNTIF('クラス'!$A$1:$A$1267,$B34)>0,$B34="",$M34=""),"",True)
C35: ="------------地形 ------------" -> ------------地形 ------------ | J35: =IFERROR(LET(_xlpm.v, VLOOKUP($I35,'用語辞書'!$A:$B,COLUMN('用語辞書'!B$1),FALSE), IF(_xlpm.v=0,"",_xlpm.v) ),"") | L35: =IF(OR(COUNTIF('クラス'!$A$1:$A$1267,$B35)>0,$B35="",$M35=""),"",True) | M35: =IF(COUNTIF($B$1:$C33, $B35), "", "存在しない") -> 存在しない
B36: 平地 | E36: P | J36: =IFERROR(LET(_xlpm.v, VLOOKUP($I36,'用語辞書'!$A:$B,COLUMN('用語辞書'!B$1),FALSE), IF(_xlpm.v=0,"",_xlpm.v) ),"") | L36: =IF(OR(COUNTIF('クラス'!$A$1:$A$1267,$B36)>0,$B36="",$M36=""),"",True) -> TRUE | M36: =IF(COUNTIF($B$1:$C34, $B36), "", "存在しない") -> 存在しない
B37: 森 | E37: P | J37: =IFERROR(LET(_xlpm.v, VLOOKUP($I37,'用語辞書'!$A:$B,COLUMN('用語辞書'!B$1),FALSE), IF(_xlpm.v=0,"",_xlpm.v) ),"") | L37: =IF(OR(COUNTIF('クラス'!$A$1:$A$1267,$B37)>0,$B37="",$M37=""),"",True) -> TRUE | M37: =IF(COUNTIF($B$1:$C35, $B37), "", "存在しない") -> 存在しない
B38: 山岳 | E38: P | J38: =IFERROR(LET(_xlpm.v, VLOOKUP($I38,'用語辞書'!$A:$B,COLUMN('用語辞書'!B$1),FALSE), IF(_xlpm.v=0,"",_xlpm.v) ),"") | L38: =IF(OR(COUNTIF('クラス'!$A$1:$A$1267,$B38)>0,$B38="",$M38=""),"",True) -> TRUE | M38: =IF(COUNTIF($B$1:$C36, $B38), "", "存在しない") -> 存在しない
B39: 丘陵 | E39: P | J39: =IFERROR(LET(_xlpm.v, VLOOKUP($I39,'用語辞書'!$A:$B,COLUMN('用語辞書'!B$1),FALSE), IF(_xlpm.v=0,"",_xlpm.v) ),"") | L39: =IF(OR(COUNTIF('クラス'!$A$1:$A$1267,$B39)>0,$B39="",$M39=""),"",True) -> TRUE | M39: =IF(COUNTIF($B$1:$C37, $B39), "", "存在しない") -> 存在しない
B40: 河川 | E40: P | J40: =IFERROR(LET(_xlpm.v, VLOOKUP($I40,'用語辞書'!$A:$B,COLUMN('用語辞書'!B$1),FALSE), IF(_xlpm.v=0,"",_xlpm.v) ),"") | L40: =IF(OR(COUNTIF('クラス'!$A$1:$A$1267,$B40)>0,$B40="",$M40=""),"",True) -> TRUE | M40: =IF(COUNTIF($B$1:$C38, $B40), "", "存在しない") -> 存在しない
B41: 湖 | E41: P | J41: =IFERROR(LET(_xlpm.v, VLOOKUP($I41,'用語辞書'!$A:$B,COLUMN('用語辞書'!B$1),FALSE), IF(_xlpm.v=0,"",_xlpm.v) ),"") | L41: =IF(OR(COUNTIF('クラス'!$A$1:$A$1267,$B41)>0,$B41="",$M41=""),"",True) -> TRUE | M41: =IF(COUNTIF($B$1:$C39, $B41), "", "存在しない") -> 存在しない
B42: 海 | E42: P | J42: =IFERROR(LET(_xlpm.v, VLOOKUP($I42,'用語辞書'!$A:$B,COLUMN('用語辞書'!B$1),FALSE), IF(_xlpm.v=0,"",_xlpm.v) ),"") | L42: =IF(OR(COUNTIF('クラス'!$A$1:$A$1267,$B42)>0,$B42="",$M42=""),"",True) -> TRUE | M42: =IF(COUNTIF($B$1:$C40, $B42), "", "存在しない") -> 存在しない
B43: 砂漠 | E43: P | J43: =IFERROR(LET(_xlpm.v, VLOOKUP($I43,'用語辞書'!$A:$B,COLUMN('用語辞書'!B$1),FALSE), IF(_xlpm.v=0,"",_xlpm.v) ),"") | L43: =IF(OR(COUNTIF('クラス'!$A$1:$A$1267,$B43)>0,$B43="",$M43=""),"",True) -> TRUE | M43: =IF(COUNTIF($B$1:$C41, $B43), "", "存在しない") -> 存在しない
B44: 沼地 | E44: P | J44: =IFERROR(LET(_xlpm.v, VLOOKUP($I44,'用語辞書'!$A:$B,COLUMN('用語辞書'!B$1),FALSE), IF(_xlpm.v=0,"",_xlpm.v) ),"") | L44: =IF(OR(COUNTIF('クラス'!$A$1:$A$1267,$B44)>0,$B44="",$M44=""),"",True) -> TRUE | M44: =IF(COUNTIF($B$1:$C42, $B44), "", "存在しない") -> 存在しない
B45: 峡谷 | E45: P | J45: =IFERROR(LET(_xlpm.v, VLOOKUP($I45,'用語辞書'!$A:$B,COLUMN('用語辞書'!B$1),FALSE), IF(_xlpm.v=0,"",_xlpm.v) ),"") | L45: =IF(OR(COUNTIF('クラス'!$A$1:$A$1267,$B45)>0,$B45="",$M45=""),"",True) -> TRUE | M45: =IF(COUNTIF($B$1:$C43, $B45), "", "存在しない") -> 存在しない
B46: 洞窟 | E46: P | J46: =IFERROR(LET(_xlpm.v, VLOOKUP($I46,'用語辞書'!$A:$B,COLUMN('用語辞書'!B$1),FALSE), IF(_xlpm.v=0,"",_xlpm.v) ),"") | L46: =IF(OR(COUNTIF('クラス'!$A$1:$A$1267,$B46)>0,$B46="",$M46=""),"",True) -> TRUE | M46: =IF(COUNTIF($B$1:$C44, $B46), "", "存在しない") -> 存在しない
B47: 雪原 | E47: P | J47: =IFERROR(LET(_xlpm.v, VLOOKUP($I47,'用語辞書'!$A:$B,COLUMN('用語辞書'!B$1),FALSE), IF(_xlpm.v=0,"",_xlpm.v) ),"") | L47: =IF(OR(COUNTIF('クラス'!$A$1:$A$1267,$B47)>0,$B47="",$M47=""),"",True) -> TRUE | M47: =IF(COUNTIF($B$1:$C45, $B47), "", "存在しない") -> 存在しない
... B50: 死の霧 | E50: P | J50: =IFERROR(LET(_xlpm.v, VLOOKUP($I50,'用語辞書'!$A:$B,COLUMN('用語辞書'!B$1),FALSE), IF(_xlpm.v=0,"",_xlpm.v) ),"") | L50: =IF(OR(COUNTIF('クラス'!$A$1:$A$1267,$B50)>0,$B50="",$M50=""),"",True) -> TRUE | M50: =IF(COUNTIF($B$1:$C48, $B50), "", "存在しない") -> 存在しない
J51: =IFERROR(LET(_xlpm.v, VLOOKUP($I51,'用語辞書'!$A:$B,COLUMN('用語辞書'!B$1),FALSE), IF(_xlpm.v=0,"",_xlpm.v) ),"") | L51: =IF(OR(COUNTIF('クラス'!$A$1:$A$1267,$B51)>0,$B51="",$M51=""),"",True) | M51: =IF(COUNTIF($B$1:$C49, $B51), "", "存在しない") -> 存在しない
J52: =IFERROR(LET(_xlpm.v, VLOOKUP($I52,'用語辞書'!$A:$B,COLUMN('用語辞書'!B$1),FALSE), IF(_xlpm.v=0,"",_xlpm.v) ),"") | L52: =IF(OR(COUNTIF('クラス'!$A$1:$A$1267,$B52)>0,$B52="",$M52=""),"",True) | M52: =IF(COUNTIF($B$1:$C50, $B52), "", "存在しない") -> 存在しない
J53: =IFERROR(LET(_xlpm.v, VLOOKUP($I53,'用語辞書'!$A:$B,COLUMN('用語辞書'!B$1),FALSE), IF(_xlpm.v=0,"",_xlpm.v) ),"") | L53: =IF(OR(COUNTIF('クラス'!$A$1:$A$1267,$B53)>0,$B53="",$M53=""),"",True) | M53: =IF(COUNTIF($B$1:$C51, $B53), "", "存在しない") -> 存在しない
J54: =IFERROR(LET(_xlpm.v, VLOOKUP($I54,'用語辞書'!$A:$B,COLUMN('用語辞書'!B$1),FALSE), IF(_xlpm.v=0,"",_xlpm.v) ),"") | L54: =IF(OR(COUNTIF('クラス'!$A$1:$A$1267,$B54)>0,$B54="",$M54=""),"",True) | M54: =IF(COUNTIF($B$1:$C52, $B54), "", "存在しない") -> 存在しない
J55: =IFERROR(LET(_xlpm.v, VLOOKUP($I55,'用語辞書'!$A:$B,COLUMN('用語辞書'!B$1),FALSE), IF(_xlpm.v=0,"",_xlpm.v) ),"") | L55: =IF(OR(COUNTIF('クラス'!$A$1:$A$1267,$B55)>0,$B55="",$M55=""),"",True) | M55: =IF(COUNTIF($B$1:$C53, $B55), "", "存在しない") -> 存在しない
J56: =IFERROR(LET(_xlpm.v, VLOOKUP($I56,'用語辞書'!$A:$B,COLUMN('用語辞書'!B$1),FALSE), IF(_xlpm.v=0,"",_xlpm.v) ),"") | L56: =IF(OR(COUNTIF('クラス'!$A$1:$A$1267,$B56)>0,$B56="",$M56=""),"",True) | M56: =IF(COUNTIF($B$1:$C54, $B56), "", "存在しない") -> 存在しない
J57: =IFERROR(LET(_xlpm.v, VLOOKUP($I57,'用語辞書'!$A:$B,COLUMN('用語辞書'!B$1),FALSE), IF(_xlpm.v=0,"",_xlpm.v) ),"") | L57: =IF(OR(COUNTIF('クラス'!$A$1:$A$1267,$B57)>0,$B57="",$M57=""),"",True) | M57: =IF(COUNTIF($B$1:$C55, $B57), "", "存在しない") -> 存在しない
J58: =IFERROR(LET(_xlpm.v, VLOOKUP($I58,'用語辞書'!$A:$B,COLUMN('用語辞書'!B$1),FALSE), IF(_xlpm.v=0,"",_xlpm.v) ),"") | L58: =IF(OR(COUNTIF('クラス'!$A$1:$A$1267,$B58)>0,$B58="",$M58=""),"",True) | M58: =IF(COUNTIF($B$1:$C56, $B58), "", "存在しない") -> 存在しない
J59: =IFERROR(LET(_xlpm.v, VLOOKUP($I59,'用語辞書'!$A:$B,COLUMN('用語辞書'!B$1),FALSE), IF(_xlpm.v=0,"",_xlpm.v) ),"") | L59: =IF(OR(COUNTIF('クラス'!$A$1:$A$1267,$B59)>0,$B59="",$M59=""),"",True) | M59: =IF(COUNTIF($B$1:$C57, $B59), "", "存在しない") -> 存在しない
L60: =IF(OR(COUNTIF('クラス'!$A$1:$A$1267,$B60)>0,$B60="",$M60=""),"",True)
B61: ジオマンサー | C61: ="------------地形 ------------" -> ------------地形 ------------ | J61: =IFERROR(LET(_xlpm.v, VLOOKUP($I61,'用語辞書'!$A:$B,COLUMN('用語辞書'!B$1),FALSE), IF(_xlpm.v=0,"",_xlpm.v) ),"") | L61: =IF(OR(COUNTIF('クラス'!$A$1:$A$1267,$B61)>0,$B61="",$M61=""),"",True) | M61: =IF(COUNTIF($B$1:$C33, $B61), "", "存在しない") -> 存在しない
A62: 1 | B62: =C62&"化" -> 平地化 | C62: 平地 | E62: A | G62: 50 | H62: ="攻撃手段:魔法 効果:"&C62&"_変換"&" 射程:20" -> 攻撃手段:魔法 効果:平地_変換 射程:20 | J62: =IFERROR(LET(_xlpm.v, VLOOKUP($I62,'用語辞書'!$A:$B,COLUMN('用語辞書'!B$1),FALSE), IF(_xlpm.v=0,"",_xlpm.v) ),"") | L62: =IF(OR(COUNTIF('クラス'!$A$1:$A$1267,$B62)>0,$B62="",$M62=""),"",True) -> TRUE | M62: =IF(COUNTIF($B$1:$C34, $B62), "", "存在しない") -> 存在しない
A63: 2 | B63: =C63&"化" -> 森化 | C63: 森 | E63: A | G63: 50 | H63: ="攻撃手段:魔法 効果:"&C63&"_変換"&" 射程:20" -> 攻撃手段:魔法 効果:森_変換 射程:20 | J63: =IFERROR(LET(_xlpm.v, VLOOKUP($I63,'用語辞書'!$A:$B,COLUMN('用語辞書'!B$1),FALSE), IF(_xlpm.v=0,"",_xlpm.v) ),"") | L63: =IF(OR(COUNTIF('クラス'!$A$1:$A$1267,$B63)>0,$B63="",$M63=""),"",True) -> TRUE | M63: =IF(COUNTIF($B$1:$C61, $B63), "", "存在しない") -> 存在しない
A64: 3 | B64: =C64&"化" -> 山岳化 | C64: 山岳 | E64: A | G64: 50 | H64: ="攻撃手段:魔法 効果:"&C64&"_変換"&" 射程:20" -> 攻撃手段:魔法 効果:山岳_変換 射程:20 | J64: =IFERROR(LET(_xlpm.v, VLOOKUP($I64,'用語辞書'!$A:$B,COLUMN('用語辞書'!B$1),FALSE), IF(_xlpm.v=0,"",_xlpm.v) ),"") | L64: =IF(OR(COUNTIF('クラス'!$A$1:$A$1267,$B64)>0,$B64="",$M64=""),"",True) -> TRUE | M64: =IF(COUNTIF($B$1:$C62, $B64), "", "存在しない") -> 存在しない
A65: 4 | B65: =C65&"化" -> 丘陵化 | C65: 丘陵 | E65: A | G65: 50 | H65: ="攻撃手段:魔法 効果:"&C65&"_変換"&" 射程:20" -> 攻撃手段:魔法 効果:丘陵_変換 射程:20 | J65: =IFERROR(LET(_xlpm.v, VLOOKUP($I65,'用語辞書'!$A:$B,COLUMN('用語辞書'!B$1),FALSE), IF(_xlpm.v=0,"",_xlpm.v) ),"") | L65: =IF(OR(COUNTIF('クラス'!$A$1:$A$1267,$B65)>0,$B65="",$M65=""),"",True) -> TRUE | M65: =IF(COUNTIF($B$1:$C63, $B65), "", "存在しない") -> 存在しない
A66: 5 | B66: =C66&"化" -> 河川化 | C66: 河川 | E66: A | G66: 50 | H66: ="攻撃手段:魔法 効果:"&C66&"_変換"&" 射程:20" -> 攻撃手段:魔法 効果:河川_変換 射程:20 | J66: =IFERROR(LET(_xlpm.v, VLOOKUP($I66,'用語辞書'!$A:$B,COLUMN('用語辞書'!B$1),FALSE), IF(_xlpm.v=0,"",_xlpm.v) ),"") | L66: =IF(OR(COUNTIF('クラス'!$A$1:$A$1267,$B66)>0,$B66="",$M66=""),"",True) -> TRUE | M66: =IF(COUNTIF($B$1:$C64, $B66), "", "存在しない") -> 存在しない
A67: 6 | B67: =C67&"化" -> 湖化 | C67: 湖 | E67: A | G67: 50 | H67: ="攻撃手段:魔法 効果:"&C67&"_変換"&" 射程:20 炸裂:10" -> 攻撃手段:魔法 効果:湖_変換 射程:20 炸裂:10 | J67: =IFERROR(LET(_xlpm.v, VLOOKUP($I67,'用語辞書'!$A:$B,COLUMN('用語辞書'!B$1),FALSE), IF(_xlpm.v=0,"",_xlpm.v) ),"") | L67: =IF(OR(COUNTIF('クラス'!$A$1:$A$1267,$B67)>0,$B67="",$M67=""),"",True) -> TRUE | M67: =IF(COUNTIF($B$1:$C65, $B67), "", "存在しない") -> 存在しない
A68: 7 | B68: =C68&"化" -> 海化 | C68: 海 | E68: A | G68: 50 | H68: ="攻撃手段:魔法 効果:"&C68&"_変換"&" 射程:20" -> 攻撃手段:魔法 効果:海_変換 射程:20 | J68: =IFERROR(LET(_xlpm.v, VLOOKUP($I68,'用語辞書'!$A:$B,COLUMN('用語辞書'!B$1),FALSE), IF(_xlpm.v=0,"",_xlpm.v) ),"") | L68: =IF(OR(COUNTIF('クラス'!$A$1:$A$1267,$B68)>0,$B68="",$M68=""),"",True) -> TRUE | M68: =IF(COUNTIF($B$1:$C66, $B68), "", "存在しない") -> 存在しない
A69: 8 | B69: =C69&"化" -> 砂漠化 | C69: 砂漠 | E69: A | G69: 50 | H69: ="攻撃手段:魔法 効果:"&C69&"_変換"&" 射程:20" -> 攻撃手段:魔法 効果:砂漠_変換 射程:20 | J69: =IFERROR(LET(_xlpm.v, VLOOKUP($I69,'用語辞書'!$A:$B,COLUMN('用語辞書'!B$1),FALSE), IF(_xlpm.v=0,"",_xlpm.v) ),"") | L69: =IF(OR(COUNTIF('クラス'!$A$1:$A$1267,$B69)>0,$B69="",$M69=""),"",True) -> TRUE | M69: =IF(COUNTIF($B$1:$C67, $B69), "", "存在しない") -> 存在しない
A70: 9 | B70: =C70&"化" -> 沼地化 | C70: 沼地 | E70: A | G70: 50 | H70: ="攻撃手段:魔法 効果:"&C70&"_変換"&" 射程:20" -> 攻撃手段:魔法 効果:沼地_変換 射程:20 | J70: =IFERROR(LET(_xlpm.v, VLOOKUP($I70,'用語辞書'!$A:$B,COLUMN('用語辞書'!B$1),FALSE), IF(_xlpm.v=0,"",_xlpm.v) ),"") | L70: =IF(OR(COUNTIF('クラス'!$A$1:$A$1267,$B70)>0,$B70="",$M70=""),"",True) -> TRUE | M70: =IF(COUNTIF($B$1:$C68, $B70), "", "存在しない") -> 存在しない
A71: 10 | B71: =C71&"化" -> 薬草繁茂化 | C71: 薬草繁茂 | E71: A | G71: 50 | H71: ="攻撃手段:魔法 効果:"&C71&"_変換"&" 射程:20" -> 攻撃手段:魔法 効果:薬草繁茂_変換 射程:20 | J71: =IFERROR(LET(_xlpm.v, VLOOKUP($I71,'用語辞書'!$A:$B,COLUMN('用語辞書'!B$1),FALSE), IF(_xlpm.v=0,"",_xlpm.v) ),"") | L71: =IF(OR(COUNTIF('クラス'!$A$1:$A$1267,$B71)>0,$B71="",$M71=""),"",True) -> TRUE | M71: =IF(COUNTIF($B$1:$C69, $B71), "", "存在しない") -> 存在しない
A72: 11 | B72: =C72&"化" -> 峡谷化 | C72: 峡谷 | E72: A | G72: 50 | H72: ="攻撃手段:魔法 効果:"&C72&"_変換"&" 射程:20" -> 攻撃手段:魔法 効果:峡谷_変換 射程:20 | J72: =IFERROR(LET(_xlpm.v, VLOOKUP($I72,'用語辞書'!$A:$B,COLUMN('用語辞書'!B$1),FALSE), IF(_xlpm.v=0,"",_xlpm.v) ),"") | L72: =IF(OR(COUNTIF('クラス'!$A$1:$A$1267,$B72)>0,$B72="",$M72=""),"",True) -> TRUE | M72: =IF(COUNTIF($B$1:$C70, $B72), "", "存在しない") -> 存在しない
A73: 12 | B73: =C73&"化" -> 洞窟化 | C73: 洞窟 | E73: A | G73: 50 | H73: ="攻撃手段:魔法 効果:"&C73&"_変換"&" 射程:20" -> 攻撃手段:魔法 効果:洞窟_変換 射程:20 | J73: =IFERROR(LET(_xlpm.v, VLOOKUP($I73,'用語辞書'!$A:$B,COLUMN('用語辞書'!B$1),FALSE), IF(_xlpm.v=0,"",_xlpm.v) ),"") | L73: =IF(OR(COUNTIF('クラス'!$A$1:$A$1267,$B73)>0,$B73="",$M73=""),"",True) -> TRUE | M73: =IF(COUNTIF($B$1:$C71, $B73), "", "存在しない") -> 存在しない
A74: 13 | B74: =C74&"化" -> 雪原化 | C74: 雪原 | E74: A | G74: 50 | H74: ="攻撃手段:魔法 効果:"&C74&"_変換"&" 射程:20" -> 攻撃手段:魔法 効果:雪原_変換 射程:20 | J74: =IFERROR(LET(_xlpm.v, VLOOKUP($I74,'用語辞書'!$A:$B,COLUMN('用語辞書'!B$1),FALSE), IF(_xlpm.v=0,"",_xlpm.v) ),"") | L74: =IF(OR(COUNTIF('クラス'!$A$1:$A$1267,$B74)>0,$B74="",$M74=""),"",True) -> TRUE | M74: =IF(COUNTIF($B$1:$C72, $B74), "", "存在しない") -> 存在しない
A75: 14 | B75: =C75&"化" -> 火山化 | C75: 火山 | E75: A | G75: 50 | H75: ="攻撃手段:魔法 効果:"&C75&"_変換"&" 射程:20" -> 攻撃手段:魔法 効果:火山_変換 射程:20 | J75: =IFERROR(LET(_xlpm.v, VLOOKUP($I75,'用語辞書'!$A:$B,COLUMN('用語辞書'!B$1),FALSE), IF(_xlpm.v=0,"",_xlpm.v) ),"") | L75: =IF(OR(COUNTIF('クラス'!$A$1:$A$1267,$B75)>0,$B75="",$M75=""),"",True) -> TRUE | M75: =IF(COUNTIF($B$1:$C73, $B75), "", "存在しない") -> 存在しない
A76: 15 | B76: =C76&"化" -> 溶岩化 | C76: 溶岩 | E76: A | G76: 50 | H76: ="攻撃手段:魔法 効果:"&C76&"_変換"&" 射程:20" -> 攻撃手段:魔法 効果:溶岩_変換 射程:20 | J76: =IFERROR(LET(_xlpm.v, VLOOKUP($I76,'用語辞書'!$A:$B,COLUMN('用語辞書'!B$1),FALSE), IF(_xlpm.v=0,"",_xlpm.v) ),"") | L76: =IF(OR(COUNTIF('クラス'!$A$1:$A$1267,$B76)>0,$B76="",$M76=""),"",True) -> TRUE | M76: =IF(COUNTIF($B$1:$C74, $B76), "", "存在しない") -> 存在しない
A77: 16 | B77: =C77&"化" -> 死の霧化 | C77: 死の霧 | E77: A | G77: 50 | H77: ="攻撃手段:魔法 効果:"&C77&"_変換"&" 射程:20" -> 攻撃手段:魔法 効果:死の霧_変換 射程:20 | J77: =IFERROR(LET(_xlpm.v, VLOOKUP($I77,'用語辞書'!$A:$B,COLUMN('用語辞書'!B$1),FALSE), IF(_xlpm.v=0,"",_xlpm.v) ),"") | L77: =IF(OR(COUNTIF('クラス'!$A$1:$A$1267,$B77)>0,$B77="",$M77=""),"",True) -> TRUE | M77: =IF(COUNTIF($B$1:$C75, $B77), "", "存在しない") -> 存在しない
J78: =IFERROR(LET(_xlpm.v, VLOOKUP($I78,'用語辞書'!$A:$B,COLUMN('用語辞書'!B$1),FALSE), IF(_xlpm.v=0,"",_xlpm.v) ),"") | L78: =IF(OR(COUNTIF('クラス'!$A$1:$A$1267,$B78)>0,$B78="",$M78=""),"",True) | M78: =IF(COUNTIF($B$1:$C76, $B78), "", "存在しない") -> 存在しない
J79: =IFERROR(LET(_xlpm.v, VLOOKUP($I79,'用語辞書'!$A:$B,COLUMN('用語辞書'!B$1),FALSE), IF(_xlpm.v=0,"",_xlpm.v) ),"") | L79: =IF(OR(COUNTIF('クラス'!$A$1:$A$1267,$B79)>0,$B79="",$M79=""),"",True) | M79: =IF(COUNTIF($B$1:$C77, $B79), "", "存在しない") -> 存在しない
J80: =IFERROR(LET(_xlpm.v, VLOOKUP($I80,'用語辞書'!$A:$B,COLUMN('用語辞書'!B$1),FALSE), IF(_xlpm.v=0,"",_xlpm.v) ),"") | L80: =IF(OR(COUNTIF('クラス'!$A$1:$A$1267,$B80)>0,$B80="",$M80=""),"",True) | M80: =IF(COUNTIF($B$1:$C78, $B80), "", "存在しない") -> 存在しない
J81: =IFERROR(LET(_xlpm.v, VLOOKUP($I81,'用語辞書'!$A:$B,COLUMN('用語辞書'!B$1),FALSE), IF(_xlpm.v=0,"",_xlpm.v) ),"") | L81: =IF(OR(COUNTIF('クラス'!$A$1:$A$1267,$B81)>0,$B81="",$M81=""),"",True) | M81: =IF(COUNTIF($B$1:$C79, $B81), "", "存在しない") -> 存在しない
J82: =IFERROR(LET(_xlpm.v, VLOOKUP($I82,'用語辞書'!$A:$B,COLUMN('用語辞書'!B$1),FALSE), IF(_xlpm.v=0,"",_xlpm.v) ),"") | L82: =IF(OR(COUNTIF('クラス'!$A$1:$A$1267,$B82)>0,$B82="",$M82=""),"",True) | M82: =IF(COUNTIF($B$1:$C80, $B82), "", "存在しない") -> 存在しない
J83: =IFERROR(LET(_xlpm.v, VLOOKUP($I83,'用語辞書'!$A:$B,COLUMN('用語辞書'!B$1),FALSE), IF(_xlpm.v=0,"",_xlpm.v) ),"") | L83: =IF(OR(COUNTIF('クラス'!$A$1:$A$1267,$B83)>0,$B83="",$M83=""),"",True) | M83: =IF(COUNTIF($B$1:$C81, $B83), "", "存在しない") -> 存在しない
J84: =IFERROR(LET(_xlpm.v, VLOOKUP($I84,'用語辞書'!$A:$B,COLUMN('用語辞書'!B$1),FALSE), IF(_xlpm.v=0,"",_xlpm.v) ),"") | L84: =IF(OR(COUNTIF('クラス'!$A$1:$A$1267,$B84)>0,$B84="",$M84=""),"",True) | M84: =IF(COUNTIF($B$1:$C82, $B84), "", "存在しない") -> 存在しない
J85: =IFERROR(LET(_xlpm.v, VLOOKUP($I85,'用語辞書'!$A:$B,COLUMN('用語辞書'!B$1),FALSE), IF(_xlpm.v=0,"",_xlpm.v) ),"") | L85: =IF(OR(COUNTIF('クラス'!$A$1:$A$1267,$B85)>0,$B85="",$M85=""),"",True) | M85: =IF(COUNTIF($B$1:$C83, $B85), "", "存在しない") -> 存在しない
L86: =IF(OR(COUNTIF('クラス'!$A$1:$A$1267,$B86)>0,$B86="",$M86=""),"",True)
C87: ============魔法一覧============ | L87: =IF(OR(COUNTIF('クラス'!$A$1:$A$1267,$B87)>0,$B87="",$M87=""),"",True) | M87: =IF(COUNTIF(#REF!, $B87), "", "存在しない") -> 存在しない
C88: ------------力場魔法 ------------ | L88: =IF(OR(COUNTIF('クラス'!$A$1:$A$1267,$B88)>0,$B88="",$M88=""),"",True) | M88: =IF(COUNTIF(#REF!, $B88), "", "存在しない") -> 存在しない
A89: 1 | B89: 力場弾 | C89: フォース・ショット | D89: 力場 | E89: A | G89: 60 | H89: 攻撃手段:魔法 特殊:攻撃 力場+24 効果:必中 射程:10 判定:魔力 | J89: 魔法による、射程1。 | L89: =IF(OR(COUNTIF('クラス'!$A$1:$A$1267,$B89)>0,$B89="",$M89=""),"",True) -> TRUE | M89: =IF(COUNTIF(#REF!, $B89), "", "存在しない") -> 存在しない
A90: 1 | B90: 盾 | C90: シールド | D90: 防御 | E90: A | G90: 60 | H90: 攻撃手段:魔法 特殊:攻撃 効果時間3t 物理ガード+10 魔法ガード+15 遠隔軽減+10 追加威力:魔力 | J90: 3ターンの間、物理ガードと魔法ガードを上昇させ、遠隔攻撃を軽減する防御効果。 | L90: =IF(OR(COUNTIF('クラス'!$A$1:$A$1267,$B90)>0,$B90="",$M90=""),"",True) -> TRUE | M90: =IF(COUNTIF(#REF!, $B90), "", "存在しない") -> 存在しない
A91: 2 | B91: 浮床 | C91: フォース・ステップ | D91: 力場 | E91: A | G91: 60 | J91: 足場として使用できる薄い力場面を空中へ固定する。 | L91: =IF(OR(COUNTIF('クラス'!$A$1:$A$1267,$B91)>0,$B91="",$M91=""),"",True) -> TRUE | M91: =IF(COUNTIF(#REF!, $B91), "", "存在しない") -> 存在しない
A92: 2 | B92: 衝圧波 | C92: フォース・ウェーブ | D92: 力場 | E92: A | G92: 60 | H92: 攻撃手段:魔法 特殊:攻撃 力場+40 射程:10 判定:魔力 | J92: 魔法による、射程1。 | L92: =IF(OR(COUNTIF('クラス'!$A$1:$A$1267,$B92)>0,$B92="",$M92=""),"",True) -> TRUE | M92: =IF(COUNTIF(#REF!, $B92), "", "存在しない") -> 存在しない
A93: 3 | B93: 圧拳 | C93: フォース・フィスト | D93: 力場 | E93: A | G93: 60 | H93: 攻撃手段:魔法 特殊:攻撃 力場+65 射程:0 判定:魔力 | J93: 魔法による、射程0。 | L93: =IF(OR(COUNTIF('クラス'!$A$1:$A$1267,$B93)>0,$B93="",$M93=""),"",True) -> TRUE | M93: =IF(COUNTIF(#REF!, $B93), "", "存在しない") -> 存在しない
A94: 3 | B94: 硬盾 | C94: ハードシールド | D94: 防御 | E94: A | G94: 60 | H94: 攻撃手段:魔法 特殊:攻撃 効果時間3t 物理ガード+15 魔法ガード+20 遠隔軽減+15 追加威力:魔力 | J94: 3ターンの間、物理ガードと魔法ガードを上昇させ、遠隔攻撃を強く軽減する防御効果。 | L94: =IF(OR(COUNTIF('クラス'!$A$1:$A$1267,$B94)>0,$B94="",$M94=""),"",True) -> TRUE | M94: =IF(COUNTIF(#REF!, $B94), "", "存在しない") -> 存在しない
A95: 4 | B95: 偏向膜 | C95: ディフレクター | D95: 力場 | E95: A | G95: 60 | J95: 斜めの力場面を形成し、飛来物や攻撃の進行方向を逸らす。 | L95: =IF(OR(COUNTIF('クラス'!$A$1:$A$1267,$B95)>0,$B95="",$M95=""),"",True) -> TRUE | M95: =IF(COUNTIF(#REF!, $B95), "", "存在しない") -> 存在しない
A96: 4 | B96: 拘束界 | C96: フォース・ケージ | D96: 力場 | E96: A | G96: 60 | J96: 対象の周囲へ閉鎖した力場面を形成し、移動を封じる。 | L96: =IF(OR(COUNTIF('クラス'!$A$1:$A$1267,$B96)>0,$B96="",$M96=""),"",True) -> TRUE | M96: =IF(COUNTIF(#REF!, $B96), "", "存在しない") -> 存在しない
A97: 4 | B97: 場断裂 | C97: フォース・クラック | D97: 力場 | E97: A | G97: 60 | H97: 攻撃手段:魔法 特殊:攻撃 力場+65 射程:10 範囲:周囲 判定:魔力 | J97: 魔法による、射程1。周囲の敵に効果が及ぶ。 | L97: =IF(OR(COUNTIF('クラス'!$A$1:$A$1267,$B97)>0,$B97="",$M97=""),"",True) -> TRUE | M97: =IF(COUNTIF(#REF!, $B97), "", "存在しない") -> 存在しない
A98: 5 | B98: 衝圧 | C98: フォース・インパクト | D98: 力場 | E98: A | G98: 60 | H98: 攻撃手段:魔法 特殊:攻撃 力場+80 体幹+65 射程:10 範囲:周囲 効果:吹き飛ばし 判定:魔力 | J98: 魔法による、射程1。周囲の敵に効果が及ぶ。 | L98: =IF(OR(COUNTIF('クラス'!$A$1:$A$1267,$B98)>0,$B98="",$M98=""),"",True) -> TRUE | M98: =IF(COUNTIF(#REF!, $B98), "", "存在しない") -> 存在しない
A99: 6 | B99: 分解 | C99: ディスインテグレイト | D99: 力場 | E99: A | G99: 60 | H99: 攻撃手段:魔法 特殊:攻撃 力場+100 効果:即死 射程:20 範囲:縦 判定:魔力 | J99: 魔法による、射程2。縦一列の敵を攻撃する。 | L99: =IF(OR(COUNTIF('クラス'!$A$1:$A$1267,$B99)>0,$B99="",$M99=""),"",True) -> TRUE | M99: =IF(COUNTIF(#REF!, $B99), "", "存在しない") -> 存在しない
A100: 7 | B100: 圧縮界 | C100: コンプレッション・フィールド | D100: 力場 | E100: A | G100: 60 | J100: 広い範囲へ展開した力場を一点へ圧縮し、内部の対象へ強大な圧力を加える。 | L100: =IF(OR(COUNTIF('クラス'!$A$1:$A$1267,$B100)>0,$B100="",$M100=""),"",True) -> TRUE | M100: =IF(COUNTIF(#REF!, $B100), "", "存在しない") -> 存在しない
A101: 7 | B101: 圧壊掌 | C101: クラッシング・ハンド | D101: 力場 | E101: A | G101: 60 | H101: 攻撃手段:魔法 特殊:攻撃 力場+125 拘束+75 射程:10 判定:魔力 | J101: 魔法による、射程1。 | L101: =IF(OR(COUNTIF('クラス'!$A$1:$A$1267,$B101)>0,$B101="",$M101=""),"",True) -> TRUE | M101: =IF(COUNTIF(#REF!, $B101), "", "存在しない") -> 存在しない
C102: ------------魔術魔法 ------------ | L102: =IF(OR(COUNTIF('クラス'!$A$1:$A$1267,$B102)>0,$B102="",$M102=""),"",True) | M102: =IF(COUNTIF(#REF!, $B102), "", "存在しない") -> 存在しない
...

Sheet クラス
A1: 名前 | B1: ルビ | C1: 種類 | D1: 合計 | E1: Tire | F1: HP | G1: MP | H1: ST | I1: 攻撃 | J1: 防御 | K1: 魔力 | L1: 精神 | M1: 速度 | N1: 命中 | O1: SIZ | P1: APP | Q1: 物理耐性 | R1: 魔法耐性 | S1: 射撃耐性 | T1: 切断耐性 | U1: 貫通耐性 | V1: 打撃耐性 | W1: 炎耐性 | X1: 氷耐性 | Y1: 雷耐性 | Z1: 毒耐性 | AA1: 光耐性 | AB1: 闇耐性 | AC1: 精神耐性 | AD1: 怯み耐性 | AE1: 出血耐性 | AF1: 拘束耐性 | AG1: 幻覚耐性 | AH1: Cr率耐性 | AI1: Cr威力耐性 | AJ1: 指揮 | AK1: 威圧 | AL1: 看破 | AM1: 早業 | AN1: 技術 | AO1: 変装 | AP1: 飛行 | AQ1: 隠密 | AR1: 索敵 | AS1: 農業 | AT1: 林業 | AU1: 漁業 | AV1: 工業 | AW1: 統治 | AX1: 交渉 | AY1: 魔術 | AZ1: 信仰 | BA1: 角 | BB1: 牙 | BC1: 爪 | BD1: 尾 | BE1: 翼 | BF1: 装甲 | BG1: Skill1 | BH1: Skill2 | BI1: Skill3 | BJ1: Skill4 | BK1: Skill5 | BL1: Skill6 | BM1: Skill7 | BN1: Skill8 | BO1: Skill9 | BP1: Skill10 | BQ1: 合計Lv | BR1: 条件クラス | BS1: 条件スキル | BT1: 条件施設 | BU1: 詳細 | BV1: 増加条件 | BW1: コスト | BX1: 穀物 | BY1: 野菜 | BZ1: 肉 | CA1: 魚 | CB1: 魂 | CC1: 死体 | CD1: 脚数 | CE1: 環境 | CF1: 装備枠 | CG1: 武器1 | CH1: 武器2 | CI1: 頭 | CJ1: 体 | CK1: 足 | CL1: 装飾1 | CM1: 装飾2 | CN1: 画像ID | CO1: 適正土地 | CP1: 苦手土地 | CQ1: 必要正魂APP | CR1: 必要負魂APP
Q2: 50 | R2: 51 | T2: 52 | U2: 53 | V2: 54 | W2: 52 | X2: 53 | Y2: 54 | Z2: 55 | AA2: 56 | AB2: 57 | AC2: 58 | AD2: 59 | AE2: 60 | AF2: 61 | AG2: 62 | AH2: 63 | AI2: 64 | AJ2: 指揮 | AK2: 部隊への命令効率を高める。士気上昇量やバフ効果量が増加し、部隊スキルの性能が向上する。
AJ3: 威圧 | AK3: 騙すを併合。敵やNPCに心理的圧力を与える。敵士気低下や怯え付与、会話時の威圧成功率が上昇する。
AJ4: 看破 | AK4: 知識を含む。敵能力・弱点・嘘・罠・アイテムの性質を見破る。不意打ち耐性や情報取得能力が向上する。
AJ5: 早業 | AK5: 軽業を併合。攻撃速度や回避率が上昇し、移動系スキルの消費が軽減される。連撃性能が向上する。
AJ6: 技術 | AK6: 装置操作・罠設置・修理・制作補助能力。戦闘中のトラップ性能や道具効果が向上する。
AJ7: 隠密 | AK7: 発見されにくくなる。奇襲成功率や離脱成功率が上昇し、不意打ち時の威力が増加する。
AJ8: 索敵 | AK8: 敵や資源を発見しやすくなる。遭遇率制御、罠発見、危険察知能力が向上する。
AJ9: 農業 | AK9: 穀物・家畜など農業生産効率を上昇させる。災害による収穫減少を軽減する。
AJ10: 林業 | AK10: 木材資源の取得量と森林管理効率を上昇させる。森林枯渇速度を軽減する。
AJ11: 漁業 | AK11: 水域資源の取得量を上昇させる。食料安定度に補正を与える。
AJ12: 工業 | AK12: 加工・生産効率を上昇させる。装備や施設の生産速度が向上する。
AJ13: 統治 | AK13: 都市安定度や治安を向上させる。反乱発生率を低下させ、維持費効率を改善する。
AJ14: 交渉 | AK14: 交易価格や外交成功率を上昇させる。条約締結や取引条件が有利になる。
... AJ16: 信仰 | AK16: 宗教効果や祝福系能力を強化する。士気回復や精神耐性補正が向上する。
BW17: 種族 | BX17: 穀物 | BY17: 野菜 | BZ17: 肉 | CA17: 魚
A18: ヒューマン | C18: 人族 | D18: =SUM(AJ18:AZ18,F18:N18)&"/"&SUM(F18:N18)&"/"&SUM(AJ18:AZ18) -> 775/460/315 | E18: 1 | F18: 75 | I18: 70 | J18: 70 | K18: 25 | L18: 70 | M18: 70 | N18: 80 | O18: 170 | P18: 0 | AJ18: 35 | AK18: 35 | AL18: 35 | AM18: 35 | AN18: 35 | AO18: 0 | AP18: 0 | AQ18: 35 | AR18: 35 | AS18: 0 | AT18: 0 | AU18: 0 | AV18: 0 | AW18: 35 | AX18: 35 | AY18: 0 | AZ18: 0 | BA18: 0 | BB18: 0 | BC18: 0 | BD18: 0 | BE18: 0 | BF18: 0 | BG18: {=IF($A18="","", INDEX(CS!$B$1:$B$15026,MATCH($A18,CS!$B:$B,0)+COLUMN(A$1),1))} | BH18: {=IF($A18="","", INDEX(CS!$B$1:$B$15026,MATCH($A18,CS!$B:$B,0)+COLUMN(B$1),1))} | BI18: {=IF($A18="","", INDEX(CS!$B$1:$B$15026,MATCH($A18,CS!$B:$B,0)+COLUMN(C$1),1))} | BJ18: {=IF($A18="","", INDEX(CS!$B$1:$B$15026,MATCH($A18,CS!$B:$B,0)+COLUMN(D$1),1))} | BK18: {=IF($A18="","", INDEX(CS!$B$1:$B$15026,MATCH($A18,CS!$B:$B,0)+COLUMN(E$1),1))} | BL18: {=IF($A18="","", INDEX(CS!$B$1:$B$15026,MATCH($A18,CS!$B:$B,0)+COLUMN(F$1),1))} | BM18: {=IF($A18="","", INDEX(CS!$B$1:$B$15026,MATCH($A18,CS!$B:$B,0)+COLUMN(G$1),1))} | BN18: {=IF($A18="","", INDEX(CS!$B$1:$B$15026,MATCH($A18,CS!$B:$B,0)+COLUMN(H$1),1))} | ... BP18: {=IF($A18="","", INDEX(CS!$B$1:$B$15026,MATCH($A18,CS!$B:$B,0)+COLUMN(J$1),1))} | BV18: 食事 | BW18: 100 | BX18: 40 | BY18: 30 | BZ18: 20 | CA18: 10 | CD18: 2 | CN18: 只人 | CO18: ["平地","河川"]
A19: エルフ | C19: 人族 | D19: =SUM(AJ19:AZ19,F19:N19)&"/"&SUM(F19:N19)&"/"&SUM(AJ19:AZ19) -> 775/460/315 | E19: 1 | F19: 65 | I19: 65 | J19: 70 | K19: 25 | L19: 70 | M19: 85 | N19: 80 | O19: 170 | P19: 0 | AJ19: 35 | AK19: 0 | AL19: 35 | AM19: 35 | AN19: 0 | AO19: 0 | AP19: 0 | AQ19: 35 | AR19: 35 | AS19: 35 | AT19: 35 | AU19: 0 | AV19: 0 | AW19: 0 | AX19: 0 | AY19: 35 | AZ19: 35 | BA19: 0 | BB19: 0 | BC19: 0 | BD19: 0 | BE19: 0 | BF19: 0 | BG19: {=IF($A19="","", INDEX(CS!$B$1:$B$15026,MATCH($A19,CS!$B:$B,0)+COLUMN(A$1),1))} | BH19: {=IF($A19="","", INDEX(CS!$B$1:$B$15026,MATCH($A19,CS!$B:$B,0)+COLUMN(B$1),1))} | BI19: {=IF($A19="","", INDEX(CS!$B$1:$B$15026,MATCH($A19,CS!$B:$B,0)+COLUMN(C$1),1))} | BJ19: {=IF($A19="","", INDEX(CS!$B$1:$B$15026,MATCH($A19,CS!$B:$B,0)+COLUMN(D$1),1))} | BK19: {=IF($A19="","", INDEX(CS!$B$1:$B$15026,MATCH($A19,CS!$B:$B,0)+COLUMN(E$1),1))} | BL19: {=IF($A19="","", INDEX(CS!$B$1:$B$15026,MATCH($A19,CS!$B:$B,0)+COLUMN(F$1),1))} | BM19: {=IF($A19="","", INDEX(CS!$B$1:$B$15026,MATCH($A19,CS!$B:$B,0)+COLUMN(G$1),1))} | BN19: {=IF($A19="","", INDEX(CS!$B$1:$B$15026,MATCH($A19,CS!$B:$B,0)+COLUMN(H$1),1))} | ... BP19: {=IF($A19="","", INDEX(CS!$B$1:$B$15026,MATCH($A19,CS!$B:$B,0)+COLUMN(J$1),1))} | BV19: 食事 | BW19: 100 | BX19: 20 | BY19: 50 | BZ19: 10 | CA19: 20 | CD19: 2 | CN19: 森人 | CO19: ["森"] | CP19: ["荒野","砂漠","火山"]
A20: ドワーフ | C20: 人族 | D20: =SUM(AJ20:AZ20,F20:N20)&"/"&SUM(F20:N20)&"/"&SUM(AJ20:AZ20) -> 775/460/315 | E20: 1 | F20: 85 | I20: 80 | J20: 80 | K20: 25 | L20: 60 | M20: 50 | N20: 80 | O20: 140 | P20: 0 | AJ20: 35 | AK20: 35 | AL20: 35 | AM20: 0 | AN20: 70 | AO20: 0 | AP20: 0 | AQ20: 0 | AR20: 35 | AS20: 0 | AT20: 0 | AU20: 0 | AV20: 70 | AW20: 35 | AX20: 0 | AY20: 0 | AZ20: 0 | BA20: 0 | BB20: 0 | BC20: 0 | BD20: 0 | BE20: 0 | BF20: 0 | BG20: {=IF($A20="","", INDEX(CS!$B$1:$B$15026,MATCH($A20,CS!$B:$B,0)+COLUMN(A$1),1))} | BH20: {=IF($A20="","", INDEX(CS!$B$1:$B$15026,MATCH($A20,CS!$B:$B,0)+COLUMN(B$1),1))} | BI20: {=IF($A20="","", INDEX(CS!$B$1:$B$15026,MATCH($A20,CS!$B:$B,0)+COLUMN(C$1),1))} | BJ20: {=IF($A20="","", INDEX(CS!$B$1:$B$15026,MATCH($A20,CS!$B:$B,0)+COLUMN(D$1),1))} | BK20: {=IF($A20="","", INDEX(CS!$B$1:$B$15026,MATCH($A20,CS!$B:$B,0)+COLUMN(E$1),1))} | BL20: {=IF($A20="","", INDEX(CS!$B$1:$B$15026,MATCH($A20,CS!$B:$B,0)+COLUMN(F$1),1))} | BM20: {=IF($A20="","", INDEX(CS!$B$1:$B$15026,MATCH($A20,CS!$B:$B,0)+COLUMN(G$1),1))} | BN20: {=IF($A20="","", INDEX(CS!$B$1:$B$15026,MATCH($A20,CS!$B:$B,0)+COLUMN(H$1),1))} | ... BP20: {=IF($A20="","", INDEX(CS!$B$1:$B$15026,MATCH($A20,CS!$B:$B,0)+COLUMN(J$1),1))} | BV20: 食事 | BW20: 100 | BX20: 30 | BY20: 20 | BZ20: 40 | CA20: 10 | CD20: 2 | CN20: 土人 | CO20: ["丘陵","山岳","洞窟"] | CP20: ["沼地","湿地"]
D21: =SUM(AJ21:AZ21,F21:N21)&"/"&SUM(F21:N21)&"/"&SUM(AJ21:AZ21) -> 0/0/0 | BG21: {=IF($A21="","", INDEX(CS!$B$1:$B$15026,MATCH($A21,CS!$B:$B,0)+COLUMN(A$1),1))} | BH21: {=IF($A21="","", INDEX(CS!$B$1:$B$15026,MATCH($A21,CS!$B:$B,0)+COLUMN(B$1),1))} | BI21: {=IF($A21="","", INDEX(CS!$B$1:$B$15026,MATCH($A21,CS!$B:$B,0)+COLUMN(C$1),1))} | BJ21: {=IF($A21="","", INDEX(CS!$B$1:$B$15026,MATCH($A21,CS!$B:$B,0)+COLUMN(D$1),1))} | BK21: {=IF($A21="","", INDEX(CS!$B$1:$B$15026,MATCH($A21,CS!$B:$B,0)+COLUMN(E$1),1))} | BL21: {=IF($A21="","", INDEX(CS!$B$1:$B$15026,MATCH($A21,CS!$B:$B,0)+COLUMN(F$1),1))} | BM21: {=IF($A21="","", INDEX(CS!$B$1:$B$15026,MATCH($A21,CS!$B:$B,0)+COLUMN(G$1),1))} | BN21: {=IF($A21="","", INDEX(CS!$B$1:$B$15026,MATCH($A21,CS!$B:$B,0)+COLUMN(H$1),1))} | ... BP21: {=IF($A21="","", INDEX(CS!$B$1:$B$15026,MATCH($A21,CS!$B:$B,0)+COLUMN(J$1),1))}
A22: ビーストマン | C22: 亜人 | D22: =SUM(AJ22:AZ22,F22:N22)&"/"&SUM(F22:N22)&"/"&SUM(AJ22:AZ22) -> 710/490/220 | E22: 1 | F22: 85 | I22: 85 | J22: 65 | K22: 35 | L22: 50 | M22: 100 | N22: 70 | P22: 0 | AC22: -20 | AD22: 10 | AF22: 10 | AJ22: 0 | AK22: 50 | AL22: 0 | AM22: 50 | AN22: 0 | AO22: 0 | AP22: 0 | AQ22: 70 | AR22: 50 | AS22: 0 | AT22: 0 | AU22: 0 | AV22: 0 | AW22: 0 | AX22: 0 | AY22: 0 | AZ22: 0 | BA22: 0 | BB22: 60 | BC22: 70 | BD22: 0 | BE22: 0 | BF22: 20 | BG22: {=IF($A22="","", INDEX(CS!$B$1:$B$15026,MATCH($A22,CS!$B:$B,0)+COLUMN(A$1),1))} -> 爪 | BH22: {=IF($A22="","", INDEX(CS!$B$1:$B$15026,MATCH($A22,CS!$B:$B,0)+COLUMN(B$1),1))} -> 牙 | BI22: {=IF($A22="","", INDEX(CS!$B$1:$B$15026,MATCH($A22,CS!$B:$B,0)+COLUMN(C$1),1))} -> 野生感覚 | BJ22: {=IF($A22="","", INDEX(CS!$B$1:$B$15026,MATCH($A22,CS!$B:$B,0)+COLUMN(D$1),1))} | BK22: {=IF($A22="","", INDEX(CS!$B$1:$B$15026,MATCH($A22,CS!$B:$B,0)+COLUMN(E$1),1))} -> 獣の身軽さ | BL22: {=IF($A22="","", INDEX(CS!$B$1:$B$15026,MATCH($A22,CS!$B:$B,0)+COLUMN(F$1),1))} | BM22: {=IF($A22="","", INDEX(CS!$B$1:$B$15026,MATCH($A22,CS!$B:$B,0)+COLUMN(G$1),1))} -> 獣性 | BN22: {=IF($A22="","", INDEX(CS!$B$1:$B$15026,MATCH($A22,CS!$B:$B,0)+COLUMN(H$1),1))} | ... BP22: {=IF($A22="","", INDEX(CS!$B$1:$B$15026,MATCH($A22,CS!$B:$B,0)+COLUMN(J$1),1))} -> 獣の本能 | BV22: 食事 | BW22: 110 | BX22: 20 | BY22: 20 | BZ22: 50 | CA22: 20 | CD22: 2 | CN22: 獣人 | CO22: ["森","荒野"]
A23: ドラゴニュート | C23: 亜人 | D23: =SUM(AJ23:AZ23,F23:N23)&"/"&SUM(F23:N23)&"/"&SUM(AJ23:AZ23) -> 710/490/220 | E23: 1 | F23: 90 | I23: 90 | J23: 75 | K23: 35 | L23: 70 | M23: 55 | N23: 75 | O23: 170 | P23: 0 | Q23: 5 | R23: 5 | AD23: 15 | AG23: -15 | AJ23: 0 | AK23: 75 | AL23: 45 | AM23: 25 | AN23: 0 | AO23: 0 | AP23: 0 | AQ23: 0 | AR23: 50 | AS23: 0 | AT23: 0 | AU23: 0 | AV23: 0 | AW23: 0 | AX23: 0 | AY23: 25 | AZ23: 0 | BA23: 0 | BB23: 100 | BC23: 90 | BD23: 80 | BE23: 0 | BF23: 100 | BG23: {=IF($A23="","", INDEX(CS!$B$1:$B$15026,MATCH($A23,CS!$B:$B,0)+COLUMN(A$1),1))} -> 牙 | BH23: {=IF($A23="","", INDEX(CS!$B$1:$B$15026,MATCH($A23,CS!$B:$B,0)+COLUMN(B$1),1))} -> 爪 | BI23: {=IF($A23="","", INDEX(CS!$B$1:$B$15026,MATCH($A23,CS!$B:$B,0)+COLUMN(C$1),1))} -> 尾 | BJ23: {=IF($A23="","", INDEX(CS!$B$1:$B$15026,MATCH($A23,CS!$B:$B,0)+COLUMN(D$1),1))} | BK23: {=IF($A23="","", INDEX(CS!$B$1:$B$15026,MATCH($A23,CS!$B:$B,0)+COLUMN(E$1),1))} -> 竜鱗 | BL23: {=IF($A23="","", INDEX(CS!$B$1:$B$15026,MATCH($A23,CS!$B:$B,0)+COLUMN(F$1),1))} | BM23: {=IF($A23="","", INDEX(CS!$B$1:$B$15026,MATCH($A23,CS!$B:$B,0)+COLUMN(G$1),1))} -> 竜人の咆哮 | BN23: {=IF($A23="","", INDEX(CS!$B$1:$B$15026,MATCH($A23,CS!$B:$B,0)+COLUMN(H$1),1))} | ... BP23: {=IF($A23="","", INDEX(CS!$B$1:$B$15026,MATCH($A23,CS!$B:$B,0)+COLUMN(J$1),1))} -> 竜の肉体 | BV23: 食事 | BW23: 110 | BX23: 15 | BY23: 10 | BZ23: 70 | CA23: 15 | CD23: 2 | CN23: 竜人 | CO23: ["山岳","火山"] | CP23: ["雪原"]
A24: オーガ | C24: 亜人 | D24: =SUM(AJ24:AZ24,F24:N24)&"/"&SUM(F24:N24)&"/"&SUM(AJ24:AZ24) -> 710/490/220 | E24: 1 | F24: 110 | I24: 105 | J24: 65 | K24: 50 | L24: 45 | M24: 55 | N24: 60 | O24: 300 | P24: -25 | W24: 10 | AC24: -15 | AD24: 15 | AG24: -15 | AJ24: 20 | AK24: 100 | AL24: 25 | AM24: -30 | AN24: -25 | AO24: 0 | AP24: 0 | AQ24: 25 | AR24: 25 | AS24: 0 | AT24: 0 | AU24: 0 | AV24: 0 | AW24: 25 | AX24: 15 | AY24: 40 | AZ24: 0 | BA24: 0 | BB24: 0 | BC24: 0 | BD24: 0 | BE24: 0 | BF24: 20 | BG24: {=IF($A24="","", INDEX(CS!$B$1:$B$15026,MATCH($A24,CS!$B:$B,0)+COLUMN(A$1),1))} -> 豪腕 | BH24: {=IF($A24="","", INDEX(CS!$B$1:$B$15026,MATCH($A24,CS!$B:$B,0)+COLUMN(B$1),1))} | BI24: {=IF($A24="","", INDEX(CS!$B$1:$B$15026,MATCH($A24,CS!$B:$B,0)+COLUMN(C$1),1))} -> 強靭な肉体 | BJ24: {=IF($A24="","", INDEX(CS!$B$1:$B$15026,MATCH($A24,CS!$B:$B,0)+COLUMN(D$1),1))} | BK24: {=IF($A24="","", INDEX(CS!$B$1:$B$15026,MATCH($A24,CS!$B:$B,0)+COLUMN(E$1),1))} -> 叩き潰し | BL24: {=IF($A24="","", INDEX(CS!$B$1:$B$15026,MATCH($A24,CS!$B:$B,0)+COLUMN(F$1),1))} | BM24: {=IF($A24="","", INDEX(CS!$B$1:$B$15026,MATCH($A24,CS!$B:$B,0)+COLUMN(G$1),1))} -> 大鬼の咆哮 | BN24: {=IF($A24="","", INDEX(CS!$B$1:$B$15026,MATCH($A24,CS!$B:$B,0)+COLUMN(H$1),1))} | ... BP24: {=IF($A24="","", INDEX(CS!$B$1:$B$15026,MATCH($A24,CS!$B:$B,0)+COLUMN(J$1),1))} -> 鬼の怪力 | BV24: 食事 | BW24: 200 | BX24: 40 | BY24: 10 | BZ24: 100 | CA24: 10 | CD24: 2 | CN24: 大鬼 | CO24: ["荒野","丘陵"] | CP24: ["沼地","湿地"]
A25: ジャイアント | C25: 亜人 | D25: =SUM(AJ25:AZ25,F25:N25)&"/"&SUM(F25:N25)&"/"&SUM(AJ25:AZ25) -> 710/490/220 | E25: 1 | F25: 90 | I25: 90 | J25: 70 | K25: 25 | L25: 70 | M25: 70 | N25: 75 | O25: 550 | P25: 0 | AJ25: 35 | AK25: 35 | AL25: 35 | AM25: -15 | AN25: 35 | AO25: 0 | AP25: 0 | AQ25: 0 | AR25: 35 | AS25: 0 | AT25: 0 | AU25: 0 | AV25: 0 | AW25: 35 | AX25: 0 | AY25: 25 | AZ25: 0 | BA25: 0 | BB25: 0 | BC25: 0 | BD25: 0 | BE25: 0 | BF25: 20 | BG25: {=IF($A25="","", INDEX(CS!$B$1:$B$15026,MATCH($A25,CS!$B:$B,0)+COLUMN(A$1),1))} -> 巨人の膂力 | BH25: {=IF($A25="","", INDEX(CS!$B$1:$B$15026,MATCH($A25,CS!$B:$B,0)+COLUMN(B$1),1))} | BI25: {=IF($A25="","", INDEX(CS!$B$1:$B$15026,MATCH($A25,CS!$B:$B,0)+COLUMN(C$1),1))} -> 巨大な体躯 | BJ25: {=IF($A25="","", INDEX(CS!$B$1:$B$15026,MATCH($A25,CS!$B:$B,0)+COLUMN(D$1),1))} | BK25: {=IF($A25="","", INDEX(CS!$B$1:$B$15026,MATCH($A25,CS!$B:$B,0)+COLUMN(E$1),1))} -> 踏みつけ | BL25: {=IF($A25="","", INDEX(CS!$B$1:$B$15026,MATCH($A25,CS!$B:$B,0)+COLUMN(F$1),1))} | BM25: {=IF($A25="","", INDEX(CS!$B$1:$B$15026,MATCH($A25,CS!$B:$B,0)+COLUMN(G$1),1))} -> 巨腕薙ぎ | BN25: {=IF($A25="","", INDEX(CS!$B$1:$B$15026,MATCH($A25,CS!$B:$B,0)+COLUMN(H$1),1))} | ... BP25: {=IF($A25="","", INDEX(CS!$B$1:$B$15026,MATCH($A25,CS!$B:$B,0)+COLUMN(J$1),1))} -> 巨躯 | BV25: 食事 | BW25: 250 | BX25: 60 | BY25: 30 | BZ25: 200 | CA25: 30 | CD25: 2 | CN25: 巨人 | CO25: ["山岳","雪原"] | CP25: ["洞窟","沼地"]
A26: ゴブリン | C26: 亜人 | D26: =SUM(AJ26:AZ26,F26:N26)&"/"&SUM(F26:N26)&"/"&SUM(AJ26:AZ26) -> 710/490/220 | E26: 1 | F26: 90 | I26: 90 | J26: 65 | K26: 30 | L26: 55 | M26: 85 | N26: 75 | O26: 100 | P26: -25 | Z26: 15 | AC26: -15 | AJ26: 25 | AK26: 0 | AL26: 25 | AM26: 35 | AN26: 35 | AO26: 0 | AP26: 0 | AQ26: 75 | AR26: 75 | AS26: 0 | AT26: 0 | AU26: 0 | AV26: 0 | AW26: -25 | AX26: -25 | AY26: 0 | AZ26: 0 | BA26: 0 | BB26: 0 | BC26: 0 | BD26: 0 | BE26: 0 | BF26: 0 | BG26: {=IF($A26="","", INDEX(CS!$B$1:$B$15026,MATCH($A26,CS!$B:$B,0)+COLUMN(A$1),1))} -> 小柄 | BH26: {=IF($A26="","", INDEX(CS!$B$1:$B$15026,MATCH($A26,CS!$B:$B,0)+COLUMN(B$1),1))} | BI26: {=IF($A26="","", INDEX(CS!$B$1:$B$15026,MATCH($A26,CS!$B:$B,0)+COLUMN(C$1),1))} -> 悪知恵 | BJ26: {=IF($A26="","", INDEX(CS!$B$1:$B$15026,MATCH($A26,CS!$B:$B,0)+COLUMN(D$1),1))} | BK26: {=IF($A26="","", INDEX(CS!$B$1:$B$15026,MATCH($A26,CS!$B:$B,0)+COLUMN(E$1),1))} -> 逃げ足 | BL26: {=IF($A26="","", INDEX(CS!$B$1:$B$15026,MATCH($A26,CS!$B:$B,0)+COLUMN(F$1),1))} | BM26: {=IF($A26="","", INDEX(CS!$B$1:$B$15026,MATCH($A26,CS!$B:$B,0)+COLUMN(G$1),1))} -> 奇襲 | BN26: {=IF($A26="","", INDEX(CS!$B$1:$B$15026,MATCH($A26,CS!$B:$B,0)+COLUMN(H$1),1))} | ... BP26: {=IF($A26="","", INDEX(CS!$B$1:$B$15026,MATCH($A26,CS!$B:$B,0)+COLUMN(J$1),1))} -> 狡猾 | BV26: 食事 | BW26: 70 | BX26: 30 | BY26: 20 | BZ26: 10 | CA26: 10 | CD26: 2 | CN26: 鬼妖 | CO26: ["洞窟","荒野"] | CP26: ["雪原"]
A27: トレント | C27: 亜人 | D27: =SUM(AJ27:AZ27,F27:N27)&"/"&SUM(F27:N27)&"/"&SUM(AJ27:AZ27) -> 710/490/220 | E27: 1 | F27: 90 | I27: 90 | J27: 70 | K27: 25 | L27: 55 | M27: 85 | N27: 75 | O27: 100 | P27: 25 | Z27: 15 | AC27: -15 | AJ27: 0 | AK27: -25 | AL27: 35 | AM27: 0 | AN27: 50 | AO27: 0 | AP27: 0 | AQ27: 75 | AR27: 25 | AS27: 75 | AT27: 0 | AU27: 0 | AV27: 0 | AW27: -25 | AX27: -25 | AY27: 0 | AZ27: 35 | BA27: 0 | BB27: 0 | BC27: 0 | BD27: 0 | BE27: 0 | BF27: 120 | BG27: {=IF($A27="","", INDEX(CS!$B$1:$B$15026,MATCH($A27,CS!$B:$B,0)+COLUMN(A$1),1))} -> 樹皮 | BH27: {=IF($A27="","", INDEX(CS!$B$1:$B$15026,MATCH($A27,CS!$B:$B,0)+COLUMN(B$1),1))} | BI27: {=IF($A27="","", INDEX(CS!$B$1:$B$15026,MATCH($A27,CS!$B:$B,0)+COLUMN(C$1),1))} -> 根張り | BJ27: {=IF($A27="","", INDEX(CS!$B$1:$B$15026,MATCH($A27,CS!$B:$B,0)+COLUMN(D$1),1))} | BK27: {=IF($A27="","", INDEX(CS!$B$1:$B$15026,MATCH($A27,CS!$B:$B,0)+COLUMN(E$1),1))} -> 枝打ち | BL27: {=IF($A27="","", INDEX(CS!$B$1:$B$15026,MATCH($A27,CS!$B:$B,0)+COLUMN(F$1),1))} | BM27: {=IF($A27="","", INDEX(CS!$B$1:$B$15026,MATCH($A27,CS!$B:$B,0)+COLUMN(G$1),1))} -> 森との同化 | BN27: {=IF($A27="","", INDEX(CS!$B$1:$B$15026,MATCH($A27,CS!$B:$B,0)+COLUMN(H$1),1))} | ... BP27: {=IF($A27="","", INDEX(CS!$B$1:$B$15026,MATCH($A27,CS!$B:$B,0)+COLUMN(J$1),1))} -> 古木の生命力 | BV27: 食事 | BW27: 70 | BX27: 30 | BY27: 20 | BZ27: 10 | CA27: 10 | CD27: 2 | CN27: 鬼妖 | CO27: ["森","湿地"] | CP27: ["砂漠","火山","溶岩"]
D28: =SUM(AJ28:AZ28,F28:N28)&"/"&SUM(F28:N28)&"/"&SUM(AJ28:AZ28) -> 0/0/0 | E28: 1 | BG28: {=IF($A28="","", INDEX(CS!$B$1:$B$15026,MATCH($A28,CS!$B:$B,0)+COLUMN(A$1),1))} | BH28: {=IF($A28="","", INDEX(CS!$B$1:$B$15026,MATCH($A28,CS!$B:$B,0)+COLUMN(B$1),1))} | BI28: {=IF($A28="","", INDEX(CS!$B$1:$B$15026,MATCH($A28,CS!$B:$B,0)+COLUMN(C$1),1))} | BJ28: {=IF($A28="","", INDEX(CS!$B$1:$B$15026,MATCH($A28,CS!$B:$B,0)+COLUMN(D$1),1))} | BK28: {=IF($A28="","", INDEX(CS!$B$1:$B$15026,MATCH($A28,CS!$B:$B,0)+COLUMN(E$1),1))} | BL28: {=IF($A28="","", INDEX(CS!$B$1:$B$15026,MATCH($A28,CS!$B:$B,0)+COLUMN(F$1),1))} | BM28: {=IF($A28="","", INDEX(CS!$B$1:$B$15026,MATCH($A28,CS!$B:$B,0)+COLUMN(G$1),1))} | BN28: {=IF($A28="","", INDEX(CS!$B$1:$B$15026,MATCH($A28,CS!$B:$B,0)+COLUMN(H$1),1))} | ... BP28: {=IF($A28="","", INDEX(CS!$B$1:$B$15026,MATCH($A28,CS!$B:$B,0)+COLUMN(J$1),1))}
B29: -=========== 悪魔 ===========- | D29: =SUM(AJ29:AZ29,F29:N29)&"/"&SUM(F29:N29)&"/"&SUM(AJ29:AZ29) -> 0/0/0 | BG29: {=IF($A29="","", INDEX(CS!$B$1:$B$15026,MATCH($A29,CS!$B:$B,0)+COLUMN(A$1),1))} | BH29: {=IF($A29="","", INDEX(CS!$B$1:$B$15026,MATCH($A29,CS!$B:$B,0)+COLUMN(B$1),1))} | BI29: {=IF($A29="","", INDEX(CS!$B$1:$B$15026,MATCH($A29,CS!$B:$B,0)+COLUMN(C$1),1))} | BJ29: {=IF($A29="","", INDEX(CS!$B$1:$B$15026,MATCH($A29,CS!$B:$B,0)+COLUMN(D$1),1))} | BK29: {=IF($A29="","", INDEX(CS!$B$1:$B$15026,MATCH($A29,CS!$B:$B,0)+COLUMN(E$1),1))} | BL29: {=IF($A29="","", INDEX(CS!$B$1:$B$15026,MATCH($A29,CS!$B:$B,0)+COLUMN(F$1),1))} | BM29: {=IF($A29="","", INDEX(CS!$B$1:$B$15026,MATCH($A29,CS!$B:$B,0)+COLUMN(G$1),1))} | BN29: {=IF($A29="","", INDEX(CS!$B$1:$B$15026,MATCH($A29,CS!$B:$B,0)+COLUMN(H$1),1))} | ... BP29: {=IF($A29="","", INDEX(CS!$B$1:$B$15026,MATCH($A29,CS!$B:$B,0)+COLUMN(J$1),1))}
A30: デヴィル | C30: 魔族 | D30: =SUM(AJ30:AZ30,F30:N30)&"/"&SUM(F30:N30)&"/"&SUM(AJ30:AZ30) -> 710/515/195 | E30: 1 | F30: 90 | I30: 80 | J30: 70 | K30: 80 | L30: 60 | M30: 70 | N30: 65 | O30: 170 | P30: -100 | Q30: 10 | R30: 5 | W30: 15 | X30: 15 | AA30: -30 | AB30: 15 | AJ30: 50 | AK30: 50 | AL30: 35 | AM30: 15 | AN30: 0 | AO30: 0 | AP30: 0 | AQ30: 35 | AR30: 35 | AS30: -25 | AT30: -25 | AU30: -25 | AV30: -25 | AW30: 0 | AX30: 0 | AY30: 75 | AZ30: 0 | BA30: 0 | BB30: 100 | BC30: 100 | BD30: 0 | BE30: 0 | BF30: 50 | BG30: {=IF($A30="","", INDEX(CS!$B$1:$B$15026,MATCH($A30,CS!$B:$B,0)+COLUMN(A$1),1))} | BH30: {=IF($A30="","", INDEX(CS!$B$1:$B$15026,MATCH($A30,CS!$B:$B,0)+COLUMN(B$1),1))} -> 邪視 | BI30: {=IF($A30="","", INDEX(CS!$B$1:$B$15026,MATCH($A30,CS!$B:$B,0)+COLUMN(C$1),1))} -> 悪魔の槍 | BJ30: {=IF($A30="","", INDEX(CS!$B$1:$B$15026,MATCH($A30,CS!$B:$B,0)+COLUMN(D$1),1))} | BK30: {=IF($A30="","", INDEX(CS!$B$1:$B$15026,MATCH($A30,CS!$B:$B,0)+COLUMN(E$1),1))} -> 悪魔の槍 | BL30: {=IF($A30="","", INDEX(CS!$B$1:$B$15026,MATCH($A30,CS!$B:$B,0)+COLUMN(F$1),1))} -> 悪の魔力 | BM30: {=IF($A30="","", INDEX(CS!$B$1:$B$15026,MATCH($A30,CS!$B:$B,0)+COLUMN(G$1),1))} -> 悪魔の外皮 | BN30: {=IF($A30="","", INDEX(CS!$B$1:$B$15026,MATCH($A30,CS!$B:$B,0)+COLUMN(H$1),1))} | ... BP30: {=IF($A30="","", INDEX(CS!$B$1:$B$15026,MATCH($A30,CS!$B:$B,0)+COLUMN(J$1),1))} -> 次元の扉 | BV30: 魂 | BW30: 30 | BX30: 0 | BY30: 0 | BZ30: 35 | CA30: 15 | CD30: 2 | CN30: 悪魔 | CO30: ["火山","荒野"] | CP30: ["雪原"]
A31: アークデヴィル | C31: 魔族 | D31: =SUM(AJ31:AZ31,F31:N31)&"/"&SUM(F31:N31)&"/"&SUM(AJ31:AZ31) -> 710/515/195 | E31: 2 | F31: 90 | I31: 80 | J31: 70 | K31: 80 | L31: 60 | M31: 70 | N31: 65 | O31: 170 | P31: -100 | Q31: 10 | R31: 5 | W31: 15 | X31: 15 | AA31: -30 | AB31: 15 | AJ31: 50 | AK31: 50 | AL31: 35 | AM31: 15 | AN31: 0 | AO31: 0 | AP31: 0 | AQ31: 35 | AR31: 35 | AS31: -25 | AT31: -25 | AU31: -25 | AV31: -25 | AW31: 0 | AX31: 0 | AY31: 75 | AZ31: 0 | BA31: 0 | BB31: 100 | BC31: 100 | BD31: 0 | BE31: 0 | BF31: 50 | BG31: {=IF($A31="","", INDEX(CS!$B$1:$B$15026,MATCH($A31,CS!$B:$B,0)+COLUMN(A$1),1))} -> #N/A | BH31: {=IF($A31="","", INDEX(CS!$B$1:$B$15026,MATCH($A31,CS!$B:$B,0)+COLUMN(B$1),1))} -> #N/A | BI31: {=IF($A31="","", INDEX(CS!$B$1:$B$15026,MATCH($A31,CS!$B:$B,0)+COLUMN(C$1),1))} -> #N/A | BJ31: {=IF($A31="","", INDEX(CS!$B$1:$B$15026,MATCH($A31,CS!$B:$B,0)+COLUMN(D$1),1))} -> #N/A | BK31: {=IF($A31="","", INDEX(CS!$B$1:$B$15026,MATCH($A31,CS!$B:$B,0)+COLUMN(E$1),1))} -> #N/A | BL31: {=IF($A31="","", INDEX(CS!$B$1:$B$15026,MATCH($A31,CS!$B:$B,0)+COLUMN(F$1),1))} -> #N/A | BM31: {=IF($A31="","", INDEX(CS!$B$1:$B$15026,MATCH($A31,CS!$B:$B,0)+COLUMN(G$1),1))} -> #N/A | BN31: {=IF($A31="","", INDEX(CS!$B$1:$B$15026,MATCH($A31,CS!$B:$B,0)+COLUMN(H$1),1))} -> #N/A | ... BP31: {=IF($A31="","", INDEX(CS!$B$1:$B$15026,MATCH($A31,CS!$B:$B,0)+COLUMN(J$1),1))} -> #N/A | BQ31: 20 | BR31: デヴィル_10 | BX31: 0 | BY31: 0 | BZ31: 35 | CA31: 15 | CD31: 2 | CN31: 悪魔 | CO31: ["火山","荒野"] | CP31: ["雪原"]
A32: アーチデヴィル | C32: 魔族 | D32: =SUM(AJ32:AZ32,F32:N32)&"/"&SUM(F32:N32)&"/"&SUM(AJ32:AZ32) -> 710/515/195 | E32: 3 | F32: 90 | I32: 80 | J32: 70 | K32: 80 | L32: 60 | M32: 70 | N32: 65 | O32: 170 | P32: -100 | Q32: 10 | R32: 5 | W32: 15 | X32: 15 | AA32: -30 | AB32: 15 | AJ32: 50 | AK32: 50 | AL32: 35 | AM32: 15 | AN32: 0 | AO32: 0 | AP32: 0 | AQ32: 35 | AR32: 35 | AS32: -25 | AT32: -25 | AU32: -25 | AV32: -25 | AW32: 0 | AX32: 0 | AY32: 75 | AZ32: 0 | BA32: 0 | BB32: 100 | BC32: 100 | BD32: 0 | BE32: 0 | BF32: 50 | BG32: {=IF($A32="","", INDEX(CS!$B$1:$B$15026,MATCH($A32,CS!$B:$B,0)+COLUMN(A$1),1))} -> #N/A | BH32: {=IF($A32="","", INDEX(CS!$B$1:$B$15026,MATCH($A32,CS!$B:$B,0)+COLUMN(B$1),1))} -> #N/A | BI32: {=IF($A32="","", INDEX(CS!$B$1:$B$15026,MATCH($A32,CS!$B:$B,0)+COLUMN(C$1),1))} -> #N/A | BJ32: {=IF($A32="","", INDEX(CS!$B$1:$B$15026,MATCH($A32,CS!$B:$B,0)+COLUMN(D$1),1))} -> #N/A | BK32: {=IF($A32="","", INDEX(CS!$B$1:$B$15026,MATCH($A32,CS!$B:$B,0)+COLUMN(E$1),1))} -> #N/A | BL32: {=IF($A32="","", INDEX(CS!$B$1:$B$15026,MATCH($A32,CS!$B:$B,0)+COLUMN(F$1),1))} -> #N/A | BM32: {=IF($A32="","", INDEX(CS!$B$1:$B$15026,MATCH($A32,CS!$B:$B,0)+COLUMN(G$1),1))} -> #N/A | BN32: {=IF($A32="","", INDEX(CS!$B$1:$B$15026,MATCH($A32,CS!$B:$B,0)+COLUMN(H$1),1))} -> #N/A | ... BP32: {=IF($A32="","", INDEX(CS!$B$1:$B$15026,MATCH($A32,CS!$B:$B,0)+COLUMN(J$1),1))} -> #N/A | BQ32: 30 | BR32: アークデヴィル_10 | BX32: 0 | BY32: 0 | BZ32: 35 | CA32: 15 | CD32: 2 | CN32: 悪魔 | CO32: ["火山","荒野"] | CP32: ["雪原"] | CR32: 500
A33: ヘルザーデヴィル | C33: 魔族 | D33: =SUM(AJ33:AZ33,F33:N33)&"/"&SUM(F33:N33)&"/"&SUM(AJ33:AZ33) -> 710/515/195 | E33: 4 | F33: 90 | I33: 80 | J33: 70 | K33: 80 | L33: 60 | M33: 70 | N33: 65 | O33: 170 | P33: -100 | AJ33: 50 | AK33: 50 | AL33: 35 | AM33: 15 | AN33: 0 | AO33: 0 | AP33: 0 | AQ33: 35 | AR33: 35 | AS33: -25 | AT33: -25 | AU33: -25 | AV33: -25 | AW33: 0 | AX33: 0 | AY33: 75 | AZ33: 0 | BA33: 0 | BB33: 100 | BC33: 100 | BD33: 0 | BE33: 0 | BF33: 50 | BQ33: 40 | BR33: アーチデヴィル_10 | BU33: デヴィル派生。性能は基礎デヴィル値を暫定継承。専用スキル・詳細階層は未調整。 | BX33: 0 | BY33: 0 | BZ33: 35 | CA33: 15 | CD33: 2 | CN33: 悪魔 | CO33: ["火山","荒野"] | CP33: ["雪原"] | CR33: 1000
A34: フレイムデヴィル | C34: 魔族 | D34: =SUM(AJ34:AZ34,F34:N34)&"/"&SUM(F34:N34)&"/"&SUM(AJ34:AZ34) -> 710/515/195 | E34: 2 | F34: 90 | I34: 80 | J34: 70 | K34: 80 | L34: 60 | M34: 70 | N34: 65 | O34: 170 | P34: -100 | AJ34: 50 | AK34: 50 | AL34: 35 | AM34: 15 | AN34: 0 | AO34: 0 | AP34: 0 | AQ34: 35 | AR34: 35 | AS34: -25 | AT34: -25 | AU34: -25 | AV34: -25 | AW34: 0 | AX34: 0 | AY34: 75 | AZ34: 0 | BA34: 0 | BB34: 100 | BC34: 100 | BD34: 0 | BE34: 0 | BF34: 50 | BR34: デヴィル_10 | BU34: デヴィル派生。性能は基礎デヴィル値を暫定継承。専用スキル・詳細階層は未調整。 | BX34: 0 | BY34: 0 | BZ34: 35 | CA34: 15 | CD34: 2 | CN34: 悪魔 | CO34: ["火山","荒野"] | CP34: ["雪原"]
A35: ヘルフレイムデヴィル | C35: 魔族 | D35: =SUM(AJ35:AZ35,F35:N35)&"/"&SUM(F35:N35)&"/"&SUM(AJ35:AZ35) -> 710/515/195 | E35: 2 | F35: 90 | I35: 80 | J35: 70 | K35: 80 | L35: 60 | M35: 70 | N35: 65 | O35: 170 | P35: -100 | AJ35: 50 | AK35: 50 | AL35: 35 | AM35: 15 | AN35: 0 | AO35: 0 | AP35: 0 | AQ35: 35 | AR35: 35 | AS35: -25 | AT35: -25 | AU35: -25 | AV35: -25 | AW35: 0 | AX35: 0 | AY35: 75 | AZ35: 0 | BA35: 0 | BB35: 100 | BC35: 100 | BD35: 0 | BE35: 0 | BF35: 50 | BR35: デヴィル_10 | BU35: デヴィル派生。性能は基礎デヴィル値を暫定継承。専用スキル・詳細階層は未調整。 | BX35: 0 | BY35: 0 | BZ35: 35 | CA35: 15 | CD35: 2 | CN35: 悪魔 | CO35: ["火山","荒野"] | CP35: ["雪原"]
A36: ヘルフロストデヴィル | C36: 魔族 | D36: =SUM(AJ36:AZ36,F36:N36)&"/"&SUM(F36:N36)&"/"&SUM(AJ36:AZ36) -> 710/515/195 | E36: 2 | F36: 90 | I36: 80 | J36: 70 | K36: 80 | L36: 60 | M36: 70 | N36: 65 | O36: 170 | P36: -100 | AJ36: 50 | AK36: 50 | AL36: 35 | AM36: 15 | AN36: 0 | AO36: 0 | AP36: 0 | AQ36: 35 | AR36: 35 | AS36: -25 | AT36: -25 | AU36: -25 | AV36: -25 | AW36: 0 | AX36: 0 | AY36: 75 | AZ36: 0 | BA36: 0 | BB36: 100 | BC36: 100 | BD36: 0 | BE36: 0 | BF36: 50 | BR36: デヴィル_10 | BU36: デヴィル派生。性能は基礎デヴィル値を暫定継承。専用スキル・詳細階層は未調整。 | BX36: 0 | BY36: 0 | BZ36: 35 | CA36: 15 | CD36: 2 | CN36: 悪魔 | CO36: ["火山","荒野"] | CP36: ["雪原"]
A37: ブラッドデヴィル | C37: 魔族 | D37: =SUM(AJ37:AZ37,F37:N37)&"/"&SUM(F37:N37)&"/"&SUM(AJ37:AZ37) -> 710/515/195 | E37: 2 | F37: 90 | I37: 80 | J37: 70 | K37: 80 | L37: 60 | M37: 70 | N37: 65 | O37: 170 | P37: -100 | AJ37: 50 | AK37: 50 | AL37: 35 | AM37: 15 | AN37: 0 | AO37: 0 | AP37: 0 | AQ37: 35 | AR37: 35 | AS37: -25 | AT37: -25 | AU37: -25 | AV37: -25 | AW37: 0 | AX37: 0 | AY37: 75 | AZ37: 0 | BA37: 0 | BB37: 100 | BC37: 100 | BD37: 0 | BE37: 0 | BF37: 50 | BR37: デヴィル_10 | BU37: デヴィル派生。性能は基礎デヴィル値を暫定継承。専用スキル・詳細階層は未調整。 | BX37: 0 | BY37: 0 | BZ37: 35 | CA37: 15 | CD37: 2 | CN37: 悪魔 | CO37: ["火山","荒野"] | CP37: ["雪原"]
A38: 武装生成 | C38: 魔族 | D38: =SUM(AJ38:AZ38,F38:N38)&"/"&SUM(F38:N38)&"/"&SUM(AJ38:AZ38) -> 710/515/195 | E38: 2 | F38: 90 | I38: 80 | J38: 70 | K38: 80 | L38: 60 | M38: 70 | N38: 65 | O38: 170 | P38: -100 | AJ38: 50 | AK38: 50 | AL38: 35 | AM38: 15 | AN38: 0 | AO38: 0 | AP38: 0 | AQ38: 35 | AR38: 35 | AS38: -25 | AT38: -25 | AU38: -25 | AV38: -25 | AW38: 0 | AX38: 0 | AY38: 75 | AZ38: 0 | BA38: 0 | BB38: 100 | BC38: 100 | BD38: 0 | BE38: 0 | BF38: 50 | BR38: デヴィル_10 | BU38: デヴィル専用系統。性能は基礎デヴィル値を暫定継承。専用スキル・正式な階層は未調整。 | BX38: 0 | BY38: 0 | BZ38: 35 | CA38: 15 | CD38: 2 | CN38: 悪魔 | CO38: ["火山","荒野"] | CP38: ["雪原"]
A39: 魔眼 | C39: 魔族 | D39: =SUM(AJ39:AZ39,F39:N39)&"/"&SUM(F39:N39)&"/"&SUM(AJ39:AZ39) -> 710/515/195 | E39: 2 | F39: 90 | I39: 80 | J39: 70 | K39: 80 | L39: 60 | M39: 70 | N39: 65 | O39: 170 | P39: -100 | AJ39: 50 | AK39: 50 | AL39: 35 | AM39: 15 | AN39: 0 | AO39: 0 | AP39: 0 | AQ39: 35 | AR39: 35 | AS39: -25 | AT39: -25 | AU39: -25 | AV39: -25 | AW39: 0 | AX39: 0 | AY39: 75 | AZ39: 0 | BA39: 0 | BB39: 100 | BC39: 100 | BD39: 0 | BE39: 0 | BF39: 50 | BR39: デヴィル_10 | BU39: デヴィル専用系統。性能は基礎デヴィル値を暫定継承。専用スキル・正式な階層は未調整。 | BX39: 0 | BY39: 0 | BZ39: 35 | CA39: 15 | CD39: 2 | CN39: 悪魔 | CO39: ["火山","荒野"] | CP39: ["雪原"]
A40: 変身 | C40: 魔族 | D40: =SUM(AJ40:AZ40,F40:N40)&"/"&SUM(F40:N40)&"/"&SUM(AJ40:AZ40) -> 710/515/195 | E40: 2 | F40: 90 | I40: 80 | J40: 70 | K40: 80 | L40: 60 | M40: 70 | N40: 65 | O40: 170 | P40: -100 | AJ40: 50 | AK40: 50 | AL40: 35 | AM40: 15 | AN40: 0 | AO40: 0 | AP40: 0 | AQ40: 35 | AR40: 35 | AS40: -25 | AT40: -25 | AU40: -25 | AV40: -25 | AW40: 0 | AX40: 0 | AY40: 75 | AZ40: 0 | BA40: 0 | BB40: 100 | BC40: 100 | BD40: 0 | BE40: 0 | BF40: 50 | BR40: デヴィル_10 | BU40: デヴィル専用系統。性能は基礎デヴィル値を暫定継承。専用スキル・正式な階層は未調整。 | BX40: 0 | BY40: 0 | BZ40: 35 | CA40: 15 | CD40: 2 | CN40: 悪魔 | CO40: ["火山","荒野"] | CP40: ["雪原"]
A41: 空間操作 | C41: 魔族 | D41: =SUM(AJ41:AZ41,F41:N41)&"/"&SUM(F41:N41)&"/"&SUM(AJ41:AZ41) -> 710/515/195 | E41: 2 | F41: 90 | I41: 80 | J41: 70 | K41: 80 | L41: 60 | M41: 70 | N41: 65 | O41: 170 | P41: -100 | AJ41: 50 | AK41: 50 | AL41: 35 | AM41: 15 | AN41: 0 | AO41: 0 | AP41: 0 | AQ41: 35 | AR41: 35 | AS41: -25 | AT41: -25 | AU41: -25 | AV41: -25 | AW41: 0 | AX41: 0 | AY41: 75 | AZ41: 0 | BA41: 0 | BB41: 100 | BC41: 100 | BD41: 0 | BE41: 0 | BF41: 50 | BR41: デヴィル_10 | BU41: デヴィル専用系統。性能は基礎デヴィル値を暫定継承。専用スキル・正式な階層は未調整。 | BX41: 0 | BY41: 0 | BZ41: 35 | CA41: 15 | CD41: 2 | CN41: 悪魔 | CO41: ["火山","荒野"] | CP41: ["雪原"]
D42: =SUM(AJ42:AZ42,F42:N42)&"/"&SUM(F42:N42)&"/"&SUM(AJ42:AZ42) -> 0/0/0 | E42: 1 | BG42: {=IF($A42="","", INDEX(CS!$B$1:$B$15026,MATCH($A42,CS!$B:$B,0)+COLUMN(A$1),1))} | BH42: {=IF($A42="","", INDEX(CS!$B$1:$B$15026,MATCH($A42,CS!$B:$B,0)+COLUMN(B$1),1))} | BI42: {=IF($A42="","", INDEX(CS!$B$1:$B$15026,MATCH($A42,CS!$B:$B,0)+COLUMN(C$1),1))} | BJ42: {=IF($A42="","", INDEX(CS!$B$1:$B$15026,MATCH($A42,CS!$B:$B,0)+COLUMN(D$1),1))} | BK42: {=IF($A42="","", INDEX(CS!$B$1:$B$15026,MATCH($A42,CS!$B:$B,0)+COLUMN(E$1),1))} | BL42: {=IF($A42="","", INDEX(CS!$B$1:$B$15026,MATCH($A42,CS!$B:$B,0)+COLUMN(F$1),1))} | BM42: {=IF($A42="","", INDEX(CS!$B$1:$B$15026,MATCH($A42,CS!$B:$B,0)+COLUMN(G$1),1))} | BN42: {=IF($A42="","", INDEX(CS!$B$1:$B$15026,MATCH($A42,CS!$B:$B,0)+COLUMN(H$1),1))} | ... BP42: {=IF($A42="","", INDEX(CS!$B$1:$B$15026,MATCH($A42,CS!$B:$B,0)+COLUMN(J$1),1))}
B43: -=========== 天使 ===========- | D43: =SUM(AJ43:AZ43,F43:N43)&"/"&SUM(F43:N43)&"/"&SUM(AJ43:AZ43) -> 0/0/0 | BG43: {=IF($A43="","", INDEX(CS!$B$1:$B$15026,MATCH($A43,CS!$B:$B,0)+COLUMN(A$1),1))} | BH43: {=IF($A43="","", INDEX(CS!$B$1:$B$15026,MATCH($A43,CS!$B:$B,0)+COLUMN(B$1),1))} | BI43: {=IF($A43="","", INDEX(CS!$B$1:$B$15026,MATCH($A43,CS!$B:$B,0)+COLUMN(C$1),1))} | BJ43: {=IF($A43="","", INDEX(CS!$B$1:$B$15026,MATCH($A43,CS!$B:$B,0)+COLUMN(D$1),1))} | BK43: {=IF($A43="","", INDEX(CS!$B$1:$B$15026,MATCH($A43,CS!$B:$B,0)+COLUMN(E$1),1))} | BL43: {=IF($A43="","", INDEX(CS!$B$1:$B$15026,MATCH($A43,CS!$B:$B,0)+COLUMN(F$1),1))} | BM43: {=IF($A43="","", INDEX(CS!$B$1:$B$15026,MATCH($A43,CS!$B:$B,0)+COLUMN(G$1),1))} | BN43: {=IF($A43="","", INDEX(CS!$B$1:$B$15026,MATCH($A43,CS!$B:$B,0)+COLUMN(H$1),1))} | ... BP43: {=IF($A43="","", INDEX(CS!$B$1:$B$15026,MATCH($A43,CS!$B:$B,0)+COLUMN(J$1),1))}
A44: エンジェル | C44: 魔族 | D44: =SUM(AJ44:AZ44,F44:N44)&"/"&SUM(F44:N44)&"/"&SUM(AJ44:AZ44) -> 710/515/195 | E44: 1 | F44: 75 | I44: 70 | J44: 80 | K44: 80 | L44: 80 | M44: 65 | N44: 65 | O44: 170 | P44: 100 | Q44: 5 | R44: 10 | Y44: 15 | Z44: 15 | AA44: 15 | AB44: -30 | AJ44: 50 | AK44: 0 | AL44: 75 | AM44: 0 | AN44: 25 | AO44: 0 | AP44: 0 | AQ44: 35 | AR44: 35 | AS44: -25 | AT44: -25 | AU44: -25 | AV44: -25 | AW44: 0 | AX44: 0 | AY44: 0 | AZ44: 75 | BA44: 0 | BB44: 0 | BC44: 0 | BD44: 0 | BE44: 0 | BF44: 20 | BG44: {=IF($A44="","", INDEX(CS!$B$1:$B$15026,MATCH($A44,CS!$B:$B,0)+COLUMN(A$1),1))} -> 浮遊 | BH44: {=IF($A44="","", INDEX(CS!$B$1:$B$15026,MATCH($A44,CS!$B:$B,0)+COLUMN(B$1),1))} | BI44: {=IF($A44="","", INDEX(CS!$B$1:$B$15026,MATCH($A44,CS!$B:$B,0)+COLUMN(C$1),1))} -> 光粒 | BJ44: {=IF($A44="","", INDEX(CS!$B$1:$B$15026,MATCH($A44,CS!$B:$B,0)+COLUMN(D$1),1))} | BK44: {=IF($A44="","", INDEX(CS!$B$1:$B$15026,MATCH($A44,CS!$B:$B,0)+COLUMN(E$1),1))} -> 天使の矢 | BL44: {=IF($A44="","", INDEX(CS!$B$1:$B$15026,MATCH($A44,CS!$B:$B,0)+COLUMN(F$1),1))} | BM44: {=IF($A44="","", INDEX(CS!$B$1:$B$15026,MATCH($A44,CS!$B:$B,0)+COLUMN(G$1),1))} -> 軽回復 | BN44: {=IF($A44="","", INDEX(CS!$B$1:$B$15026,MATCH($A44,CS!$B:$B,0)+COLUMN(H$1),1))} | ... BP44: {=IF($A44="","", INDEX(CS!$B$1:$B$15026,MATCH($A44,CS!$B:$B,0)+COLUMN(J$1),1))} -> 天使の祝福 | BV44: 魂 | BW44: 30 | BX44: 5 | BY44: 25 | BZ44: 5 | CA44: 5 | CD44: 2 | CN44: 天使 | CO44: ["山岳","雪原"] | CP44: ["死の霧"]
A45: アークエンジェル | C45: 魔族 | D45: =SUM(AJ45:AZ45,F45:N45)&"/"&SUM(F45:N45)&"/"&SUM(AJ45:AZ45) -> 710/515/195 | E45: 2 | F45: 75 | I45: 70 | J45: 80 | K45: 80 | L45: 80 | M45: 65 | N45: 65 | O45: 170 | P45: 100 | AJ45: 50 | AK45: 0 | AL45: 75 | AM45: 0 | AN45: 25 | AO45: 0 | AP45: 0 | AQ45: 35 | AR45: 35 | AS45: -25 | AT45: -25 | AU45: -25 | AV45: -25 | AW45: 0 | AX45: 0 | AY45: 0 | AZ45: 75 | BA45: 0 | BB45: 0 | BC45: 0 | BD45: 0 | BE45: 0 | BF45: 20 | BG45: {=IF($A45="","", INDEX(CS!$B$1:$B$15026,MATCH($A45,CS!$B:$B,0)+COLUMN(A$1),1))} -> #N/A | BH45: {=IF($A45="","", INDEX(CS!$B$1:$B$15026,MATCH($A45,CS!$B:$B,0)+COLUMN(B$1),1))} -> #N/A | BI45: {=IF($A45="","", INDEX(CS!$B$1:$B$15026,MATCH($A45,CS!$B:$B,0)+COLUMN(C$1),1))} -> #N/A | BJ45: {=IF($A45="","", INDEX(CS!$B$1:$B$15026,MATCH($A45,CS!$B:$B,0)+COLUMN(D$1),1))} -> #N/A | BK45: {=IF($A45="","", INDEX(CS!$B$1:$B$15026,MATCH($A45,CS!$B:$B,0)+COLUMN(E$1),1))} -> #N/A | BL45: {=IF($A45="","", INDEX(CS!$B$1:$B$15026,MATCH($A45,CS!$B:$B,0)+COLUMN(F$1),1))} -> #N/A | BM45: {=IF($A45="","", INDEX(CS!$B$1:$B$15026,MATCH($A45,CS!$B:$B,0)+COLUMN(G$1),1))} -> #N/A | BN45: {=IF($A45="","", INDEX(CS!$B$1:$B$15026,MATCH($A45,CS!$B:$B,0)+COLUMN(H$1),1))} -> #N/A | ... BP45: {=IF($A45="","", INDEX(CS!$B$1:$B$15026,MATCH($A45,CS!$B:$B,0)+COLUMN(J$1),1))} -> #N/A | BX45: 5 | BY45: 25 | BZ45: 5 | CA45: 5 | CD45: 2 | CN45: 天使 | CO45: ["山岳","雪原"] | CP45: ["死の霧"]
A46: アーチエンジェル | C46: 魔族 | D46: =SUM(AJ46:AZ46,F46:N46)&"/"&SUM(F46:N46)&"/"&SUM(AJ46:AZ46) -> 710/515/195 | E46: 3 | F46: 75 | I46: 70 | J46: 80 | K46: 80 | L46: 80 | M46: 65 | N46: 65 | O46: 170 | P46: 100 | AJ46: 50 | AK46: 0 | AL46: 75 | AM46: 0 | AN46: 25 | AO46: 0 | AP46: 0 | AQ46: 35 | AR46: 35 | AS46: -25 | AT46: -25 | AU46: -25 | AV46: -25 | AW46: 0 | AX46: 0 | AY46: 0 | AZ46: 75 | BA46: 0 | BB46: 0 | BC46: 0 | BD46: 0 | BE46: 0 | BF46: 20 | BG46: {=IF($A46="","", INDEX(CS!$B$1:$B$15026,MATCH($A46,CS!$B:$B,0)+COLUMN(A$1),1))} -> #N/A | BH46: {=IF($A46="","", INDEX(CS!$B$1:$B$15026,MATCH($A46,CS!$B:$B,0)+COLUMN(B$1),1))} -> #N/A | BI46: {=IF($A46="","", INDEX(CS!$B$1:$B$15026,MATCH($A46,CS!$B:$B,0)+COLUMN(C$1),1))} -> #N/A | BJ46: {=IF($A46="","", INDEX(CS!$B$1:$B$15026,MATCH($A46,CS!$B:$B,0)+COLUMN(D$1),1))} -> #N/A | BK46: {=IF($A46="","", INDEX(CS!$B$1:$B$15026,MATCH($A46,CS!$B:$B,0)+COLUMN(E$1),1))} -> #N/A | BL46: {=IF($A46="","", INDEX(CS!$B$1:$B$15026,MATCH($A46,CS!$B:$B,0)+COLUMN(F$1),1))} -> #N/A | BM46: {=IF($A46="","", INDEX(CS!$B$1:$B$15026,MATCH($A46,CS!$B:$B,0)+COLUMN(G$1),1))} -> #N/A | BN46: {=IF($A46="","", INDEX(CS!$B$1:$B$15026,MATCH($A46,CS!$B:$B,0)+COLUMN(H$1),1))} -> #N/A | ... BP46: {=IF($A46="","", INDEX(CS!$B$1:$B$15026,MATCH($A46,CS!$B:$B,0)+COLUMN(J$1),1))} -> #N/A | BX46: 5 | BY46: 25 | BZ46: 5 | CA46: 5 | CD46: 2 | CN46: 天使 | CO46: ["山岳","雪原"] | CP46: ["死の霧"] | CQ46: 500
A47: ヘヴンエンジェル | C47: 魔族 | D47: =SUM(AJ47:AZ47,F47:N47)&"/"&SUM(F47:N47)&"/"&SUM(AJ47:AZ47) -> 710/515/195 | E47: 4 | F47: 75 | I47: 70 | J47: 80 | K47: 80 | L47: 80 | M47: 65 | N47: 65 | O47: 170 | P47: 100 | AJ47: 50 | AK47: 0 | AL47: 75 | AM47: 0 | AN47: 25 | AO47: 0 | AP47: 0 | AQ47: 35 | AR47: 35 | AS47: -25 | AT47: -25 | AU47: -25 | AV47: -25 | AW47: 0 | AX47: 0 | AY47: 0 | AZ47: 75 | BA47: 0 | BB47: 0 | BC47: 0 | BD47: 0 | BE47: 0 | BF47: 20 | BG47: {=IF($A47="","", INDEX(CS!$B$1:$B$15026,MATCH($A47,CS!$B:$B,0)+COLUMN(A$1),1))} -> #N/A | BH47: {=IF($A47="","", INDEX(CS!$B$1:$B$15026,MATCH($A47,CS!$B:$B,0)+COLUMN(B$1),1))} -> #N/A | BI47: {=IF($A47="","", INDEX(CS!$B$1:$B$15026,MATCH($A47,CS!$B:$B,0)+COLUMN(C$1),1))} -> #N/A | BJ47: {=IF($A47="","", INDEX(CS!$B$1:$B$15026,MATCH($A47,CS!$B:$B,0)+COLUMN(D$1),1))} -> #N/A | BK47: {=IF($A47="","", INDEX(CS!$B$1:$B$15026,MATCH($A47,CS!$B:$B,0)+COLUMN(E$1),1))} -> #N/A | BL47: {=IF($A47="","", INDEX(CS!$B$1:$B$15026,MATCH($A47,CS!$B:$B,0)+COLUMN(F$1),1))} -> #N/A | BM47: {=IF($A47="","", INDEX(CS!$B$1:$B$15026,MATCH($A47,CS!$B:$B,0)+COLUMN(G$1),1))} -> #N/A | BN47: {=IF($A47="","", INDEX(CS!$B$1:$B$15026,MATCH($A47,CS!$B:$B,0)+COLUMN(H$1),1))} -> #N/A | ... BP47: {=IF($A47="","", INDEX(CS!$B$1:$B$15026,MATCH($A47,CS!$B:$B,0)+COLUMN(J$1),1))} -> #N/A | BX47: 5 | BY47: 25 | BZ47: 5 | CA47: 5 | CD47: 2 | CN47: 天使 | CO47: ["山岳","雪原"] | CP47: ["死の霧"] | CQ47: 1000
A48: エンジェルズ | C48: 魔族 | D48: =SUM(AJ48:AZ48,F48:N48)&"/"&SUM(F48:N48)&"/"&SUM(AJ48:AZ48) -> 710/515/195 | E48: 2 | F48: 75 | I48: 70 | J48: 80 | K48: 80 | L48: 80 | M48: 65 | N48: 65 | O48: 170 | P48: 100 | AJ48: 50 | AK48: 0 | AL48: 75 | AM48: 0 | AN48: 25 | AO48: 0 | AP48: 0 | AQ48: 35 | AR48: 35 | AS48: -25 | AT48: -25 | AU48: -25 | AV48: -25 | AW48: 0 | AX48: 0 | AY48: 0 | AZ48: 75 | BA48: 0 | BB48: 0 | BC48: 0 | BD48: 0 | BE48: 0 | BF48: 20 | BR48: エンジェル_10 | BU48: 天使階級。性能は基礎エンジェル値を暫定継承。バード系の支援役。専用スキルは未調整。 | BX48: 5 | BY48: 25 | BZ48: 5 | CA48: 5 | CD48: 2 | CN48: 天使 | CO48: ["山岳","雪原"] | CP48: ["死の霧"]
A49: アークエンジェルズ | C49: 魔族 | D49: =SUM(AJ49:AZ49,F49:N49)&"/"&SUM(F49:N49)&"/"&SUM(AJ49:AZ49) -> 710/515/195 | E49: 3 | F49: 75 | I49: 70 | J49: 80 | K49: 80 | L49: 80 | M49: 65 | N49: 65 | O49: 170 | P49: 100 | AJ49: 50 | AK49: 0 | AL49: 75 | AM49: 0 | AN49: 25 | AO49: 0 | AP49: 0 | AQ49: 35 | AR49: 35 | AS49: -25 | AT49: -25 | AU49: -25 | AV49: -25 | AW49: 0 | AX49: 0 | AY49: 0 | AZ49: 75 | BA49: 0 | BB49: 0 | BC49: 0 | BD49: 0 | BE49: 0 | BF49: 20 | BR49: エンジェルズ_10 | BU49: 天使階級。性能は基礎エンジェル値を暫定継承。ナイト系の前衛役。専用スキルは未調整。 | BX49: 5 | BY49: 25 | BZ49: 5 | CA49: 5 | CD49: 2 | CN49: 天使 | CO49: ["山岳","雪原"] | CP49: ["死の霧"]
A50: プリンシパリティ | C50: 魔族 | D50: =SUM(AJ50:AZ50,F50:N50)&"/"&SUM(F50:N50)&"/"&SUM(AJ50:AZ50) -> 710/515/195 | E50: 4 | F50: 75 | I50: 70 | J50: 80 | K50: 80 | L50: 80 | M50: 65 | N50: 65 | O50: 170 | P50: 100 | AJ50: 50 | AK50: 0 | AL50: 75 | AM50: 0 | AN50: 25 | AO50: 0 | AP50: 0 | AQ50: 35 | AR50: 35 | AS50: -25 | AT50: -25 | AU50: -25 | AV50: -25 | AW50: 0 | AX50: 0 | AY50: 0 | AZ50: 75 | BA50: 0 | BB50: 0 | BC50: 0 | BD50: 0 | BE50: 0 | BF50: 20 | BR50: アークエンジェルズ_10 | BU50: 天使階級。性能は基礎エンジェル値を暫定継承。コマンダー系の指揮役。専用スキルは未調整。 | BX50: 5 | BY50: 25 | BZ50: 5 | CA50: 5 | CD50: 2 | CN50: 天使 | CO50: ["山岳","雪原"] | CP50: ["死の霧"]
A51: パワード | C51: 魔族 | D51: =SUM(AJ51:AZ51,F51:N51)&"/"&SUM(F51:N51)&"/"&SUM(AJ51:AZ51) -> 710/515/195 | E51: 5 | F51: 75 | I51: 70 | J51: 80 | K51: 80 | L51: 80 | M51: 65 | N51: 65 | O51: 170 | P51: 100 | AJ51: 50 | AK51: 0 | AL51: 75 | AM51: 0 | AN51: 25 | AO51: 0 | AP51: 0 | AQ51: 35 | AR51: 35 | AS51: -25 | AT51: -25 | AU51: -25 | AV51: -25 | AW51: 0 | AX51: 0 | AY51: 0 | AZ51: 75 | BA51: 0 | BB51: 0 | BC51: 0 | BD51: 0 | BE51: 0 | BF51: 20 | BR51: プリンシパリティ_10 | BU51: 天使階級。性能は基礎エンジェル値を暫定継承。パラディン系の聖戦士役。専用スキルは未調整。 | BX51: 5 | BY51: 25 | BZ51: 5 | CA51: 5 | CD51: 2 | CN51: 天使 | CO51: ["山岳","雪原"] | CP51: ["死の霧"]
A52: デュナミス | C52: 魔族 | D52: =SUM(AJ52:AZ52,F52:N52)&"/"&SUM(F52:N52)&"/"&SUM(AJ52:AZ52) -> 710/515/195 | E52: 6 | F52: 75 | I52: 70 | J52: 80 | K52: 80 | L52: 80 | M52: 65 | N52: 65 | O52: 170 | P52: 100 | AJ52: 50 | AK52: 0 | AL52: 75 | AM52: 0 | AN52: 25 | AO52: 0 | AP52: 0 | AQ52: 35 | AR52: 35 | AS52: -25 | AT52: -25 | AU52: -25 | AV52: -25 | AW52: 0 | AX52: 0 | AY52: 0 | AZ52: 75 | BA52: 0 | BB52: 0 | BC52: 0 | BD52: 0 | BE52: 0 | BF52: 20 | BR52: パワード_10 | BU52: 天使階級。性能は基礎エンジェル値を暫定継承。モンク系の近接役。専用スキルは未調整。 | BX52: 5 | BY52: 25 | BZ52: 5 | CA52: 5 | CD52: 2 | CN52: 天使 | CO52: ["山岳","雪原"] | CP52: ["死の霧"]
D53: =SUM(AJ53:AZ53,F53:N53)&"/"&SUM(F53:N53)&"/"&SUM(AJ53:AZ53) -> 0/0/0 | E53: 1 | BG53: {=IF($A53="","", INDEX(CS!$B$1:$B$15026,MATCH($A53,CS!$B:$B,0)+COLUMN(A$1),1))} | BH53: {=IF($A53="","", INDEX(CS!$B$1:$B$15026,MATCH($A53,CS!$B:$B,0)+COLUMN(B$1),1))} | BI53: {=IF($A53="","", INDEX(CS!$B$1:$B$15026,MATCH($A53,CS!$B:$B,0)+COLUMN(C$1),1))} | BJ53: {=IF($A53="","", INDEX(CS!$B$1:$B$15026,MATCH($A53,CS!$B:$B,0)+COLUMN(D$1),1))} | BK53: {=IF($A53="","", INDEX(CS!$B$1:$B$15026,MATCH($A53,CS!$B:$B,0)+COLUMN(E$1),1))} | BL53: {=IF($A53="","", INDEX(CS!$B$1:$B$15026,MATCH($A53,CS!$B:$B,0)+COLUMN(F$1),1))} | BM53: {=IF($A53="","", INDEX(CS!$B$1:$B$15026,MATCH($A53,CS!$B:$B,0)+COLUMN(G$1),1))} | BN53: {=IF($A53="","", INDEX(CS!$B$1:$B$15026,MATCH($A53,CS!$B:$B,0)+COLUMN(H$1),1))} | ... BP53: {=IF($A53="","", INDEX(CS!$B$1:$B$15026,MATCH($A53,CS!$B:$B,0)+COLUMN(J$1),1))}
B54: -=========== アンデッド ===========- | D54: =SUM(AJ54:AZ54,F54:N54)&"/"&SUM(F54:N54)&"/"&SUM(AJ54:AZ54) -> 0/0/0 | BG54: {=IF($A54="","", INDEX(CS!$B$1:$B$15026,MATCH($A54,CS!$B:$B,0)+COLUMN(A$1),1))} | BH54: {=IF($A54="","", INDEX(CS!$B$1:$B$15026,MATCH($A54,CS!$B:$B,0)+COLUMN(B$1),1))} | BI54: {=IF($A54="","", INDEX(CS!$B$1:$B$15026,MATCH($A54,CS!$B:$B,0)+COLUMN(C$1),1))} | BJ54: {=IF($A54="","", INDEX(CS!$B$1:$B$15026,MATCH($A54,CS!$B:$B,0)+COLUMN(D$1),1))} | BK54: {=IF($A54="","", INDEX(CS!$B$1:$B$15026,MATCH($A54,CS!$B:$B,0)+COLUMN(E$1),1))} | BL54: {=IF($A54="","", INDEX(CS!$B$1:$B$15026,MATCH($A54,CS!$B:$B,0)+COLUMN(F$1),1))} | BM54: {=IF($A54="","", INDEX(CS!$B$1:$B$15026,MATCH($A54,CS!$B:$B,0)+COLUMN(G$1),1))} | BN54: {=IF($A54="","", INDEX(CS!$B$1:$B$15026,MATCH($A54,CS!$B:$B,0)+COLUMN(H$1),1))} | ... BP54: {=IF($A54="","", INDEX(CS!$B$1:$B$15026,MATCH($A54,CS!$B:$B,0)+COLUMN(J$1),1))}
A55: ヴァンパイア | C55: 魔族 | D55: =SUM(AJ55:AZ55,F55:N55)&"/"&SUM(F55:N55)&"/"&SUM(AJ55:AZ55) -> 710/515/195 | E55: 1 | F55: 90 | I55: 80 | J55: 60 | K55: 80 | L55: 60 | M55: 80 | N55: 65 | O55: 170 | P55: -75 | Q55: 15 | W55: -30 | Z55: 100 | AA55: -30 | AC55: 100 | AE55: 25 | AJ55: 50 | AK55: 45 | AL55: 50 | AM55: 0 | AN55: 0 | AO55: 0 | AP55: 0 | AQ55: 50 | AR55: 50 | AS55: -25 | AT55: -25 | AU55: -25 | AV55: -25 | AW55: 0 | AX55: 0 | AY55: 50 | AZ55: 0 | BA55: 0 | BB55: 100 | BC55: 0 | BD55: 0 | BE55: 0 | BF55: 20 | BG55: {=IF($A55="","", INDEX(CS!$B$1:$B$15026,MATCH($A55,CS!$B:$B,0)+COLUMN(A$1),1))} -> 吸血 | BH55: {=IF($A55="","", INDEX(CS!$B$1:$B$15026,MATCH($A55,CS!$B:$B,0)+COLUMN(B$1),1))} | BI55: {=IF($A55="","", INDEX(CS!$B$1:$B$15026,MATCH($A55,CS!$B:$B,0)+COLUMN(C$1),1))} -> 夜の狩人 | BJ55: {=IF($A55="","", INDEX(CS!$B$1:$B$15026,MATCH($A55,CS!$B:$B,0)+COLUMN(D$1),1))} | BK55: {=IF($A55="","", INDEX(CS!$B$1:$B$15026,MATCH($A55,CS!$B:$B,0)+COLUMN(E$1),1))} -> 眷族化-ゾンビ | BL55: {=IF($A55="","", INDEX(CS!$B$1:$B$15026,MATCH($A55,CS!$B:$B,0)+COLUMN(F$1),1))} | BM55: {=IF($A55="","", INDEX(CS!$B$1:$B$15026,MATCH($A55,CS!$B:$B,0)+COLUMN(G$1),1))} -> 不死の肉体 | BN55: {=IF($A55="","", INDEX(CS!$B$1:$B$15026,MATCH($A55,CS!$B:$B,0)+COLUMN(H$1),1))} | ... BP55: {=IF($A55="","", INDEX(CS!$B$1:$B$15026,MATCH($A55,CS!$B:$B,0)+COLUMN(J$1),1))} -> 眷族化-グール | BV55: 死体 | BW55: 50 | BX55: 0 | BY55: 0 | BZ55: 10 | CA55: 5 | CB55: 0 | CC55: 35 | CD55: 2 | CN55: 吸血鬼 | CO55: ["丘陵","森"] | CP55: ["砂漠","平地"]
A56: ゾンビ | C56: 魔族 | D56: =SUM(AJ56:AZ56,F56:N56)&"/"&SUM(F56:N56)&"/"&SUM(AJ56:AZ56) -> 540/465/75 | E56: 1 | F56: 110 | I56: 110 | J56: 50 | K56: 50 | L56: 50 | M56: 35 | N56: 60 | O56: 170 | P56: -50 | W56: -25 | Z56: 35 | AA56: -25 | AB56: 25 | AC56: 100 | AD56: 35 | AE56: 25 | AG56: 25 | AI56: -25 | AJ56: 0 | AK56: 75 | AL56: 0 | AM56: 0 | AN56: 0 | AO56: 0 | AP56: 0 | AQ56: 75 | AR56: 25 | AS56: -25 | AT56: -25 | AU56: -25 | AV56: -25 | AW56: 0 | AX56: 0 | AY56: 0 | AZ56: 0 | BA56: 0 | BB56: 100 | BC56: 100 | BD56: 0 | BE56: 0 | BF56: 20 | BG56: {=IF($A56="","", INDEX(CS!$B$1:$B$15026,MATCH($A56,CS!$B:$B,0)+COLUMN(A$1),1))} -> 屍者の肉体 | BH56: {=IF($A56="","", INDEX(CS!$B$1:$B$15026,MATCH($A56,CS!$B:$B,0)+COLUMN(B$1),1))} | BI56: {=IF($A56="","", INDEX(CS!$B$1:$B$15026,MATCH($A56,CS!$B:$B,0)+COLUMN(C$1),1))} -> 痛覚鈍化 | BJ56: {=IF($A56="","", INDEX(CS!$B$1:$B$15026,MATCH($A56,CS!$B:$B,0)+COLUMN(D$1),1))} | BK56: {=IF($A56="","", INDEX(CS!$B$1:$B$15026,MATCH($A56,CS!$B:$B,0)+COLUMN(E$1),1))} -> 腐敗打撃 | BL56: {=IF($A56="","", INDEX(CS!$B$1:$B$15026,MATCH($A56,CS!$B:$B,0)+COLUMN(F$1),1))} | BM56: {=IF($A56="","", INDEX(CS!$B$1:$B$15026,MATCH($A56,CS!$B:$B,0)+COLUMN(G$1),1))} -> 死体喰らい | BN56: {=IF($A56="","", INDEX(CS!$B$1:$B$15026,MATCH($A56,CS!$B:$B,0)+COLUMN(H$1),1))} | ... BP56: {=IF($A56="","", INDEX(CS!$B$1:$B$15026,MATCH($A56,CS!$B:$B,0)+COLUMN(J$1),1))} -> 不死者 | BU56: アンデッド基礎種。ゾンビ系の起点。 | BV56: 死体 | BW56: 50 | BZ56: 75 | CD56: 2 | CN56: 動死体
A57: スケルトン | C57: 魔族 | D57: =SUM(AJ57:AZ57,F57:N57)&"/"&SUM(F57:N57)&"/"&SUM(AJ57:AZ57) -> 655/505/150 | E57: 1 | F57: 80 | I57: 75 | J57: 75 | K57: 50 | L57: 75 | M57: 75 | N57: 75 | O57: 170 | P57: -50 | Q57: 10 | W57: -35 | Z57: 100 | AA57: -35 | AB57: 25 | AC57: 100 | AE57: 100 | AJ57: 0 | AK57: 50 | AL57: 50 | AM57: 25 | AN57: 25 | AO57: 0 | AP57: 0 | AQ57: 50 | AR57: 50 | AS57: -25 | AT57: -25 | AU57: -25 | AV57: -25 | AW57: 0 | AX57: 0 | AY57: 0 | AZ57: 0 | BA57: 0 | BB57: 0 | BC57: 10 | BD57: 0 | BE57: 0 | BF57: 40 | BG57: {=IF($A57="","", INDEX(CS!$B$1:$B$15026,MATCH($A57,CS!$B:$B,0)+COLUMN(A$1),1))} -> 骨の身体 | BH57: {=IF($A57="","", INDEX(CS!$B$1:$B$15026,MATCH($A57,CS!$B:$B,0)+COLUMN(B$1),1))} | BI57: {=IF($A57="","", INDEX(CS!$B$1:$B$15026,MATCH($A57,CS!$B:$B,0)+COLUMN(C$1),1))} -> 骨格強化 | BJ57: {=IF($A57="","", INDEX(CS!$B$1:$B$15026,MATCH($A57,CS!$B:$B,0)+COLUMN(D$1),1))} | BK57: {=IF($A57="","", INDEX(CS!$B$1:$B$15026,MATCH($A57,CS!$B:$B,0)+COLUMN(E$1),1))} -> 骸骨兵 | BL57: {=IF($A57="","", INDEX(CS!$B$1:$B$15026,MATCH($A57,CS!$B:$B,0)+COLUMN(F$1),1))} | BM57: {=IF($A57="","", INDEX(CS!$B$1:$B$15026,MATCH($A57,CS!$B:$B,0)+COLUMN(G$1),1))} -> 死者の眼 | BN57: {=IF($A57="","", INDEX(CS!$B$1:$B$15026,MATCH($A57,CS!$B:$B,0)+COLUMN(H$1),1))} | ... BP57: {=IF($A57="","", INDEX(CS!$B$1:$B$15026,MATCH($A57,CS!$B:$B,0)+COLUMN(J$1),1))} -> 死者の呼び声 | BU57: アンデッド基礎種。スケルトン系の起点。 | BV57: 死体 | BW57: 50 | CD57: 2 | CN57: 骸骨
A58: ゴースト | C58: 魔族 | D58: =SUM(AJ58:AZ58,F58:N58)&"/"&SUM(F58:N58)&"/"&SUM(AJ58:AZ58) -> 710/515/195 | E58: 1 | F58: 65 | I58: 65 | J58: 50 | K58: 90 | L58: 90 | M58: 90 | N58: 65 | O58: 170 | P58: -25 | Q58: 25 | Z58: 100 | AA58: -45 | AB58: 25 | AJ58: 0 | AK58: 0 | AL58: 50 | AM58: 0 | AN58: 0 | AO58: 0 | AP58: 0 | AQ58: 100 | AR58: 50 | AS58: -25 | AT58: -25 | AU58: -25 | AV58: -25 | AW58: 0 | AX58: 0 | AY58: 95 | AZ58: 0 | BA58: 0 | BB58: 0 | BC58: 0 | BD58: 0 | BE58: 0 | BF58: 0 | BG58: {=IF($A58="","", INDEX(CS!$B$1:$B$15026,MATCH($A58,CS!$B:$B,0)+COLUMN(A$1),1))} -> 浮遊 | BH58: {=IF($A58="","", INDEX(CS!$B$1:$B$15026,MATCH($A58,CS!$B:$B,0)+COLUMN(B$1),1))} | BI58: {=IF($A58="","", INDEX(CS!$B$1:$B$15026,MATCH($A58,CS!$B:$B,0)+COLUMN(C$1),1))} -> 霊体 | BJ58: {=IF($A58="","", INDEX(CS!$B$1:$B$15026,MATCH($A58,CS!$B:$B,0)+COLUMN(D$1),1))} | BK58: {=IF($A58="","", INDEX(CS!$B$1:$B$15026,MATCH($A58,CS!$B:$B,0)+COLUMN(E$1),1))} -> 恐怖の囁き | BL58: {=IF($A58="","", INDEX(CS!$B$1:$B$15026,MATCH($A58,CS!$B:$B,0)+COLUMN(F$1),1))} | BM58: {=IF($A58="","", INDEX(CS!$B$1:$B$15026,MATCH($A58,CS!$B:$B,0)+COLUMN(G$1),1))} -> 透過 | BN58: {=IF($A58="","", INDEX(CS!$B$1:$B$15026,MATCH($A58,CS!$B:$B,0)+COLUMN(H$1),1))} | ... BP58: {=IF($A58="","", INDEX(CS!$B$1:$B$15026,MATCH($A58,CS!$B:$B,0)+COLUMN(J$1),1))} -> 完全霊体 | BU58: アンデッド基礎種。霊体系の起点。 | BV58: 魂 | BW58: 25 | CB58: 25 | CD58: 2 | CI58: × | CJ58: × | CK58: × | CN58: 幽霊
A59: グール | C59: 魔族 | D59: =SUM(AJ59:AZ59,F59:N59)&"/"&SUM(F59:N59)&"/"&SUM(AJ59:AZ59) -> 605/530/75 | E59: 2 | F59: 110 | I59: 100 | J59: 50 | K59: 50 | L59: 50 | M59: 100 | N59: 70 | O59: 170 | P59: -75 | W59: -25 | Z59: 35 | AA59: -25 | AB59: 25 | AC59: 100 | AD59: 35 | AE59: 25 | AG59: 25 | AI59: -25 | AJ59: 0 | AK59: 50 | AL59: 0 | AM59: 25 | AN59: 0 | AO59: 0 | AP59: 0 | AQ59: 75 | AR59: 25 | AS59: -25 | AT59: -25 | AU59: -25 | AV59: -25 | AW59: 0 | AX59: 0 | AY59: 0 | AZ59: 0 | BG59: {=IF($A59="","", INDEX(CS!$B$1:$B$15026,MATCH($A59,CS!$B:$B,0)+COLUMN(A$1),1))} -> 屍肉の爪 | BH59: {=IF($A59="","", INDEX(CS!$B$1:$B$15026,MATCH($A59,CS!$B:$B,0)+COLUMN(B$1),1))} | BI59: {=IF($A59="","", INDEX(CS!$B$1:$B$15026,MATCH($A59,CS!$B:$B,0)+COLUMN(C$1),1))} -> 屍肉喰らい | BJ59: {=IF($A59="","", INDEX(CS!$B$1:$B$15026,MATCH($A59,CS!$B:$B,0)+COLUMN(D$1),1))} | BK59: {=IF($A59="","", INDEX(CS!$B$1:$B$15026,MATCH($A59,CS!$B:$B,0)+COLUMN(E$1),1))} -> 腐毒爪 | BL59: {=IF($A59="","", INDEX(CS!$B$1:$B$15026,MATCH($A59,CS!$B:$B,0)+COLUMN(F$1),1))} | BM59: {=IF($A59="","", INDEX(CS!$B$1:$B$15026,MATCH($A59,CS!$B:$B,0)+COLUMN(G$1),1))} -> 飢餓の嗅覚 | BN59: {=IF($A59="","", INDEX(CS!$B$1:$B$15026,MATCH($A59,CS!$B:$B,0)+COLUMN(H$1),1))} | ... BP59: {=IF($A59="","", INDEX(CS!$B$1:$B$15026,MATCH($A59,CS!$B:$B,0)+COLUMN(J$1),1))} -> 飢餓の狂乱 | BR59: ゾンビ_10 | BU59: ゾンビから派生する上位種。
A60: ガスト | C60: 魔族 | D60: =SUM(AJ60:AZ60,F60:N60)&"/"&SUM(F60:N60)&"/"&SUM(AJ60:AZ60) -> 685/560/125 | E60: 3 | F60: 105 | I60: 110 | J60: 50 | K60: 50 | L60: 55 | M60: 110 | N60: 80 | O60: 170 | P60: -75 | W60: -25 | Z60: 35 | AA60: -25 | AB60: 25 | AC60: 100 | AD60: 35 | AE60: 25 | AG60: 25 | AI60: -25 | AJ60: 0 | AK60: 50 | AL60: 0 | AM60: 50 | AN60: 0 | AO60: 0 | AP60: 0 | AQ60: 75 | AR60: 50 | AS60: -25 | AT60: -25 | AU60: -25 | AV60: -25 | AW60: 0 | AX60: 0 | AY60: 0 | AZ60: 0 | BG60: {=IF($A60="","", INDEX(CS!$B$1:$B$15026,MATCH($A60,CS!$B:$B,0)+COLUMN(A$1),1))} -> 腐臭 | BH60: {=IF($A60="","", INDEX(CS!$B$1:$B$15026,MATCH($A60,CS!$B:$B,0)+COLUMN(B$1),1))} | BI60: {=IF($A60="","", INDEX(CS!$B$1:$B$15026,MATCH($A60,CS!$B:$B,0)+COLUMN(C$1),1))} -> 壊死爪 | BJ60: {=IF($A60="","", INDEX(CS!$B$1:$B$15026,MATCH($A60,CS!$B:$B,0)+COLUMN(D$1),1))} | BK60: {=IF($A60="","", INDEX(CS!$B$1:$B$15026,MATCH($A60,CS!$B:$B,0)+COLUMN(E$1),1))} -> 死肉再生 | BL60: {=IF($A60="","", INDEX(CS!$B$1:$B$15026,MATCH($A60,CS!$B:$B,0)+COLUMN(F$1),1))} | BM60: {=IF($A60="","", INDEX(CS!$B$1:$B$15026,MATCH($A60,CS!$B:$B,0)+COLUMN(G$1),1))} -> 飢餓感知 | BN60: {=IF($A60="","", INDEX(CS!$B$1:$B$15026,MATCH($A60,CS!$B:$B,0)+COLUMN(H$1),1))} | ... BP60: {=IF($A60="","", INDEX(CS!$B$1:$B$15026,MATCH($A60,CS!$B:$B,0)+COLUMN(J$1),1))} -> 腐乱の狂宴 | BR60: グール_10 | BU60: グールから派生する上位種。腐臭と俊敏な捕食能力を強化したアンデッド。
C61: 魔族 | D61: =SUM(AJ61:AZ61,F61:N61)&"/"&SUM(F61:N61)&"/"&SUM(AJ61:AZ61) -> 0/0/0 | BG61: {=IF($A61="","", INDEX(CS!$B$1:$B$15026,MATCH($A61,CS!$B:$B,0)+COLUMN(A$1),1))} | BH61: {=IF($A61="","", INDEX(CS!$B$1:$B$15026,MATCH($A61,CS!$B:$B,0)+COLUMN(B$1),1))} | BI61: {=IF($A61="","", INDEX(CS!$B$1:$B$15026,MATCH($A61,CS!$B:$B,0)+COLUMN(C$1),1))} | BJ61: {=IF($A61="","", INDEX(CS!$B$1:$B$15026,MATCH($A61,CS!$B:$B,0)+COLUMN(D$1),1))} | BK61: {=IF($A61="","", INDEX(CS!$B$1:$B$15026,MATCH($A61,CS!$B:$B,0)+COLUMN(E$1),1))} | BL61: {=IF($A61="","", INDEX(CS!$B$1:$B$15026,MATCH($A61,CS!$B:$B,0)+COLUMN(F$1),1))} | BM61: {=IF($A61="","", INDEX(CS!$B$1:$B$15026,MATCH($A61,CS!$B:$B,0)+COLUMN(G$1),1))} | BN61: {=IF($A61="","", INDEX(CS!$B$1:$B$15026,MATCH($A61,CS!$B:$B,0)+COLUMN(H$1),1))} | ... BP61: {=IF($A61="","", INDEX(CS!$B$1:$B$15026,MATCH($A61,CS!$B:$B,0)+COLUMN(J$1),1))} | BR61: ゾンビ_10 | BU61: ゾンビから派生する上位種。
A62: ワイト | C62: 魔族 | D62: =SUM(AJ62:AZ62,F62:N62)&"/"&SUM(F62:N62)&"/"&SUM(AJ62:AZ62) -> 530/530/0 | E62: 2 | F62: 70 | I62: 65 | J62: 60 | K62: 90 | L62: 90 | M62: 90 | N62: 65 | O62: 170 | P62: -75 | Q62: 25 | AJ62: 0 | AK62: 50 | AL62: 0 | AM62: 0 | AN62: 0 | AO62: 0 | AP62: 0 | AQ62: 0 | AR62: 0 | AS62: -25 | AT62: -25 | AU62: -25 | AV62: -25 | AW62: 0 | AX62: 0 | AY62: 50 | AZ62: 0 | BG62: {=IF($A62="","", INDEX(CS!$B$1:$B$15026,MATCH($A62,CS!$B:$B,0)+COLUMN(A$1),1))} -> 冷気の手 | BH62: {=IF($A62="","", INDEX(CS!$B$1:$B$15026,MATCH($A62,CS!$B:$B,0)+COLUMN(B$1),1))} | BI62: {=IF($A62="","", INDEX(CS!$B$1:$B$15026,MATCH($A62,CS!$B:$B,0)+COLUMN(C$1),1))} -> 生命力吸収 | BJ62: {=IF($A62="","", INDEX(CS!$B$1:$B$15026,MATCH($A62,CS!$B:$B,0)+COLUMN(D$1),1))} | BK62: {=IF($A62="","", INDEX(CS!$B$1:$B$15026,MATCH($A62,CS!$B:$B,0)+COLUMN(E$1),1))} -> 死者の威圧 | BL62: {=IF($A62="","", INDEX(CS!$B$1:$B$15026,MATCH($A62,CS!$B:$B,0)+COLUMN(F$1),1))} | BM62: {=IF($A62="","", INDEX(CS!$B$1:$B$15026,MATCH($A62,CS!$B:$B,0)+COLUMN(G$1),1))} -> 冷気纏い | BN62: {=IF($A62="","", INDEX(CS!$B$1:$B$15026,MATCH($A62,CS!$B:$B,0)+COLUMN(H$1),1))} | ... BP62: {=IF($A62="","", INDEX(CS!$B$1:$B$15026,MATCH($A62,CS!$B:$B,0)+COLUMN(J$1),1))} -> 死者の号令 | BR62: ゾンビ_10 | BU62: ゾンビから派生する上位種。
A63: リッチ | C63: 魔族 | D63: =SUM(AJ63:AZ63,F63:N63)&"/"&SUM(F63:N63)&"/"&SUM(AJ63:AZ63) -> 545/545/0 | E63: 3 | F63: 70 | I63: 65 | J63: 70 | K63: 90 | L63: 90 | M63: 90 | N63: 70 | O63: 170 | P63: -100 | Q63: 25 | AJ63: 0 | AK63: 0 | AL63: 75 | AM63: 0 | AN63: 25 | AO63: 0 | AP63: 0 | AQ63: 0 | AR63: 0 | AS63: -25 | AT63: -25 | AU63: -25 | AV63: -25 | AW63: 25 | AX63: 0 | AY63: 75 | AZ63: -100 | BG63: {=IF($A63="","", INDEX(CS!$B$1:$B$15026,MATCH($A63,CS!$B:$B,0)+COLUMN(A$1),1))} -> 死霊魔力 | BH63: {=IF($A63="","", INDEX(CS!$B$1:$B$15026,MATCH($A63,CS!$B:$B,0)+COLUMN(B$1),1))} | BI63: {=IF($A63="","", INDEX(CS!$B$1:$B$15026,MATCH($A63,CS!$B:$B,0)+COLUMN(C$1),1))} -> 骨魂障壁 | BJ63: {=IF($A63="","", INDEX(CS!$B$1:$B$15026,MATCH($A63,CS!$B:$B,0)+COLUMN(D$1),1))} | BK63: {=IF($A63="","", INDEX(CS!$B$1:$B$15026,MATCH($A63,CS!$B:$B,0)+COLUMN(E$1),1))} -> 魂吸収 | BL63: {=IF($A63="","", INDEX(CS!$B$1:$B$15026,MATCH($A63,CS!$B:$B,0)+COLUMN(F$1),1))} | BM63: {=IF($A63="","", INDEX(CS!$B$1:$B$15026,MATCH($A63,CS!$B:$B,0)+COLUMN(G$1),1))} -> 死霊術師 | BN63: {=IF($A63="","", INDEX(CS!$B$1:$B$15026,MATCH($A63,CS!$B:$B,0)+COLUMN(H$1),1))} | ... BP63: {=IF($A63="","", INDEX(CS!$B$1:$B$15026,MATCH($A63,CS!$B:$B,0)+COLUMN(J$1),1))} -> 不死の魔導核 | BR63: スケルトン_10 | BU63: スケルトンから派生する上位種。
A64: レヴナント | C64: 魔族 | D64: =SUM(AJ64:AZ64,F64:N64)&"/"&SUM(F64:N64)&"/"&SUM(AJ64:AZ64) -> 580/505/75 | E64: 2 | F64: 110 | I64: 110 | J64: 60 | K64: 50 | L64: 60 | M64: 50 | N64: 65 | O64: 170 | P64: -50 | W64: -25 | Z64: 35 | AA64: -25 | AB64: 25 | AC64: 100 | AD64: 35 | AE64: 25 | AG64: 25 | AI64: -25 | AJ64: 0 | AK64: 50 | AL64: 0 | AM64: 25 | AN64: 0 | AO64: 0 | AP64: 0 | AQ64: 50 | AR64: 25 | AS64: -25 | AT64: -25 | AU64: -25 | AV64: -25 | AW64: 25 | AX64: 0 | AY64: 0 | AZ64: 0 | BG64: {=IF($A64="","", INDEX(CS!$B$1:$B$15026,MATCH($A64,CS!$B:$B,0)+COLUMN(A$1),1))} -> 執念打撃 | BH64: {=IF($A64="","", INDEX(CS!$B$1:$B$15026,MATCH($A64,CS!$B:$B,0)+COLUMN(B$1),1))} | BI64: {=IF($A64="","", INDEX(CS!$B$1:$B$15026,MATCH($A64,CS!$B:$B,0)+COLUMN(C$1),1))} -> 復讐の執念 | BJ64: {=IF($A64="","", INDEX(CS!$B$1:$B$15026,MATCH($A64,CS!$B:$B,0)+COLUMN(D$1),1))} | BK64: {=IF($A64="","", INDEX(CS!$B$1:$B$15026,MATCH($A64,CS!$B:$B,0)+COLUMN(E$1),1))} -> 死なずの肉体 | BL64: {=IF($A64="","", INDEX(CS!$B$1:$B$15026,MATCH($A64,CS!$B:$B,0)+COLUMN(F$1),1))} | BM64: {=IF($A64="","", INDEX(CS!$B$1:$B$15026,MATCH($A64,CS!$B:$B,0)+COLUMN(G$1),1))} -> 執念の追跡 | BN64: {=IF($A64="","", INDEX(CS!$B$1:$B$15026,MATCH($A64,CS!$B:$B,0)+COLUMN(H$1),1))} | ... BP64: {=IF($A64="","", INDEX(CS!$B$1:$B$15026,MATCH($A64,CS!$B:$B,0)+COLUMN(J$1),1))} -> 黄泉返り | BR64: ゾンビ_10 | BU64: ゾンビから派生する上位種。
A65: ドゥームゾンビ | C65: 魔族 | D65: =SUM(AJ65:AZ65,F65:N65)&"/"&SUM(F65:N65)&"/"&SUM(AJ65:AZ65) -> 635/560/75 | E65: 3 | F65: 115 | I65: 110 | J65: 65 | K65: 50 | L65: 75 | M65: 75 | N65: 70 | O65: 170 | P65: -75 | W65: -25 | Z65: 35 | AA65: -25 | AB65: 25 | AC65: 100 | AD65: 35 | AE65: 25 | AG65: 25 | AI65: -25 | AJ65: 0 | AK65: 75 | AL65: 0 | AM65: 0 | AN65: 0 | AO65: 0 | AP65: 0 | AQ65: 75 | AR65: 25 | AS65: -25 | AT65: -25 | AU65: -25 | AV65: -25 | AW65: 0 | AX65: 0 | AY65: 0 | AZ65: 0 | BG65: {=IF($A65="","", INDEX(CS!$B$1:$B$15026,MATCH($A65,CS!$B:$B,0)+COLUMN(A$1),1))} -> #N/A | BH65: {=IF($A65="","", INDEX(CS!$B$1:$B$15026,MATCH($A65,CS!$B:$B,0)+COLUMN(B$1),1))} -> #N/A | BI65: {=IF($A65="","", INDEX(CS!$B$1:$B$15026,MATCH($A65,CS!$B:$B,0)+COLUMN(C$1),1))} -> #N/A | BJ65: {=IF($A65="","", INDEX(CS!$B$1:$B$15026,MATCH($A65,CS!$B:$B,0)+COLUMN(D$1),1))} -> #N/A | BK65: {=IF($A65="","", INDEX(CS!$B$1:$B$15026,MATCH($A65,CS!$B:$B,0)+COLUMN(E$1),1))} -> #N/A | BL65: {=IF($A65="","", INDEX(CS!$B$1:$B$15026,MATCH($A65,CS!$B:$B,0)+COLUMN(F$1),1))} -> #N/A | BM65: {=IF($A65="","", INDEX(CS!$B$1:$B$15026,MATCH($A65,CS!$B:$B,0)+COLUMN(G$1),1))} -> #N/A | BN65: {=IF($A65="","", INDEX(CS!$B$1:$B$15026,MATCH($A65,CS!$B:$B,0)+COLUMN(H$1),1))} -> #N/A | ... BP65: {=IF($A65="","", INDEX(CS!$B$1:$B$15026,MATCH($A65,CS!$B:$B,0)+COLUMN(J$1),1))} -> #N/A | BR65: レヴナント_10
A66: レイス | C66: 魔族 | D66: =SUM(AJ66:AZ66,F66:N66)&"/"&SUM(F66:N66)&"/"&SUM(AJ66:AZ66) -> 530/530/0 | E66: 2 | F66: 65 | I66: 65 | J66: 45 | K66: 95 | L66: 95 | M66: 90 | N66: 75 | O66: 170 | P66: -75 | AJ66: 0 | AK66: 0 | AL66: 0 | AM66: 0 | AN66: 0 | AO66: 0 | AP66: 0 | AQ66: 50 | AR66: 0 | AS66: -25 | AT66: -25 | AU66: -25 | AV66: -25 | AW66: 0 | AX66: 0 | AY66: 50 | AZ66: 0 | BG66: {=IF($A66="","", INDEX(CS!$B$1:$B$15026,MATCH($A66,CS!$B:$B,0)+COLUMN(A$1),1))} -> 霊刃 | BH66: {=IF($A66="","", INDEX(CS!$B$1:$B$15026,MATCH($A66,CS!$B:$B,0)+COLUMN(B$1),1))} | BI66: {=IF($A66="","", INDEX(CS!$B$1:$B$15026,MATCH($A66,CS!$B:$B,0)+COLUMN(C$1),1))} -> 影潜り | BJ66: {=IF($A66="","", INDEX(CS!$B$1:$B$15026,MATCH($A66,CS!$B:$B,0)+COLUMN(D$1),1))} | BK66: {=IF($A66="","", INDEX(CS!$B$1:$B$15026,MATCH($A66,CS!$B:$B,0)+COLUMN(E$1),1))} -> 霊体強化 | BL66: {=IF($A66="","", INDEX(CS!$B$1:$B$15026,MATCH($A66,CS!$B:$B,0)+COLUMN(F$1),1))} | BM66: {=IF($A66="","", INDEX(CS!$B$1:$B$15026,MATCH($A66,CS!$B:$B,0)+COLUMN(G$1),1))} -> 魂削り | BN66: {=IF($A66="","", INDEX(CS!$B$1:$B$15026,MATCH($A66,CS!$B:$B,0)+COLUMN(H$1),1))} | ... BP66: {=IF($A66="","", INDEX(CS!$B$1:$B$15026,MATCH($A66,CS!$B:$B,0)+COLUMN(J$1),1))} -> 死の接触 | BR66: ゴースト_10 | BU66: ゴーストから派生する上位霊体。
A67: バンシー | C67: 魔族 | D67: =SUM(AJ67:AZ67,F67:N67)&"/"&SUM(F67:N67)&"/"&SUM(AJ67:AZ67) -> 555/555/0 | E67: 3 | F67: 60 | I67: 55 | J67: 40 | K67: 110 | L67: 115 | M67: 100 | N67: 75 | O67: 170 | P67: -75 | AJ67: 0 | AK67: 50 | AL67: 0 | AM67: 0 | AN67: 0 | AO67: 0 | AP67: 0 | AQ67: 0 | AR67: 0 | AS67: -25 | AT67: -25 | AU67: -25 | AV67: -25 | AW67: 0 | AX67: 0 | AY67: 50 | AZ67: 0 | BG67: {=IF($A67="","", INDEX(CS!$B$1:$B$15026,MATCH($A67,CS!$B:$B,0)+COLUMN(A$1),1))} -> 嘆きの声 | BH67: {=IF($A67="","", INDEX(CS!$B$1:$B$15026,MATCH($A67,CS!$B:$B,0)+COLUMN(B$1),1))} | BI67: {=IF($A67="","", INDEX(CS!$B$1:$B$15026,MATCH($A67,CS!$B:$B,0)+COLUMN(C$1),1))} -> バンシーの絶叫 | BJ67: {=IF($A67="","", INDEX(CS!$B$1:$B$15026,MATCH($A67,CS!$B:$B,0)+COLUMN(D$1),1))} | BK67: {=IF($A67="","", INDEX(CS!$B$1:$B$15026,MATCH($A67,CS!$B:$B,0)+COLUMN(E$1),1))} -> 悲嘆の霊体 | BL67: {=IF($A67="","", INDEX(CS!$B$1:$B$15026,MATCH($A67,CS!$B:$B,0)+COLUMN(F$1),1))} | BM67: {=IF($A67="","", INDEX(CS!$B$1:$B$15026,MATCH($A67,CS!$B:$B,0)+COLUMN(G$1),1))} -> 予兆の泣き声 | BN67: {=IF($A67="","", INDEX(CS!$B$1:$B$15026,MATCH($A67,CS!$B:$B,0)+COLUMN(H$1),1))} | ... BP67: {=IF($A67="","", INDEX(CS!$B$1:$B$15026,MATCH($A67,CS!$B:$B,0)+COLUMN(J$1),1))} -> 死を告げる絶叫 | BR67: ゴースト_10 | BU67: ゴーストから派生する上位霊体。
A68: ギャザード・グラッジ | C68: 魔族 | D68: =SUM(AJ68:AZ68,F68:N68)&"/"&SUM(F68:N68)&"/"&SUM(AJ68:AZ68) -> 565/565/0 | E68: 3 | F68: 85 | I68: 70 | J68: 50 | K68: 100 | L68: 110 | M68: 80 | N68: 70 | O68: 170 | P68: -100 | AJ68: 0 | AK68: 75 | AL68: 0 | AM68: 0 | AN68: 0 | AO68: 0 | AP68: 0 | AQ68: 0 | AR68: 0 | AS68: -25 | AT68: -25 | AU68: -25 | AV68: -25 | AW68: 0 | AX68: 0 | AY68: 25 | AZ68: 0 | BG68: {=IF($A68="","", INDEX(CS!$B$1:$B$15026,MATCH($A68,CS!$B:$B,0)+COLUMN(A$1),1))} -> #N/A | BH68: {=IF($A68="","", INDEX(CS!$B$1:$B$15026,MATCH($A68,CS!$B:$B,0)+COLUMN(B$1),1))} -> #N/A | BI68: {=IF($A68="","", INDEX(CS!$B$1:$B$15026,MATCH($A68,CS!$B:$B,0)+COLUMN(C$1),1))} -> #N/A | BJ68: {=IF($A68="","", INDEX(CS!$B$1:$B$15026,MATCH($A68,CS!$B:$B,0)+COLUMN(D$1),1))} -> #N/A | BK68: {=IF($A68="","", INDEX(CS!$B$1:$B$15026,MATCH($A68,CS!$B:$B,0)+COLUMN(E$1),1))} -> #N/A | BL68: {=IF($A68="","", INDEX(CS!$B$1:$B$15026,MATCH($A68,CS!$B:$B,0)+COLUMN(F$1),1))} -> #N/A | BM68: {=IF($A68="","", INDEX(CS!$B$1:$B$15026,MATCH($A68,CS!$B:$B,0)+COLUMN(G$1),1))} -> #N/A | BN68: {=IF($A68="","", INDEX(CS!$B$1:$B$15026,MATCH($A68,CS!$B:$B,0)+COLUMN(H$1),1))} -> #N/A | ... BP68: {=IF($A68="","", INDEX(CS!$B$1:$B$15026,MATCH($A68,CS!$B:$B,0)+COLUMN(J$1),1))} -> #N/A | BR68: レイス_10 | BU68: レイスから派生する上位霊体。
A69: デュラハン | C69: 魔族 | D69: =SUM(AJ69:AZ69,F69:N69)&"/"&SUM(F69:N69)&"/"&SUM(AJ69:AZ69) -> 535/535/0 | E69: 2 | F69: 100 | I69: 105 | J69: 80 | K69: 50 | L69: 65 | M69: 65 | N69: 70 | O69: 170 | P69: -50 | AJ69: 25 | AK69: 25 | AL69: 0 | AM69: 0 | AN69: 25 | AO69: 0 | AP69: 0 | AQ69: 0 | AR69: 25 | AS69: -25 | AT69: -25 | AU69: -25 | AV69: -25 | AW69: 0 | AX69: 0 | AY69: 0 | AZ69: 0 | BG69: {=IF($A69="","", INDEX(CS!$B$1:$B$15026,MATCH($A69,CS!$B:$B,0)+COLUMN(A$1),1))} -> 首無し騎士 | BH69: {=IF($A69="","", INDEX(CS!$B$1:$B$15026,MATCH($A69,CS!$B:$B,0)+COLUMN(B$1),1))} | BI69: {=IF($A69="","", INDEX(CS!$B$1:$B$15026,MATCH($A69,CS!$B:$B,0)+COLUMN(C$1),1))} -> 首狩り | BJ69: {=IF($A69="","", INDEX(CS!$B$1:$B$15026,MATCH($A69,CS!$B:$B,0)+COLUMN(D$1),1))} | BK69: {=IF($A69="","", INDEX(CS!$B$1:$B$15026,MATCH($A69,CS!$B:$B,0)+COLUMN(E$1),1))} -> 黒鎧 | BL69: {=IF($A69="","", INDEX(CS!$B$1:$B$15026,MATCH($A69,CS!$B:$B,0)+COLUMN(F$1),1))} | BM69: {=IF($A69="","", INDEX(CS!$B$1:$B$15026,MATCH($A69,CS!$B:$B,0)+COLUMN(G$1),1))} -> 死騎士の突撃 | BN69: {=IF($A69="","", INDEX(CS!$B$1:$B$15026,MATCH($A69,CS!$B:$B,0)+COLUMN(H$1),1))} | ... BP69: {=IF($A69="","", INDEX(CS!$B$1:$B$15026,MATCH($A69,CS!$B:$B,0)+COLUMN(J$1),1))} -> 死騎士の威光 | BR69: ゾンビ_10 | BU69: ゾンビから派生する武装アンデッド上位種。
A70: 蒼炎のデュラハン | C70: 魔族 | D70: =SUM(AJ70:AZ70,F70:N70)&"/"&SUM(F70:N70)&"/"&SUM(AJ70:AZ70) -> 560/560/0 | E70: 3 | F70: 100 | I70: 105 | J70: 80 | K70: 60 | L70: 70 | M70: 70 | N70: 75 | O70: 170 | P70: -50 | AJ70: 25 | AK70: 25 | AL70: 0 | AM70: 0 | AN70: 0 | AO70: 0 | AP70: 0 | AQ70: 0 | AR70: 25 | AS70: -25 | AT70: -25 | AU70: -25 | AV70: -25 | AW70: 0 | AX70: 0 | AY70: 25 | AZ70: 0 | BG70: {=IF($A70="","", INDEX(CS!$B$1:$B$15026,MATCH($A70,CS!$B:$B,0)+COLUMN(A$1),1))} -> 蒼炎の鎧 | BH70: {=IF($A70="","", INDEX(CS!$B$1:$B$15026,MATCH($A70,CS!$B:$B,0)+COLUMN(B$1),1))} | BI70: {=IF($A70="","", INDEX(CS!$B$1:$B$15026,MATCH($A70,CS!$B:$B,0)+COLUMN(C$1),1))} -> 蒼炎斬 | BJ70: {=IF($A70="","", INDEX(CS!$B$1:$B$15026,MATCH($A70,CS!$B:$B,0)+COLUMN(D$1),1))} | BK70: {=IF($A70="","", INDEX(CS!$B$1:$B$15026,MATCH($A70,CS!$B:$B,0)+COLUMN(E$1),1))} -> 蒼炎纏い | BL70: {=IF($A70="","", INDEX(CS!$B$1:$B$15026,MATCH($A70,CS!$B:$B,0)+COLUMN(F$1),1))} | BM70: {=IF($A70="","", INDEX(CS!$B$1:$B$15026,MATCH($A70,CS!$B:$B,0)+COLUMN(G$1),1))} -> 鬼火突撃 | BN70: {=IF($A70="","", INDEX(CS!$B$1:$B$15026,MATCH($A70,CS!$B:$B,0)+COLUMN(H$1),1))} | ... BP70: {=IF($A70="","", INDEX(CS!$B$1:$B$15026,MATCH($A70,CS!$B:$B,0)+COLUMN(J$1),1))} -> 蒼炎騎士王 | BR70: デュラハン_10 | BU70: デュラハンから派生する上位種。
C71: 魔族 | D71: =SUM(AJ71:AZ71,F71:N71)&"/"&SUM(F71:N71)&"/"&SUM(AJ71:AZ71) -> 0/0/0 | E71: 1 | BG71: {=IF($A71="","", INDEX(CS!$B$1:$B$15026,MATCH($A71,CS!$B:$B,0)+COLUMN(A$1),1))} | BH71: {=IF($A71="","", INDEX(CS!$B$1:$B$15026,MATCH($A71,CS!$B:$B,0)+COLUMN(B$1),1))} | BI71: {=IF($A71="","", INDEX(CS!$B$1:$B$15026,MATCH($A71,CS!$B:$B,0)+COLUMN(C$1),1))} | BJ71: {=IF($A71="","", INDEX(CS!$B$1:$B$15026,MATCH($A71,CS!$B:$B,0)+COLUMN(D$1),1))} | BK71: {=IF($A71="","", INDEX(CS!$B$1:$B$15026,MATCH($A71,CS!$B:$B,0)+COLUMN(E$1),1))} | BL71: {=IF($A71="","", INDEX(CS!$B$1:$B$15026,MATCH($A71,CS!$B:$B,0)+COLUMN(F$1),1))} | BM71: {=IF($A71="","", INDEX(CS!$B$1:$B$15026,MATCH($A71,CS!$B:$B,0)+COLUMN(G$1),1))} | BN71: {=IF($A71="","", INDEX(CS!$B$1:$B$15026,MATCH($A71,CS!$B:$B,0)+COLUMN(H$1),1))} | ... BP71: {=IF($A71="","", INDEX(CS!$B$1:$B$15026,MATCH($A71,CS!$B:$B,0)+COLUMN(J$1),1))}
C72: 魔族 | D72: =SUM(AJ72:AZ72,F72:N72)&"/"&SUM(F72:N72)&"/"&SUM(AJ72:AZ72) -> 0/0/0 | E72: 1 | BG72: {=IF($A72="","", INDEX(CS!$B$1:$B$15026,MATCH($A72,CS!$B:$B,0)+COLUMN(A$1),1))} | BH72: {=IF($A72="","", INDEX(CS!$B$1:$B$15026,MATCH($A72,CS!$B:$B,0)+COLUMN(B$1),1))} | BI72: {=IF($A72="","", INDEX(CS!$B$1:$B$15026,MATCH($A72,CS!$B:$B,0)+COLUMN(C$1),1))} | BJ72: {=IF($A72="","", INDEX(CS!$B$1:$B$15026,MATCH($A72,CS!$B:$B,0)+COLUMN(D$1),1))} | BK72: {=IF($A72="","", INDEX(CS!$B$1:$B$15026,MATCH($A72,CS!$B:$B,0)+COLUMN(E$1),1))} | BL72: {=IF($A72="","", INDEX(CS!$B$1:$B$15026,MATCH($A72,CS!$B:$B,0)+COLUMN(F$1),1))} | BM72: {=IF($A72="","", INDEX(CS!$B$1:$B$15026,MATCH($A72,CS!$B:$B,0)+COLUMN(G$1),1))} | BN72: {=IF($A72="","", INDEX(CS!$B$1:$B$15026,MATCH($A72,CS!$B:$B,0)+COLUMN(H$1),1))} | ... BP72: {=IF($A72="","", INDEX(CS!$B$1:$B$15026,MATCH($A72,CS!$B:$B,0)+COLUMN(J$1),1))}
C73: 魔族 | D73: =SUM(AJ73:AZ73,F73:N73)&"/"&SUM(F73:N73)&"/"&SUM(AJ73:AZ73) -> 0/0/0 | E73: 1 | BG73: {=IF($A73="","", INDEX(CS!$B$1:$B$15026,MATCH($A73,CS!$B:$B,0)+COLUMN(A$1),1))} | BH73: {=IF($A73="","", INDEX(CS!$B$1:$B$15026,MATCH($A73,CS!$B:$B,0)+COLUMN(B$1),1))} | BI73: {=IF($A73="","", INDEX(CS!$B$1:$B$15026,MATCH($A73,CS!$B:$B,0)+COLUMN(C$1),1))} | BJ73: {=IF($A73="","", INDEX(CS!$B$1:$B$15026,MATCH($A73,CS!$B:$B,0)+COLUMN(D$1),1))} | BK73: {=IF($A73="","", INDEX(CS!$B$1:$B$15026,MATCH($A73,CS!$B:$B,0)+COLUMN(E$1),1))} | BL73: {=IF($A73="","", INDEX(CS!$B$1:$B$15026,MATCH($A73,CS!$B:$B,0)+COLUMN(F$1),1))} | BM73: {=IF($A73="","", INDEX(CS!$B$1:$B$15026,MATCH($A73,CS!$B:$B,0)+COLUMN(G$1),1))} | BN73: {=IF($A73="","", INDEX(CS!$B$1:$B$15026,MATCH($A73,CS!$B:$B,0)+COLUMN(H$1),1))} | ... BP73: {=IF($A73="","", INDEX(CS!$B$1:$B$15026,MATCH($A73,CS!$B:$B,0)+COLUMN(J$1),1))}
A74: フレイムエレメンタル | B74: 精霊 | C74: 魔族 | D74: =SUM(AJ74:AZ74,F74:N74)&"/"&SUM(F74:N74)&"/"&SUM(AJ74:AZ74) -> 690/515/175 | E74: 1 | F74: 75 | I74: 55 | J74: 60 | K74: 100 | L74: 85 | M74: 75 | N74: 65 | O74: 140 | P74: 0 | Q74: 15 | T74: 100 | U74: -45 | W74: 100 | X74: -45 | AE74: 100 | AJ74: 0 | AK74: 0 | AL74: 75 | AM74: 0 | AN74: 0 | AO74: 0 | AP74: 0 | AQ74: 75 | AR74: 25 | AS74: -25 | AT74: -25 | AU74: -25 | AV74: -25 | AW74: 0 | AX74: 0 | AY74: 100 | AZ74: 0 | BG74: {=IF($A74="","", INDEX(CS!$B$1:$B$15026,MATCH($A74,CS!$B:$B,0)+COLUMN(A$1),1))} -> 炎の拳 | BH74: {=IF($A74="","", INDEX(CS!$B$1:$B$15026,MATCH($A74,CS!$B:$B,0)+COLUMN(B$1),1))} | BI74: {=IF($A74="","", INDEX(CS!$B$1:$B$15026,MATCH($A74,CS!$B:$B,0)+COLUMN(C$1),1))} -> 浮遊 | BJ74: {=IF($A74="","", INDEX(CS!$B$1:$B$15026,MATCH($A74,CS!$B:$B,0)+COLUMN(D$1),1))} | BK74: {=IF($A74="","", INDEX(CS!$B$1:$B$15026,MATCH($A74,CS!$B:$B,0)+COLUMN(E$1),1))} -> 火炎 | BL74: {=IF($A74="","", INDEX(CS!$B$1:$B$15026,MATCH($A74,CS!$B:$B,0)+COLUMN(F$1),1))} -> 炎の魔力 | BM74: {=IF($A74="","", INDEX(CS!$B$1:$B$15026,MATCH($A74,CS!$B:$B,0)+COLUMN(G$1),1))} | BN74: {=IF($A74="","", INDEX(CS!$B$1:$B$15026,MATCH($A74,CS!$B:$B,0)+COLUMN(H$1),1))} | ... BP74: {=IF($A74="","", INDEX(CS!$B$1:$B$15026,MATCH($A74,CS!$B:$B,0)+COLUMN(J$1),1))} -> 炎の吐息 | CD74: 1 | CI74: × | CJ74: × | CK74: × | CN74: 精霊
A75: フロストエレメンタル | B75: 精霊 | C75: 魔族 | D75: =SUM(AJ75:AZ75,F75:N75)&"/"&SUM(F75:N75)&"/"&SUM(AJ75:AZ75) -> 690/515/175 | E75: 1 | F75: 75 | I75: 55 | J75: 60 | K75: 100 | L75: 85 | M75: 75 | N75: 65 | O75: 140 | P75: 0 | Q75: 15 | T75: -45 | U75: 100 | W75: -45 | X75: 100 | AE75: 100 | AJ75: 0 | AK75: 0 | AL75: 75 | AM75: 0 | AN75: 0 | AO75: 0 | AP75: 0 | AQ75: 75 | AR75: 25 | AS75: -25 | AT75: -25 | AU75: -25 | AV75: -25 | AW75: 0 | AX75: 0 | AY75: 100 | AZ75: 0 | BG75: {=IF($A75="","", INDEX(CS!$B$1:$B$15026,MATCH($A75,CS!$B:$B,0)+COLUMN(A$1),1))} -> 氷の拳 | BH75: {=IF($A75="","", INDEX(CS!$B$1:$B$15026,MATCH($A75,CS!$B:$B,0)+COLUMN(B$1),1))} | BI75: {=IF($A75="","", INDEX(CS!$B$1:$B$15026,MATCH($A75,CS!$B:$B,0)+COLUMN(C$1),1))} -> 浮遊 | BJ75: {=IF($A75="","", INDEX(CS!$B$1:$B$15026,MATCH($A75,CS!$B:$B,0)+COLUMN(D$1),1))} | BK75: {=IF($A75="","", INDEX(CS!$B$1:$B$15026,MATCH($A75,CS!$B:$B,0)+COLUMN(E$1),1))} -> 冷気の光線 | BL75: {=IF($A75="","", INDEX(CS!$B$1:$B$15026,MATCH($A75,CS!$B:$B,0)+COLUMN(F$1),1))} -> 氷の魔力 | BM75: {=IF($A75="","", INDEX(CS!$B$1:$B$15026,MATCH($A75,CS!$B:$B,0)+COLUMN(G$1),1))} | BN75: {=IF($A75="","", INDEX(CS!$B$1:$B$15026,MATCH($A75,CS!$B:$B,0)+COLUMN(H$1),1))} | ... BP75: {=IF($A75="","", INDEX(CS!$B$1:$B$15026,MATCH($A75,CS!$B:$B,0)+COLUMN(J$1),1))} -> 氷の吐息 | CD75: 1 | CN75: 精霊
A76: ウォーターエレメンタル | B76: 精霊 | C76: 魔族 | D76: =SUM(AJ76:AZ76,F76:N76)&"/"&SUM(F76:N76)&"/"&SUM(AJ76:AZ76) -> 690/515/175 | E76: 1 | F76: 75 | I76: 55 | J76: 60 | K76: 100 | L76: 85 | M76: 75 | N76: 65 | O76: 140 | P76: 0 | Q76: 15 | T76: -45 | U76: 100 | W76: -45 | X76: 100 | AE76: 100 | AJ76: 0 | AK76: 0 | AL76: 75 | AM76: 0 | AN76: 0 | AO76: 0 | AP76: 0 | AQ76: 75 | AR76: 25 | AS76: -25 | AT76: -25 | AU76: -25 | AV76: -25 | AW76: 0 | AX76: 0 | AY76: 100 | AZ76: 0 | BG76: {=IF($A76="","", INDEX(CS!$B$1:$B$15026,MATCH($A76,CS!$B:$B,0)+COLUMN(A$1),1))} -> 水の拳 | BH76: {=IF($A76="","", INDEX(CS!$B$1:$B$15026,MATCH($A76,CS!$B:$B,0)+COLUMN(B$1),1))} | BI76: {=IF($A76="","", INDEX(CS!$B$1:$B$15026,MATCH($A76,CS!$B:$B,0)+COLUMN(C$1),1))} -> 水の精霊 | BJ76: {=IF($A76="","", INDEX(CS!$B$1:$B$15026,MATCH($A76,CS!$B:$B,0)+COLUMN(D$1),1))} | BK76: {=IF($A76="","", INDEX(CS!$B$1:$B$15026,MATCH($A76,CS!$B:$B,0)+COLUMN(E$1),1))} -> 水力 | BL76: {=IF($A76="","", INDEX(CS!$B$1:$B$15026,MATCH($A76,CS!$B:$B,0)+COLUMN(F$1),1))} -> 水の魔力 | BM76: {=IF($A76="","", INDEX(CS!$B$1:$B$15026,MATCH($A76,CS!$B:$B,0)+COLUMN(G$1),1))} | BN76: {=IF($A76="","", INDEX(CS!$B$1:$B$15026,MATCH($A76,CS!$B:$B,0)+COLUMN(H$1),1))} | ... BP76: {=IF($A76="","", INDEX(CS!$B$1:$B$15026,MATCH($A76,CS!$B:$B,0)+COLUMN(J$1),1))} -> 水の吐息 | CD76: 1 | CN76: 精霊
A77: エアエレメンタル | B77: 精霊 | C77: 魔族 | D77: =SUM(AJ77:AZ77,F77:N77)&"/"&SUM(F77:N77)&"/"&SUM(AJ77:AZ77) -> 690/515/175 | E77: 1 | F77: 75 | I77: 55 | J77: 60 | K77: 100 | L77: 85 | M77: 75 | N77: 65 | O77: 140 | P77: 0 | Q77: -15 | V77: 100 | Y77: 100 | AE77: 100 | AJ77: 0 | AK77: 0 | AL77: 75 | AM77: 0 | AN77: 0 | AO77: 0 | AP77: 0 | AQ77: 75 | AR77: 25 | AS77: -25 | AT77: -25 | AU77: -25 | AV77: -25 | AW77: 0 | AX77: 0 | AY77: 100 | AZ77: 0 | BG77: {=IF($A77="","", INDEX(CS!$B$1:$B$15026,MATCH($A77,CS!$B:$B,0)+COLUMN(A$1),1))} -> 風の拳 | BH77: {=IF($A77="","", INDEX(CS!$B$1:$B$15026,MATCH($A77,CS!$B:$B,0)+COLUMN(B$1),1))} | BI77: {=IF($A77="","", INDEX(CS!$B$1:$B$15026,MATCH($A77,CS!$B:$B,0)+COLUMN(C$1),1))} -> 浮遊 | BJ77: {=IF($A77="","", INDEX(CS!$B$1:$B$15026,MATCH($A77,CS!$B:$B,0)+COLUMN(D$1),1))} | BK77: {=IF($A77="","", INDEX(CS!$B$1:$B$15026,MATCH($A77,CS!$B:$B,0)+COLUMN(E$1),1))} -> 突風 | BL77: {=IF($A77="","", INDEX(CS!$B$1:$B$15026,MATCH($A77,CS!$B:$B,0)+COLUMN(F$1),1))} -> 風の魔力 | BM77: {=IF($A77="","", INDEX(CS!$B$1:$B$15026,MATCH($A77,CS!$B:$B,0)+COLUMN(G$1),1))} | BN77: {=IF($A77="","", INDEX(CS!$B$1:$B$15026,MATCH($A77,CS!$B:$B,0)+COLUMN(H$1),1))} | ... BP77: {=IF($A77="","", INDEX(CS!$B$1:$B$15026,MATCH($A77,CS!$B:$B,0)+COLUMN(J$1),1))} -> 風の吐息 | CD77: 1 | CN77: 精霊
A78: アースエレメンタル | B78: 精霊 | C78: 魔族 | D78: =SUM(AJ78:AZ78,F78:N78)&"/"&SUM(F78:N78)&"/"&SUM(AJ78:AZ78) -> 700/525/175 | E78: 1 | F78: 90 | I78: 90 | J78: 80 | K78: 100 | L78: 50 | M78: 50 | N78: 65 | O78: 140 | P78: 0 | Q78: 15 | Z78: -45 | AE78: 100 | AJ78: 0 | AK78: 0 | AL78: 75 | AM78: 0 | AN78: 0 | AO78: 0 | AP78: 0 | AQ78: 75 | AR78: 25 | AS78: -25 | AT78: -25 | AU78: -25 | AV78: -25 | AW78: 0 | AX78: 0 | AY78: 100 | AZ78: 0 | BG78: {=IF($A78="","", INDEX(CS!$B$1:$B$15026,MATCH($A78,CS!$B:$B,0)+COLUMN(A$1),1))} -> 地の拳 | BH78: {=IF($A78="","", INDEX(CS!$B$1:$B$15026,MATCH($A78,CS!$B:$B,0)+COLUMN(B$1),1))} | BI78: {=IF($A78="","", INDEX(CS!$B$1:$B$15026,MATCH($A78,CS!$B:$B,0)+COLUMN(C$1),1))} -> 浮遊 | BJ78: {=IF($A78="","", INDEX(CS!$B$1:$B$15026,MATCH($A78,CS!$B:$B,0)+COLUMN(D$1),1))} | BK78: {=IF($A78="","", INDEX(CS!$B$1:$B$15026,MATCH($A78,CS!$B:$B,0)+COLUMN(E$1),1))} -> 魔法の石 | BL78: {=IF($A78="","", INDEX(CS!$B$1:$B$15026,MATCH($A78,CS!$B:$B,0)+COLUMN(F$1),1))} -> 地の魔力 | BM78: {=IF($A78="","", INDEX(CS!$B$1:$B$15026,MATCH($A78,CS!$B:$B,0)+COLUMN(G$1),1))} | BN78: {=IF($A78="","", INDEX(CS!$B$1:$B$15026,MATCH($A78,CS!$B:$B,0)+COLUMN(H$1),1))} | ... BP78: {=IF($A78="","", INDEX(CS!$B$1:$B$15026,MATCH($A78,CS!$B:$B,0)+COLUMN(J$1),1))} -> 石礫の吐息 | CD78: 1 | CN78: 精霊
A79: アークフレイムエレメンタル | B79: 精霊 | C79: 魔族 | D79: =SUM(AJ79:AZ79,F79:N79)&"/"&SUM(F79:N79)&"/"&SUM(AJ79:AZ79) -> 690/515/175 | E79: 2 | F79: 75 | I79: 55 | J79: 60 | K79: 100 | L79: 85 | M79: 75 | N79: 65 | O79: 140 | P79: 0 | Q79: 15 | T79: 100 | U79: -45 | W79: 100 | X79: -45 | AE79: 100 | AJ79: 0 | AK79: 0 | AL79: 75 | AM79: 0 | AN79: 0 | AO79: 0 | AP79: 0 | AQ79: 75 | AR79: 25 | AS79: -25 | AT79: -25 | AU79: -25 | AV79: -25 | AW79: 0 | AX79: 0 | AY79: 100 | AZ79: 0 | BR79: フレイムエレメンタル_10 | BU79: フレイムエレメンタルの上位種。性能は下位種値を暫定継承。専用スキル未設定。 | CD79: 1 | CI79: × | CJ79: × | CK79: × | CN79: 精霊
A80: グレーターフレイムエレメンタル | B80: 精霊 | C80: 魔族 | D80: =SUM(AJ80:AZ80,F80:N80)&"/"&SUM(F80:N80)&"/"&SUM(AJ80:AZ80) -> 690/515/175 | E80: 3 | F80: 75 | I80: 55 | J80: 60 | K80: 100 | L80: 85 | M80: 75 | N80: 65 | O80: 140 | P80: 0 | Q80: 15 | T80: 100 | U80: -45 | W80: 100 | X80: -45 | AE80: 100 | AJ80: 0 | AK80: 0 | AL80: 75 | AM80: 0 | AN80: 0 | AO80: 0 | AP80: 0 | AQ80: 75 | AR80: 25 | AS80: -25 | AT80: -25 | AU80: -25 | AV80: -25 | AW80: 0 | AX80: 0 | AY80: 100 | AZ80: 0 | BR80: アークフレイムエレメンタル_10 | BU80: アークフレイムエレメンタルの上位種。性能は下位種値を暫定継承。専用スキル未設定。 | CD80: 1 | CI80: × | CJ80: × | CK80: × | CN80: 精霊
A81: エルダーフレイムエレメンタル | B81: 精霊 | C81: 魔族 | D81: =SUM(AJ81:AZ81,F81:N81)&"/"&SUM(F81:N81)&"/"&SUM(AJ81:AZ81) -> 690/515/175 | E81: 4 | F81: 75 | I81: 55 | J81: 60 | K81: 100 | L81: 85 | M81: 75 | N81: 65 | O81: 140 | P81: 0 | Q81: 15 | T81: 100 | U81: -45 | W81: 100 | X81: -45 | AE81: 100 | AJ81: 0 | AK81: 0 | AL81: 75 | AM81: 0 | AN81: 0 | AO81: 0 | AP81: 0 | AQ81: 75 | AR81: 25 | AS81: -25 | AT81: -25 | AU81: -25 | AV81: -25 | AW81: 0 | AX81: 0 | AY81: 100 | AZ81: 0 | BR81: グレーターフレイムエレメンタル_10 | BU81: グレーターフレイムエレメンタルの上位種。性能は下位種値を暫定継承。専用スキル未設定。 | CD81: 1 | CI81: × | CJ81: × | CK81: × | CN81: 精霊
A82: アークフロストエレメンタル | B82: 精霊 | C82: 魔族 | D82: =SUM(AJ82:AZ82,F82:N82)&"/"&SUM(F82:N82)&"/"&SUM(AJ82:AZ82) -> 690/515/175 | E82: 2 | F82: 75 | I82: 55 | J82: 60 | K82: 100 | L82: 85 | M82: 75 | N82: 65 | O82: 140 | P82: 0 | Q82: 15 | T82: -45 | U82: 100 | W82: -45 | X82: 100 | AE82: 100 | AJ82: 0 | AK82: 0 | AL82: 75 | AM82: 0 | AN82: 0 | AO82: 0 | AP82: 0 | AQ82: 75 | AR82: 25 | AS82: -25 | AT82: -25 | AU82: -25 | AV82: -25 | AW82: 0 | AX82: 0 | AY82: 100 | AZ82: 0 | BR82: フロストエレメンタル_10 | BU82: フロストエレメンタルの上位種。性能は下位種値を暫定継承。専用スキル未設定。 | CD82: 1 | CN82: 精霊
A83: グレーターフロストエレメンタル | B83: 精霊 | C83: 魔族 | D83: =SUM(AJ83:AZ83,F83:N83)&"/"&SUM(F83:N83)&"/"&SUM(AJ83:AZ83) -> 690/515/175 | E83: 3 | F83: 75 | I83: 55 | J83: 60 | K83: 100 | L83: 85 | M83: 75 | N83: 65 | O83: 140 | P83: 0 | Q83: 15 | T83: -45 | U83: 100 | W83: -45 | X83: 100 | AE83: 100 | AJ83: 0 | AK83: 0 | AL83: 75 | AM83: 0 | AN83: 0 | AO83: 0 | AP83: 0 | AQ83: 75 | AR83: 25 | AS83: -25 | AT83: -25 | AU83: -25 | AV83: -25 | AW83: 0 | AX83: 0 | AY83: 100 | AZ83: 0 | BR83: アークフロストエレメンタル_10 | BU83: アークフロストエレメンタルの上位種。性能は下位種値を暫定継承。専用スキル未設定。 | CD83: 1 | CN83: 精霊
A84: エルダーフロストエレメンタル | B84: 精霊 | C84: 魔族 | D84: =SUM(AJ84:AZ84,F84:N84)&"/"&SUM(F84:N84)&"/"&SUM(AJ84:AZ84) -> 690/515/175 | E84: 4 | F84: 75 | I84: 55 | J84: 60 | K84: 100 | L84: 85 | M84: 75 | N84: 65 | O84: 140 | P84: 0 | Q84: 15 | T84: -45 | U84: 100 | W84: -45 | X84: 100 | AE84: 100 | AJ84: 0 | AK84: 0 | AL84: 75 | AM84: 0 | AN84: 0 | AO84: 0 | AP84: 0 | AQ84: 75 | AR84: 25 | AS84: -25 | AT84: -25 | AU84: -25 | AV84: -25 | AW84: 0 | AX84: 0 | AY84: 100 | AZ84: 0 | BR84: グレーターフロストエレメンタル_10 | BU84: グレーターフロストエレメンタルの上位種。性能は下位種値を暫定継承。専用スキル未設定。 | CD84: 1 | CN84: 精霊
A85: アークウォーターエレメンタル | B85: 精霊 | C85: 魔族 | D85: =SUM(AJ85:AZ85,F85:N85)&"/"&SUM(F85:N85)&"/"&SUM(AJ85:AZ85) -> 690/515/175 | E85: 2 | F85: 75 | I85: 55 | J85: 60 | K85: 100 | L85: 85 | M85: 75 | N85: 65 | O85: 140 | P85: 0 | Q85: 15 | T85: -45 | U85: 100 | W85: -45 | X85: 100 | AE85: 100 | AJ85: 0 | AK85: 0 | AL85: 75 | AM85: 0 | AN85: 0 | AO85: 0 | AP85: 0 | AQ85: 75 | AR85: 25 | AS85: -25 | AT85: -25 | AU85: -25 | AV85: -25 | AW85: 0 | AX85: 0 | AY85: 100 | AZ85: 0 | BR85: ウォーターエレメンタル_10 | BU85: ウォーターエレメンタルの上位種。性能は下位種値を暫定継承。専用スキル未設定。 | CD85: 1 | CN85: 精霊
A86: グレーターウォーターエレメンタル | B86: 精霊 | C86: 魔族 | D86: =SUM(AJ86:AZ86,F86:N86)&"/"&SUM(F86:N86)&"/"&SUM(AJ86:AZ86) -> 690/515/175 | E86: 3 | F86: 75 | I86: 55 | J86: 60 | K86: 100 | L86: 85 | M86: 75 | N86: 65 | O86: 140 | P86: 0 | Q86: 15 | T86: -45 | U86: 100 | W86: -45 | X86: 100 | AE86: 100 | AJ86: 0 | AK86: 0 | AL86: 75 | AM86: 0 | AN86: 0 | AO86: 0 | AP86: 0 | AQ86: 75 | AR86: 25 | AS86: -25 | AT86: -25 | AU86: -25 | AV86: -25 | AW86: 0 | AX86: 0 | AY86: 100 | AZ86: 0 | BR86: アークウォーターエレメンタル_10 | BU86: アークウォーターエレメンタルの上位種。性能は下位種値を暫定継承。専用スキル未設定。 | CD86: 1 | CN86: 精霊
A87: エルダーウォーターエレメンタル | B87: 精霊 | C87: 魔族 | D87: =SUM(AJ87:AZ87,F87:N87)&"/"&SUM(F87:N87)&"/"&SUM(AJ87:AZ87) -> 690/515/175 | E87: 4 | F87: 75 | I87: 55 | J87: 60 | K87: 100 | L87: 85 | M87: 75 | N87: 65 | O87: 140 | P87: 0 | Q87: 15 | T87: -45 | U87: 100 | W87: -45 | X87: 100 | AE87: 100 | AJ87: 0 | AK87: 0 | AL87: 75 | AM87: 0 | AN87: 0 | AO87: 0 | AP87: 0 | AQ87: 75 | AR87: 25 | AS87: -25 | AT87: -25 | AU87: -25 | AV87: -25 | AW87: 0 | AX87: 0 | AY87: 100 | AZ87: 0 | BR87: グレーターウォーターエレメンタル_10 | BU87: グレーターウォーターエレメンタルの上位種。性能は下位種値を暫定継承。専用スキル未設定。 | CD87: 1 | CN87: 精霊
A88: アークエアエレメンタル | B88: 精霊 | C88: 魔族 | D88: =SUM(AJ88:AZ88,F88:N88)&"/"&SUM(F88:N88)&"/"&SUM(AJ88:AZ88) -> 690/515/175 | E88: 2 | F88: 75 | I88: 55 | J88: 60 | K88: 100 | L88: 85 | M88: 75 | N88: 65 | O88: 140 | P88: 0 | Q88: -15 | V88: 100 | Y88: 100 | AE88: 100 | AJ88: 0 | AK88: 0 | AL88: 75 | AM88: 0 | AN88: 0 | AO88: 0 | AP88: 0 | AQ88: 75 | AR88: 25 | AS88: -25 | AT88: -25 | AU88: -25 | AV88: -25 | AW88: 0 | AX88: 0 | AY88: 100 | AZ88: 0 | BR88: エアエレメンタル_10 | BU88: エアエレメンタルの上位種。性能は下位種値を暫定継承。専用スキル未設定。 | CD88: 1 | CN88: 精霊
A89: グレーターエアエレメンタル | B89: 精霊 | C89: 魔族 | D89: =SUM(AJ89:AZ89,F89:N89)&"/"&SUM(F89:N89)&"/"&SUM(AJ89:AZ89) -> 690/515/175 | E89: 3 | F89: 75 | I89: 55 | J89: 60 | K89: 100 | L89: 85 | M89: 75 | N89: 65 | O89: 140 | P89: 0 | Q89: -15 | V89: 100 | Y89: 100 | AE89: 100 | AJ89: 0 | AK89: 0 | AL89: 75 | AM89: 0 | AN89: 0 | AO89: 0 | AP89: 0 | AQ89: 75 | AR89: 25 | AS89: -25 | AT89: -25 | AU89: -25 | AV89: -25 | AW89: 0 | AX89: 0 | AY89: 100 | AZ89: 0 | BR89: アークエアエレメンタル_10 | BU89: アークエアエレメンタルの上位種。性能は下位種値を暫定継承。専用スキル未設定。 | CD89: 1 | CN89: 精霊
A90: エルダーエアエレメンタル | B90: 精霊 | C90: 魔族 | D90: =SUM(AJ90:AZ90,F90:N90)&"/"&SUM(F90:N90)&"/"&SUM(AJ90:AZ90) -> 690/515/175 | E90: 4 | F90: 75 | I90: 55 | J90: 60 | K90: 100 | L90: 85 | M90: 75 | N90: 65 | O90: 140 | P90: 0 | Q90: -15 | V90: 100 | Y90: 100 | AE90: 100 | AJ90: 0 | AK90: 0 | AL90: 75 | AM90: 0 | AN90: 0 | AO90: 0 | AP90: 0 | AQ90: 75 | AR90: 25 | AS90: -25 | AT90: -25 | AU90: -25 | AV90: -25 | AW90: 0 | AX90: 0 | AY90: 100 | AZ90: 0 | BR90: グレーターエアエレメンタル_10 | BU90: グレーターエアエレメンタルの上位種。性能は下位種値を暫定継承。専用スキル未設定。 | CD90: 1 | CN90: 精霊
A91: アークアースエレメンタル | B91: 精霊 | C91: 魔族 | D91: =SUM(AJ91:AZ91,F91:N91)&"/"&SUM(F91:N91)&"/"&SUM(AJ91:AZ91) -> 700/525/175 | E91: 2 | F91: 90 | I91: 90 | J91: 80 | K91: 100 | L91: 50 | M91: 50 | N91: 65 | O91: 140 | P91: 0 | Q91: 15 | Z91: -45 | AE91: 100 | AJ91: 0 | AK91: 0 | AL91: 75 | AM91: 0 | AN91: 0 | AO91: 0 | AP91: 0 | AQ91: 75 | AR91: 25 | AS91: -25 | AT91: -25 | AU91: -25 | AV91: -25 | AW91: 0 | AX91: 0 | AY91: 100 | AZ91: 0 | BR91: アースエレメンタル_10 | BU91: アースエレメンタルの上位種。性能は下位種値を暫定継承。専用スキル未設定。 | CD91: 1 | CN91: 精霊
A92: グレーターアースエレメンタル | B92: 精霊 | C92: 魔族 | D92: =SUM(AJ92:AZ92,F92:N92)&"/"&SUM(F92:N92)&"/"&SUM(AJ92:AZ92) -> 700/525/175 | E92: 3 | F92: 90 | I92: 90 | J92: 80 | K92: 100 | L92: 50 | M92: 50 | N92: 65 | O92: 140 | P92: 0 | Q92: 15 | Z92: -45 | AE92: 100 | AJ92: 0 | AK92: 0 | AL92: 75 | AM92: 0 | AN92: 0 | AO92: 0 | AP92: 0 | AQ92: 75 | AR92: 25 | AS92: -25 | AT92: -25 | AU92: -25 | AV92: -25 | AW92: 0 | AX92: 0 | AY92: 100 | AZ92: 0 | BR92: アークアースエレメンタル_10 | BU92: アークアースエレメンタルの上位種。性能は下位種値を暫定継承。専用スキル未設定。 | CD92: 1 | CN92: 精霊
A93: エルダーアースエレメンタル | B93: 精霊 | C93: 魔族 | D93: =SUM(AJ93:AZ93,F93:N93)&"/"&SUM(F93:N93)&"/"&SUM(AJ93:AZ93) -> 700/525/175 | E93: 4 | F93: 90 | I93: 90 | J93: 80 | K93: 100 | L93: 50 | M93: 50 | N93: 65 | O93: 140 | P93: 0 | Q93: 15 | Z93: -45 | AE93: 100 | AJ93: 0 | AK93: 0 | AL93: 75 | AM93: 0 | AN93: 0 | AO93: 0 | AP93: 0 | AQ93: 75 | AR93: 25 | AS93: -25 | AT93: -25 | AU93: -25 | AV93: -25 | AW93: 0 | AX93: 0 | AY93: 100 | AZ93: 0 | BR93: グレーターアースエレメンタル_10 | BU93: グレーターアースエレメンタルの上位種。性能は下位種値を暫定継承。専用スキル未設定。 | CD93: 1 | CN93: 精霊
C94: 魔族 | D94: =SUM(AJ94:AZ94,F94:N94)&"/"&SUM(F94:N94)&"/"&SUM(AJ94:AZ94) -> 0/0/0 | E94: 1 | BG94: {=IF($A94="","", INDEX(CS!$B$1:$B$15026,MATCH($A94,CS!$B:$B,0)+COLUMN(A$1),1))} | BH94: {=IF($A94="","", INDEX(CS!$B$1:$B$15026,MATCH($A94,CS!$B:$B,0)+COLUMN(B$1),1))} | BI94: {=IF($A94="","", INDEX(CS!$B$1:$B$15026,MATCH($A94,CS!$B:$B,0)+COLUMN(C$1),1))} | BJ94: {=IF($A94="","", INDEX(CS!$B$1:$B$15026,MATCH($A94,CS!$B:$B,0)+COLUMN(D$1),1))} | BK94: {=IF($A94="","", INDEX(CS!$B$1:$B$15026,MATCH($A94,CS!$B:$B,0)+COLUMN(E$1),1))} | BL94: {=IF($A94="","", INDEX(CS!$B$1:$B$15026,MATCH($A94,CS!$B:$B,0)+COLUMN(F$1),1))} | BM94: {=IF($A94="","", INDEX(CS!$B$1:$B$15026,MATCH($A94,CS!$B:$B,0)+COLUMN(G$1),1))} | BN94: {=IF($A94="","", INDEX(CS!$B$1:$B$15026,MATCH($A94,CS!$B:$B,0)+COLUMN(H$1),1))} | ... BP94: {=IF($A94="","", INDEX(CS!$B$1:$B$15026,MATCH($A94,CS!$B:$B,0)+COLUMN(J$1),1))}
C95: 魔族 | D95: =SUM(AJ95:AZ95,F95:N95)&"/"&SUM(F95:N95)&"/"&SUM(AJ95:AZ95) -> 0/0/0 | E95: 1 | BG95: {=IF($A95="","", INDEX(CS!$B$1:$B$15026,MATCH($A95,CS!$B:$B,0)+COLUMN(A$1),1))} | BH95: {=IF($A95="","", INDEX(CS!$B$1:$B$15026,MATCH($A95,CS!$B:$B,0)+COLUMN(B$1),1))} | BI95: {=IF($A95="","", INDEX(CS!$B$1:$B$15026,MATCH($A95,CS!$B:$B,0)+COLUMN(C$1),1))} | BJ95: {=IF($A95="","", INDEX(CS!$B$1:$B$15026,MATCH($A95,CS!$B:$B,0)+COLUMN(D$1),1))} | BK95: {=IF($A95="","", INDEX(CS!$B$1:$B$15026,MATCH($A95,CS!$B:$B,0)+COLUMN(E$1),1))} | BL95: {=IF($A95="","", INDEX(CS!$B$1:$B$15026,MATCH($A95,CS!$B:$B,0)+COLUMN(F$1),1))} | BM95: {=IF($A95="","", INDEX(CS!$B$1:$B$15026,MATCH($A95,CS!$B:$B,0)+COLUMN(G$1),1))} | BN95: {=IF($A95="","", INDEX(CS!$B$1:$B$15026,MATCH($A95,CS!$B:$B,0)+COLUMN(H$1),1))} | ... BP95: {=IF($A95="","", INDEX(CS!$B$1:$B$15026,MATCH($A95,CS!$B:$B,0)+COLUMN(J$1),1))}
C96: 魔族 | D96: =SUM(AJ96:AZ96,F96:N96)&"/"&SUM(F96:N96)&"/"&SUM(AJ96:AZ96) -> 0/0/0 | E96: 1 | BG96: {=IF($A96="","", INDEX(CS!$B$1:$B$15026,MATCH($A96,CS!$B:$B,0)+COLUMN(A$1),1))} | BH96: {=IF($A96="","", INDEX(CS!$B$1:$B$15026,MATCH($A96,CS!$B:$B,0)+COLUMN(B$1),1))} | BI96: {=IF($A96="","", INDEX(CS!$B$1:$B$15026,MATCH($A96,CS!$B:$B,0)+COLUMN(C$1),1))} | BJ96: {=IF($A96="","", INDEX(CS!$B$1:$B$15026,MATCH($A96,CS!$B:$B,0)+COLUMN(D$1),1))} | BK96: {=IF($A96="","", INDEX(CS!$B$1:$B$15026,MATCH($A96,CS!$B:$B,0)+COLUMN(E$1),1))} | BL96: {=IF($A96="","", INDEX(CS!$B$1:$B$15026,MATCH($A96,CS!$B:$B,0)+COLUMN(F$1),1))} | BM96: {=IF($A96="","", INDEX(CS!$B$1:$B$15026,MATCH($A96,CS!$B:$B,0)+COLUMN(G$1),1))} | BN96: {=IF($A96="","", INDEX(CS!$B$1:$B$15026,MATCH($A96,CS!$B:$B,0)+COLUMN(H$1),1))} | ... BP96: {=IF($A96="","", INDEX(CS!$B$1:$B$15026,MATCH($A96,CS!$B:$B,0)+COLUMN(J$1),1))}
C97: 魔族 | D97: =SUM(AJ97:AZ97,F97:N97)&"/"&SUM(F97:N97)&"/"&SUM(AJ97:AZ97) -> 0/0/0 | E97: 1 | BG97: {=IF($A97="","", INDEX(CS!$B$1:$B$15026,MATCH($A97,CS!$B:$B,0)+COLUMN(A$1),1))} | BH97: {=IF($A97="","", INDEX(CS!$B$1:$B$15026,MATCH($A97,CS!$B:$B,0)+COLUMN(B$1),1))} | BI97: {=IF($A97="","", INDEX(CS!$B$1:$B$15026,MATCH($A97,CS!$B:$B,0)+COLUMN(C$1),1))} | BJ97: {=IF($A97="","", INDEX(CS!$B$1:$B$15026,MATCH($A97,CS!$B:$B,0)+COLUMN(D$1),1))} | BK97: {=IF($A97="","", INDEX(CS!$B$1:$B$15026,MATCH($A97,CS!$B:$B,0)+COLUMN(E$1),1))} | BL97: {=IF($A97="","", INDEX(CS!$B$1:$B$15026,MATCH($A97,CS!$B:$B,0)+COLUMN(F$1),1))} | BM97: {=IF($A97="","", INDEX(CS!$B$1:$B$15026,MATCH($A97,CS!$B:$B,0)+COLUMN(G$1),1))} | BN97: {=IF($A97="","", INDEX(CS!$B$1:$B$15026,MATCH($A97,CS!$B:$B,0)+COLUMN(H$1),1))} | ... BP97: {=IF($A97="","", INDEX(CS!$B$1:$B$15026,MATCH($A97,CS!$B:$B,0)+COLUMN(J$1),1))}
C98: 魔族 | D98: =SUM(AJ98:AZ98,F98:N98)&"/"&SUM(F98:N98)&"/"&SUM(AJ98:AZ98) -> 0/0/0 | E98: 1 | BG98: {=IF($A98="","", INDEX(CS!$B$1:$B$15026,MATCH($A98,CS!$B:$B,0)+COLUMN(A$1),1))} | BH98: {=IF($A98="","", INDEX(CS!$B$1:$B$15026,MATCH($A98,CS!$B:$B,0)+COLUMN(B$1),1))} | BI98: {=IF($A98="","", INDEX(CS!$B$1:$B$15026,MATCH($A98,CS!$B:$B,0)+COLUMN(C$1),1))} | BJ98: {=IF($A98="","", INDEX(CS!$B$1:$B$15026,MATCH($A98,CS!$B:$B,0)+COLUMN(D$1),1))} | BK98: {=IF($A98="","", INDEX(CS!$B$1:$B$15026,MATCH($A98,CS!$B:$B,0)+COLUMN(E$1),1))} | BL98: {=IF($A98="","", INDEX(CS!$B$1:$B$15026,MATCH($A98,CS!$B:$B,0)+COLUMN(F$1),1))} | BM98: {=IF($A98="","", INDEX(CS!$B$1:$B$15026,MATCH($A98,CS!$B:$B,0)+COLUMN(G$1),1))} | BN98: {=IF($A98="","", INDEX(CS!$B$1:$B$15026,MATCH($A98,CS!$B:$B,0)+COLUMN(H$1),1))} | ... BP98: {=IF($A98="","", INDEX(CS!$B$1:$B$15026,MATCH($A98,CS!$B:$B,0)+COLUMN(J$1),1))}
B99: -=========== 基礎クラス ===========- | D99: =SUM(AJ99:AZ99,F99:N99)&"/"&SUM(F99:N99)&"/"&SUM(AJ99:AZ99) -> 0/0/0 | E99: 1 | BG99: {=IF($A99="","", INDEX(CS!$B$1:$B$15026,MATCH($A99,CS!$B:$B,0)+COLUMN(A$1),1))} | BH99: {=IF($A99="","", INDEX(CS!$B$1:$B$15026,MATCH($A99,CS!$B:$B,0)+COLUMN(B$1),1))} | BI99: {=IF($A99="","", INDEX(CS!$B$1:$B$15026,MATCH($A99,CS!$B:$B,0)+COLUMN(C$1),1))} | BJ99: {=IF($A99="","", INDEX(CS!$B$1:$B$15026,MATCH($A99,CS!$B:$B,0)+COLUMN(D$1),1))} | BK99: {=IF($A99="","", INDEX(CS!$B$1:$B$15026,MATCH($A99,CS!$B:$B,0)+COLUMN(E$1),1))} | BL99: {=IF($A99="","", INDEX(CS!$B$1:$B$15026,MATCH($A99,CS!$B:$B,0)+COLUMN(F$1),1))} | BM99: {=IF($A99="","", INDEX(CS!$B$1:$B$15026,MATCH($A99,CS!$B:$B,0)+COLUMN(G$1),1))} | BN99: {=IF($A99="","", INDEX(CS!$B$1:$B$15026,MATCH($A99,CS!$B:$B,0)+COLUMN(H$1),1))} | ... BP99: {=IF($A99="","", INDEX(CS!$B$1:$B$15026,MATCH($A99,CS!$B:$B,0)+COLUMN(J$1),1))}
A100: ファイター | B100: 戦士 | C100: 戦士系 | D100: =SUM(AJ100:AZ100,F100:N100)&"/"&SUM(F100:N100)&"/"&SUM(AJ100:AZ100) -> 710/460/250 | E100: 1 | F100: 85 | I100: 90 | J100: 80 | K100: 25 | L100: 50 | M100: 55 | N100: 75 | P100: 0 | AJ100: 75 | AK100: 50 | AL100: 25 | AM100: 25 | AN100: 25 | AO100: 0 | AP100: 0 | AQ100: 0 | AR100: 25 | AS100: 0 | AT100: 0 | AU100: 0 | AV100: 0 | AW100: 25 | AX100: 0 | AY100: 0 | AZ100: 0 | BG100: {=IF($A100="","", INDEX(CS!$B$1:$B$15026,MATCH($A100,CS!$B:$B,0)+COLUMN(A$1),1))} | BH100: {=IF($A100="","", INDEX(CS!$B$1:$B$15026,MATCH($A100,CS!$B:$B,0)+COLUMN(B$1),1))} -> 闘気撃 | BI100: {=IF($A100="","", INDEX(CS!$B$1:$B$15026,MATCH($A100,CS!$B:$B,0)+COLUMN(C$1),1))} -> 武器の扱い | BJ100: {=IF($A100="","", INDEX(CS!$B$1:$B$15026,MATCH($A100,CS!$B:$B,0)+COLUMN(D$1),1))} | BK100: {=IF($A100="","", INDEX(CS!$B$1:$B$15026,MATCH($A100,CS!$B:$B,0)+COLUMN(E$1),1))} -> 闘気守 | BL100: {=IF($A100="","", INDEX(CS!$B$1:$B$15026,MATCH($A100,CS!$B:$B,0)+COLUMN(F$1),1))} | BM100: {=IF($A100="","", INDEX(CS!$B$1:$B$15026,MATCH($A100,CS!$B:$B,0)+COLUMN(G$1),1))} | BN100: {=IF($A100="","", INDEX(CS!$B$1:$B$15026,MATCH($A100,CS!$B:$B,0)+COLUMN(H$1),1))} -> 雄叫び | ... BP100: {=IF($A100="","", INDEX(CS!$B$1:$B$15026,MATCH($A100,CS!$B:$B,0)+COLUMN(J$1),1))} -> 一閃撃 | CG100: 長剣 | CJ100: 鎧 | CK100: 靴 | CN100: 戦士
A101: ナイト | B101: 騎士 | C101: 戦士系 | D101: =SUM(AJ101:AZ101,F101:N101)&"/"&SUM(F101:N101)&"/"&SUM(AJ101:AZ101) -> 710/460/250 | E101: 1 | F101: 85 | I101: 80 | J101: 90 | K101: 25 | L101: 55 | M101: 50 | N101: 75 | P101: 0 | AJ101: 100 | AK101: 0 | AL101: 25 | AM101: 25 | AN101: 25 | AO101: 0 | AP101: 0 | AQ101: 0 | AR101: 25 | AS101: 0 | AT101: 0 | AU101: 0 | AV101: 0 | AW101: 50 | AX101: 0 | AY101: 0 | AZ101: 0 | BG101: {=IF($A101="","", INDEX(CS!$B$1:$B$15026,MATCH($A101,CS!$B:$B,0)+COLUMN(A$1),1))} | BH101: {=IF($A101="","", INDEX(CS!$B$1:$B$15026,MATCH($A101,CS!$B:$B,0)+COLUMN(B$1),1))} -> 闘気守 | BI101: {=IF($A101="","", INDEX(CS!$B$1:$B$15026,MATCH($A101,CS!$B:$B,0)+COLUMN(C$1),1))} -> 武器の扱い | BJ101: {=IF($A101="","", INDEX(CS!$B$1:$B$15026,MATCH($A101,CS!$B:$B,0)+COLUMN(D$1),1))} | BK101: {=IF($A101="","", INDEX(CS!$B$1:$B$15026,MATCH($A101,CS!$B:$B,0)+COLUMN(E$1),1))} -> 闘気撃 | BL101: {=IF($A101="","", INDEX(CS!$B$1:$B$15026,MATCH($A101,CS!$B:$B,0)+COLUMN(F$1),1))} -> 反撃 | BM101: {=IF($A101="","", INDEX(CS!$B$1:$B$15026,MATCH($A101,CS!$B:$B,0)+COLUMN(G$1),1))} | BN101: {=IF($A101="","", INDEX(CS!$B$1:$B$15026,MATCH($A101,CS!$B:$B,0)+COLUMN(H$1),1))} -> 雄叫び | ... BP101: {=IF($A101="","", INDEX(CS!$B$1:$B$15026,MATCH($A101,CS!$B:$B,0)+COLUMN(J$1),1))} -> 一閃撃 | CG101: 剣 | CH101: 軽盾 | CJ101: 鎧 | CK101: 靴 | CN101: 戦士
...

Sheet 種族
A1: 種族 | B1: 能力クラス | C1: 使用可 | D1: 旧名称 | E1: 画像 | F1: 概要 | G1: 詳細 | H1: 特徴 | I1: マーカー文字 | J1: マーカー色 | K1: 初期人数 | L1: 高さ | M1: ヒーロー | N1: 軍隊 | O1: 土地 | P1: 設定メモ | Q1: 推奨クラス | R1: 推奨都市特化
A2: 只人 | B2: ヒューマン | C2: TRUE | D2: ["人間","ヒューマン"] | E2: /assets/images/role/人間.webp | F2: 都市運営と前線維持の両面が安定した標準種族。 | G2: 制度適応が高く、どの国家体制でも扱いやすい。初期拡張や内政立ち上げを堅実に進められる。 | H2: ["統治適応","兵站安定","万能型"] | I2: 只 | J2: #3e5d84 | K2: 50 | L2: 0 | M2: 1 | N2: 0.15 | O2: 平地 | R2: 交易都市/農業都市/学術都市
A3: エルフ | B3: エルフ | C3: TRUE | D3: ["森人"] | E3: /assets/images/role/森人.webp | F3: 魔法・索敵に秀でた長命種。 | G3: 森地形と相性が良く、精密運用で真価を発揮する。防衛よりも戦術優位を取り続ける構成向き。 | H3: ["魔術適性","索敵強化","森林親和"] | I3: 森 | J3: #4a7d3c | K3: 50 | L3: 0 | M3: 1 | N3: 0.1 | O3: 森 | Q3: ウィザード/アーチャー/スカウト/ドルイド | R3: 魔法都市/学術都市/神秘都市
A4: ドワーフ | B4: ドワーフ | C4: FALSE | D4: ["土人"] | I4: 土 | J4: #7a5f3a | K4: 50 | L4: 1 | M4: 1 | N4: 0.1 | O4: 洞窟,丘,山 | P4: 表示情報（画像・概要・詳細・特徴）が未設定 | Q4: ファイター/ナイト/ドルイド
A5: 獣人 | B5: ビーストマン | C5: FALSE | D5: ["ビーストマン"] | I5: 獣 | J5: #8a6d2e | K5: 60 | L5: 1 | M5: 0.8 | N5: 0.2 | O5: 平地 | P5: 表示情報（画像・概要・詳細・特徴）が未設定 | Q5: モンク/レンジャー/フェンサー
A6: 竜人 | B6: ドラゴニュート | C6: TRUE | D6: ["ドラゴニュート"] | E6: /assets/images/role/竜人.webp | F6: 範囲攻撃と高い制圧力を持つ高位戦闘種。 | G6: 攻守の基礎値が高く、軍事ルートとの相性が良い。主戦力として扱いやすく、対多数でも崩れにくい。 | H6: ["範囲制圧","高火力","高耐性"] | I6: 竜 | J6: #39687f | K6: 25 | L6: 1 | M6: 1.25 | N6: 0.25 | O6: 丘,山,平地,沼 | Q6: ファイター/ウォーリアー/ガーディアン | R6: 軍事都市/城塞都市
A7: オーガ | B7: オーガ | C7: TRUE | D7: ["大鬼"] | E7: /assets/images/illust/オーガ.webp | F7: 高耐久と打撃力で前線を押し込む巨躯種。 | G7: 初動から強く、接敵後の制圧戦に強い。継戦コストは重いが、局地戦の突破力は全種族でも上位。 | H7: ["高耐久","前線圧力","近接制圧"] | I7: 鬼 | J7: #7f3f2e | K7: 25 | L7: 1 | M7: 0.8 | N7: 0.35 | O7: 丘,平地,森,山 | Q7: ファイター/ウォーリアー/ガーディアン | R7: 軍事都市/城塞都市
A8: 巨人 | B8: ジャイアント | C8: FALSE | D8: ["ジャイアント"] | I8: 巨 | J8: #6b5c4b | K8: 15 | L8: 2 | M8: 1.2 | N8: 0.45 | O8: 丘,平地,山 | P8: 表示情報（画像・概要・詳細・特徴）が未設定
A9: ゴブリン | B9: ゴブリン | C9: TRUE | D9: ["鬼妖"] | E9: /assets/images/illust/ゴブリン.webp | F9: 機動と数で優位を作る群体運用向け種族。 | G9: 単体性能は低いが展開速度が高く、補給線妨害や攪乱が得意。長期戦では構成次第で化ける。 | H9: ["展開速度","攪乱","低コスト運用"] | I9: 妖 | J9: #5f7c3a | K9: 75 | L9: 0 | M9: 0.5 | N9: 0.1 | O9: 丘,森 | Q9: スカウト/アーチャー/ファイター | R9: 軍事都市/交易都市
A10: 悪魔 | B10: デヴィル | C10: TRUE | D10: ["デヴィル"] | E10: /assets/images/role/悪魔.webp | F10: 吸収・圧殺に寄った攻勢特化種族。 | G10: 短期決戦の爆発力が高い。治安や内政の管理負荷は上がるが、戦闘リターンは非常に大きい。 | H10: ["吸収戦闘","攻勢特化","高リスク高リターン"] | I10: 魔 | J10: #6a2f4f | K10: 10 | L10: 3 | M10: 1.5 | N10: 0.6 | O10: 山,森,湖 | Q10: ウィザード/ファイター/スカウト | R10: 魔法都市/軍事都市/神秘都市
A11: 天使 | B11: エンジェル | C11: TRUE | D11: ["エンジェル"] | E11: /assets/images/role/天使.webp | F11: 支援と維持戦に優れた加護系種族。 | G11: 部隊全体の安定性を上げる効果が多く、長期戦で有利。信仰系スキルや統治との噛み合わせが良い。 | H11: ["全体支援","持久戦","信仰適性"] | I11: 天 | J11: #5c6fa2 | K11: 15 | L11: 3 | M11: 1.5 | N11: 0.6 | O11: 火山,山,丘,洞窟 | Q11: クレリック/ナイト/パラディン | R11: 信仰都市/城塞都市
A12: ヴァンパイア | B12: ヴァンパイア | C12: TRUE | D12: ["吸血鬼"] | E12: /assets/images/role/吸血鬼.webp | F12: 継戦吸収型の技巧種族。 | G12: 削り合いに強く、戦線維持能力が高い。瞬間火力よりも、戦闘テンポの主導権を握る運用向き。 | H12: ["自己回復","持久戦","夜戦適性"] | I12: 吸 | J12: #662f4a | K12: 10 | L12: 3 | M12: 1.5 | N12: 0.6 | O12: 洞窟,森,渓谷 | P12: 高さ未設定 | Q12: ウィザード/スカウト/レンジャー | R12: 軍事都市/城塞都市/死者の都
C13: FALSE
C14: FALSE
C15: FALSE
C16: FALSE
C17: FALSE
C18: FALSE
C19: FALSE
C20: FALSE
C21: FALSE
C22: FALSE
C23: FALSE
C24: FALSE
... C1000: FALSE

Sheet 用語辞書
A1: 追加効果 | B1: 説明 | D1: 技能名 | E1: 説明 | G1: 範囲タイプ | H1: 説明 | I1: 処理タイプ
A2: 連鎖 | B2: 対象から近くの別対象へ順に連鎖して効果が及ぶ | D2: 指揮 | E2: 部隊への命令効率を高める。士気上昇量やバフ効果量が増加し、部隊スキルの性能が向上する。 | G2: 単体 | H2: 指定した1体のみを対象にする | I2: single
A3: 能力値回復 | B3: 対象の能力値（攻撃・防御・魔力・精神・速度・命中など）を回復する | D3: 威圧 | E3: 騙すを併合。敵やNPCに心理的圧力を与える。敵士気低下や怯え付与、会話時の威圧成功率が上昇する。 | G3: 直線 | H3: 指定方向へ一直線上の対象を貫通して攻撃する | I3: line
A4: AP回復 | B4: 対象のAPを回復する | D4: 看破 | E4: 知識を含む。敵能力・弱点・嘘・罠・アイテムの性質を見破る。不意打ち耐性や情報取得能力が向上する。 | G4: 扇 | H4: 自分前方に扇形範囲で攻撃する | I4: fan
A5: AP増加 | B5: 対象の最大APまたは現在AP上限を一時的に増加させる | D5: 早業 | E5: 軽業を併合。攻撃速度や回避率が上昇し、移動系スキルの消費が軽減される。連撃性能が向上する。 | G5: 円 | H5: 指定地点を中心とした円形範囲を攻撃する | I5: circle
A6: APダメージ | B6: 対象のAPを減少させる | D6: 技術 | E6: 装置操作・罠設置・修理・制作補助能力。戦闘中のトラップ性能や道具効果が向上する。 | G6: 周囲 | H6: 自分を中心とした円形範囲を攻撃する。間に対象がいると後ろには当たらない | I6: around
A7: HPダメージ | B7: 対象のHPにダメージを与える | D7: 隠密 | E7: 発見されにくくなる。奇襲成功率や離脱成功率が上昇し、不意打ち時の威力が増加する。 | G7: 前方 | H7: 自分前方の矩形（長方形）範囲を攻撃する。 | I7: front
A8: 攻撃ダメージ | B8: 対象の攻撃値を一時的に減少させる | D8: 索敵 | E8: 敵や資源を発見しやすくなる。遭遇率制御、罠発見、危険察知能力が向上する。 | G8: ライン | H8: 2か所を指定しその間を攻撃 | I8: line
A9: 防御ダメージ | B9: 対象の防御値を一時的に減少させる | D9: 農業 | E9: 穀物・家畜など農業生産効率を上昇させる。災害による収穫減少を軽減する。 | G9: 全体 | H9: 対象陣営全体に効果が及ぶ | I9: all
A10: 魔力ダメージ | B10: 対象の魔力を一時的に減少させる | D10: 林業 | E10: 木材資源の取得量と森林管理効率を上昇させる。森林枯渇速度を軽減する。
A11: 精神ダメージ | B11: 対象の精神を一時的に減少させる | D11: 漁業 | E11: 水域資源の取得量を上昇させる。食料安定度に補正を与える。 | G11: 味方 | I11: all
A12: 速度ダメージ | B12: 対象の速度を一時的に減少させる | D12: 工業 | E12: 加工・生産効率を上昇させる。装備や施設の生産速度が向上する。 | G12: 敵 | I12: all
A13: 命中ダメージ | B13: 対象の命中を一時的に減少させる | D13: 統治 | E13: 都市安定度や治安を向上させる。反乱発生率を低下させ、維持費効率を改善する。 | G13: 全て | I13: all
A14: 技能ダメージ | B14: 対象の技能値を一時的に減少させる | D14: 交渉 | E14: 交易価格や外交成功率を上昇させる。条約締結や取引条件が有利になる。 | G14: 自身以外 | I14: all
A15: 炎上 | B15: 毎ターンHPダメージを受ける状態 | D15: 魔術 | E15: 魔法スキルの威力や成功率を向上させる。魔法道具の作成ができるようになり、防衛力が上昇する。 | G15: 放射 | H15: 使用者の前方へ扇状に放射する | I15: fan
A16: 凍結 | B16: 速度とAPと防御にダメージ | D16: 信仰 | E16: 宗教効果や祝福系能力を強化する。回復速度が上昇、アンデッドの出現を抑制できる。 | G16: 散弾 | H16: 指定方向の複数マスへ散開して攻撃する | I16: fan
A17: 帯電 | B17: 速度とAPと怯みにダメージ | G17: 縦 | H17: 指定方向へ縦一列を攻撃する | I17: line
A18: 腐蝕 | B18: 毎ターンHPダメージ＋防御にダメージ | G18: 爆発 | H18: 指定地点を中心に円形範囲を攻撃する | I18: circle
A19: 気絶 | B19: 一定時間行動不能になる状態 | G19: 炸裂 | H19: 指定地点を中心に炸裂し周囲へ効果を与える | I19: circle
A20: 遮断 | B20: 自身の後ろに攻撃が届かなくなる | G20: 奥1 | H20: 着弾点と、使用者から見て着弾点のさらに奥1マスを対象にする（計2マス）
A21: 恐怖 | B21: 攻撃・命中・士気などが低下する状態 | G21: 奥2 | H21: 着弾点と、その奥へ一直線に2マスを対象にする（計3マス）
A22: 混乱 | B22: 行動が指定したスキル、近くに攻撃、自分に攻撃、このターンAPがなくなるのどれかになる。 | G22: 後方2 | H22: 着弾点と、使用者から見て着弾点の奥側に隣接する左右2マスを対象にする（計3マス）
A23: 魅了 | B23: 一時的に敵対行動ができなくなる、または味方扱いになる状態 | G23: 横2 | H23: 着弾点と、進行方向に対して左右の隣接2マスを対象にする（計3マス）
A24: 吸血 | B24: 与えた出血ダメージ分をHPとして回復する | G24: 小扇 | H24: 着弾点を先端として奥側へ広がる小型の扇形範囲。着弾点を含む4マスを基本とする
A25: 吸収 | B25: 与えたダメージや効果の一部を自分の能力値に変換する | G25: 半径1 | H25: 着弾点を中心に隣接6マスを含む範囲（計7マス） | I25: circle
A26: 反射 | B26: 受けたダメージの一部を攻撃者へ返す
A27: 障壁 | B27: 追加HPを得て、なくなるまで追加効果を受けなくなる
A28: 時間停止 | B28: 一定時間対象の行動や時間経過を停止させる
A30: 吹き飛ばし | B30: 対象を後方へ移動させる
A31: 引き寄せ | B31: 対象を自分の方へ移動させる
A32: 位置交換 | B32: 対象と位置を入れ替える
A33: 転倒 | B33: 移動不可＋回避低下
A34: 浮遊 | B34: 地形効果を無視する
A35: 固定 | B35: 指定位置から移動不可
A37: 復活 | B37: 戦闘不能から復帰
A38: 不死 | B38: HP0でも一定ターン生存
A39: 封印 | B39: 特定属性無効化
... A70: 壁生成 | B70: 高さ+1マスの壁を作る。耐久値は魔法の値

Sheet 地形
A1: 地形 | B1: 詳細 | C1: モンスター危険度 | D1: 開拓難易度 | E1: 移動コスト | F1: 移動条件 | G1: 穀物 | H1: 野菜 | I1: 肉 | J1: 魚 | K1: 木材 | L1: 黒木 | M1: 特木 | N1: 石材 | O1: 鉄 | P1: 銀鉄 | Q1: 青金鋼 | R1: 赤黒鋼 | S1: 金 | T1: 銀 | U1: 宝石 | V1: 台風 | W1: 竜巻 | X1: 吹雪 | Y1: 噴火 | Z1: 砂嵐 | AA1: 洪水 | AB1: 地震 | AC1: 雷嵐 | AD1: HP | AE1: MP | AF1: ST | AG1: 攻撃 | AH1: 防御 | AI1: 魔力 | AJ1: 精神 | AK1: 速度 | AL1: 命中 | AM1: SIZ | AN1: 指揮 | AO1: 威圧 | AP1: 看破 | AQ1: 早業 | AR1: 技術 | AS1: 隠密 | AT1: 索敵 | AU1: 農業 | AV1: 林業 | AW1: 漁業 | AX1: 工業 | AY1: 統治 | AZ1: 交渉 | BA1: 魔術 | BB1: 信仰 | BD1: 保有可能人数 | BE1: 浄化 | BF1: 穢れ | BG1: 回復 | BH1: ヒーロー | BI1: 軍隊 | BJ1: 生成対象 | BK1: 生成順 | BL1: 生成色 | BM1: 生成重み | BN1: 生成略称 | BO1: 勢力配置区分 | BP1: 休火山候補率 | BQ1: 別名 | BR1: ターンダメージ最大HP率 | BS1: ターンダメージ耐性 | BT1: 変換レイヤー | BU1: 発見研究区分 | BV1: 必要発見研究Lv | BW1: 危険地帯設定
A2: 平地 | B2: 移動コスト1。基準マス。都市建設可。生産補正なし。視界良好。 | C2: 0.2 | D2: 1 | E2: 1 | F2: - | G2: 60 | H2: 40 | I2: 20 | J2: 0 | K2: 25 | L2: 0 | M2: 0 | N2: 25 | O2: 10 | P2: 0 | Q2: 0 | R2: 0 | S2: 0 | T2: 0 | U2: 0 | V2: 0 | W2: 0.1 | X2: 0 | Y2: 0 | Z2: 0 | AA2: 0.05 | AB2: -0.05 | AC2: 0.05 | BJ2: =TRUE() -> TRUE | BK2: 1 | BL2: #b6cc71 | BM2: 26 | BN2: 平 | BO2: 基本 | BT2: 基本
A3: 森 | B3: 移動コスト2。木材資源+。隠密+35 過剰採取で平地化。 | C3: 0.6 | D3: 3 | E3: 2 | F3: - | G3: 25 | H3: 60 | I3: 35 | J3: 0 | K3: 100 | L3: 0 | M3: 0 | N3: 25 | O3: 0 | P3: 0 | Q3: 0 | R3: 0 | S3: 0 | T3: 0 | U3: 0 | V3: -0.05 | W3: -0.05 | X3: 0.05 | Y3: 0 | Z3: 0 | AA3: 0.05 | AB3: 0.05 | AC3: 0.1 | AK3: -10 | AL3: -5 | AS3: 35 | BB3: 15 | BJ3: =TRUE() -> TRUE | BK3: 3 | BL3: #7fa56a | BM3: 18 | BN3: 森 | BO3: 基本 | BT3: 基本
A4: 丘陵 | B4: 移動コスト2。鉱石資源+中。都市建設可。 | C4: 0.5 | D4: 3 | E4: 2 | F4: - | G4: 20 | H4: 20 | I4: 60 | J4: 10 | K4: 40 | L4: 0 | M4: 0 | N4: 100 | O4: 80 | P4: 0 | Q4: 0 | R4: 0 | S4: 10 | T4: 0 | U4: 0 | V4: -0.05 | W4: -0.05 | X4: 0.1 | Y4: 0.1 | Z4: 0 | AA4: -0.05 | AB4: 0.15 | AC4: 0.1 | AS4: -10 | BJ4: =TRUE() -> TRUE | BK4: 4 | BL4: #a49367 | BM4: 12 | BN4: 丘 | BO4: 基本 | BQ4: 丘
A5: 山岳 | B5: 通常移動不可（飛行/特殊のみ可）。鉱石資源+大。都市建設不可。 | C5: 0.8 | D5: 5 | E5: 2 | F5: - | G5: 10 | H5: 10 | I5: 20 | J5: 10 | K5: 30 | L5: 0 | M5: 0 | N5: 150 | O5: 200 | P5: 0 | Q5: 0 | R5: 0 | S5: 30 | T5: 0 | U5: 0 | V5: -0.1 | W5: -0.05 | X5: 0.15 | Y5: 0.2 | Z5: 0 | AA5: -0.05 | AB5: 0.2 | AC5: 0.1 | AK5: -15 | AL5: -10 | BB5: 25 | BJ5: =TRUE() -> TRUE | BK5: 5 | BL5: #8b847d | BM5: 10 | BN5: 山 | BO5: 基本 | BP5: 0.2 | BQ5: 山
A6: 湖 | B6: 水上ユニットのみ移動可。食料+中。防御補正なし。 | C6: 0.5 | D6: 2 | E6: 1 | F6: 遊泳 | G6: 10 | H6: 10 | I6: 0 | J6: 90 | K6: 0 | L6: 0 | M6: 0 | N6: 0 | O6: 35 | P6: 0 | Q6: 0 | R6: 0 | S6: 8 | T6: 0 | U6: 0 | V6: 0.1 | W6: -0.1 | X6: -0.05 | Y6: 0 | Z6: 0 | AA6: 0.2 | AB6: -0.1 | AC6: 0.05 | BB6: 35 | BJ6: =TRUE() -> TRUE | BK6: 9 | BL6: #6ea5d1 | BM6: 8 | BN6: 湖 | BO6: 基本
A7: 河川 | B7: 移動コスト2（橋で1）。農業+20%。都市隣接で成長+。 | C7: 0.4 | D7: 2 | E7: 1 | F7: - | G7: 20 | H7: 15 | I7: 5 | J7: 35 | K7: 0 | L7: 0 | M7: 0 | N7: 0 | O7: 0 | P7: 0 | Q7: 0 | R7: 0 | S7: 5 | T7: 0 | U7: 0 | V7: 0.2 | W7: -0.05 | X7: -0.05 | Y7: 0 | Z7: 0 | AA7: 0.2 | AB7: -0.05 | AC7: 0.05 | BJ7: =TRUE() -> TRUE | BK7: 8 | BL7: #78aed8 | BM7: 10 | BN7: 川 | BO7: 基本 | BQ7: 河
A8: 大河 | B8: 移動コスト4（橋で1）水上ユニットはペナルティなし | C8: 0.4 | D8: 2 | E8: 4 | F8: - | G8: 25 | H8: 35 | I8: 10 | J8: 60 | K8: 0 | L8: 0 | M8: 0 | N8: 0 | O8: 0 | P8: 0 | Q8: 0 | R8: 0 | S8: 5 | T8: 0 | U8: 0 | V8: 0.2 | W8: -0.05 | X8: -0.05 | Y8: 0 | Z8: 0 | AA8: 0.2 | AB8: -0.05 | AC8: 0.05
A9: 海 | B9: 水上ユニットのみ移動可。交易+。港設置可。嵐イベント発生。 | C9: 0.75 | D9: 4 | E9: 2 | F9: 遊泳 | G9: 10 | H9: 10 | I9: 0 | J9: 110 | K9: 0 | L9: 0 | M9: 0 | N9: 0 | O9: 35 | P9: 0 | Q9: 0 | R9: 0 | S9: 20 | T9: 0 | U9: 0 | V9: 0.35 | W9: -0.1 | X9: -0.05 | Y9: 0 | Z9: 0 | AA9: 0.35 | AB9: -0.1 | AC9: 0.05 | BJ9: =TRUE() -> TRUE | BK9: 10 | BL9: #4f88ba | BM9: 7 | BN9: 海
A10: 荒野 | B10: 移動コスト1。基準マス。都市建設可。生産補正なし。視界良好。 | C10: 0.3 | D10: 1 | E10: 1 | F10: - | G10: 15 | H10: 15 | I10: 20 | J10: 0 | K10: 0 | L10: 0 | M10: 0 | N10: 100 | O10: 45 | P10: 0 | Q10: 0 | R10: 0 | S10: 5 | T10: 0 | U10: 0 | V10: 0 | W10: 0.1 | X10: 0 | Y10: 0 | Z10: 0.1 | AA10: 0 | AB10: 0.1 | AC10: 0 | BJ10: =TRUE() -> TRUE | BK10: 2 | BL10: #d9c98b | BM10: 12 | BN10: 荒 | BO10: 基本 | BQ10: 荒 | BT10: 基本
A11: 砂漠 | B11: 移動コスト2。生産-20%。水源があれば都市可。特殊資源あり。 | C11: 0.5 | D11: 4 | E11: 2 | F11: - | G11: 10 | H11: 10 | I11: 10 | J11: 0 | K11: 0 | L11: 0 | M11: 0 | N11: 50 | O11: 0 | P11: 0 | Q11: 0 | R11: 0 | S11: 30 | T11: 0 | U11: 0 | V11: -0.05 | W11: 0.05 | X11: -0.1 | Y11: 0 | Z11: 0.3 | AA11: -0.05 | AB11: 0.05 | AC11: 0.05 | AK11: -10 | AL11: -10 | AS11: -10 | BJ11: =TRUE() -> TRUE | BK11: 11 | BL11: #d8be76 | BM11: 7 | BN11: 砂 | BO11: 基本 | BT11: 基本
A12: 沼地 | B12: 移動コスト3。防御+5%。毒耐性判定発生。農業不可。 | C12: 0.65 | D12: 4 | E12: 3 | F12: - | G12: 10 | H12: 15 | I12: 20 | J12: 50 | K12: 20 | L12: 0 | M12: 0 | N12: 5 | O12: 0 | P12: 0 | Q12: 0 | R12: 0 | S12: 0 | T12: 0 | U12: 0 | V12: 0.1 | W12: 0 | X12: 0 | Y12: 0 | Z12: 0 | AA12: 0.3 | AB12: 0 | AC12: 0.1 | AK12: -25 | AL12: -15 | AS12: 10 | BO12: 特殊 | BQ12: 沼 | BT12: 特殊
A13: 湿地 | B13: 移動コスト3。防御+5%。毒耐性判定発生。農業不可。 | C13: 0.65 | D13: 4 | E13: 3 | F13: - | G13: 45 | H13: 30 | I13: 20 | J13: 30 | K13: 20 | L13: 0 | M13: 0 | N13: 5 | O13: 0 | P13: 0 | Q13: 0 | R13: 0 | S13: 0 | T13: 0 | U13: 0 | V13: 0.1 | W13: 0 | X13: 0 | Y13: 0 | Z13: 0 | AA13: 0.3 | AB13: 0 | AC13: 0.1 | AK13: -25 | AL13: -15 | AS13: 10 | BT13: 特殊
A14: 峡谷 | B14: 通常通行不可（橋必須）。防御+20%。地形要塞。 | C14: 0.7 | D14: 5 | E14: 2 | F14: 飛行 | G14: 5 | H14: 5 | I14: 15 | J14: 0 | K14: 5 | L14: 0 | M14: 0 | N14: 160 | O14: 120 | P14: 0 | Q14: 0 | R14: 0 | S14: 20 | T14: 0 | U14: 0 | V14: -0.1 | W14: -0.05 | X14: 0.05 | Y14: 0.1 | Z14: 0.05 | AA14: -0.2 | AB14: 0.3 | AC14: 0.05 | AS14: 15 | BO14: 特殊 | BQ14: 渓谷
A15: 洞窟 | B15: 地下扱い。視界制限。特殊資源+。地上ユニット制限あり。 | C15: 0.9 | D15: 6 | E15: 1 | F15: - | G15: 0 | H15: 0 | I15: 10 | J15: 0 | K15: 0 | L15: 0 | M15: 0 | N15: 80 | O15: 150 | P15: 0 | Q15: 0 | R15: 0 | S15: 40 | T15: 0 | U15: 0 | V15: 0 | W15: 0 | X15: 0 | Y15: 0 | Z15: 0 | AA15: -0.3 | AB15: 0.25 | AC15: 0 | AS15: 45 | BO15: 特殊 | BQ15: 洞 | BU15: 地下探索 | BV15: 1
A16: 雪原 | B16: 移動コスト2。生産-10%。寒冷耐性でペナルティ無効。 | C16: 0.65 | D16: 3 | E16: 1 | F16: - | G16: 12 | H16: 10 | I16: 35 | J16: 5 | K16: 8 | L16: 0 | M16: 0 | N16: 70 | O16: 50 | P16: 0 | Q16: 0 | R16: 0 | S16: 8 | T16: 0 | U16: 0 | V16: -0.05 | W16: 0.05 | X16: 0.25 | Y16: 0 | Z16: 0 | AA16: -0.05 | AB16: 0.1 | AC16: 0.1 | AK16: -15 | AL16: -10 | BJ16: =TRUE() -> TRUE | BK16: 6 | BL16: #cfdbe8 | BM16: 6 | BN16: 雪 | BO16: 基本 | BQ16: 雪 | BT16: 基本
A17: 火山 | B17: 都市不可。鉱石+大。噴火イベントあり。防御+15%。 | C17: 0.95 | D17: 6 | E17: 2 | F17: - | G17: 2 | H17: 3 | I17: 10 | J17: 0 | K17: 0 | L17: 0 | M17: 0 | N17: 180 | O17: 80 | P17: 0 | Q17: 0 | R17: 0 | S17: 80 | T17: 0 | U17: 0 | V17: 0 | W17: 0 | X17: 0 | Y17: 0.4 | Z17: 0.1 | AA17: -0.3 | AB17: 0.3 | AC17: 0.15 | BB17: 50 | BJ17: =TRUE() -> TRUE | BK17: 7 | BL17: #7e4f45 | BM17: 4 | BN17: 火 | BO17: 基本
A18: 溶岩 | B18: 通常移動不可。耐熱ユニットのみ可。ダメージ地形。 | C18: 0.9 | D18: 3 | E18: 2 | F18: 耐熱|炎耐性:100 | G18: -50 | H18: -50 | I18: -50 | J18: -50 | K18: -75 | L18: 0 | M18: 0 | N18: 25 | O18: 25 | P18: 0 | Q18: 0 | R18: 0 | S18: 10 | T18: 0 | U18: 0 | V18: 0 | W18: 0 | X18: 0 | Y18: 0 | Z18: 0 | AA18: 0 | AB18: 0 | AC18: 0 | AK18: -30 | AL18: -30 | BR18: 0.1 | BS18: 炎耐性
A19: 死の霧 | B19: アンデッドが発生するようになる霧。 そのマスで倒されたキャラや出現する敵にアンデッドが付与されることがある。 | C19: 0.9 | D19: 4 | E19: 0 | F19: - | G19: -50 | H19: -50 | I19: -50 | J19: -50 | K19: -75 | L19: 0 | M19: 0 | N19: 0 | O19: 0 | P19: 0 | Q19: 0 | R19: 0 | S19: 0 | T19: 0 | U19: 0 | V19: 0 | W19: 0 | X19: 0 | Y19: 0 | Z19: 0 | AA19: 0 | AB19: 0 | AC19: 0 | AL19: -15 | AS19: 20 | BF19: 50 | BT19: 特殊
A21: 薬草の群生地 | G21: 15 | H21: 15 | BE21: 5 | BG21: 10 | BT21: 特殊 | BU21: 生態調査 | BV21: 1
A22: 金山 | C22: 0.3 | S22: 40 | BU22: 地質調査 | BV22: 1
A23: 銀鉱脈 | C23: 0.15 | T23: 0 | BU23: 地質調査 | BV23: 1
A24: 宝石脈 | C24: 0.15 | U24: 0 | BU24: 地質調査 | BV24: 2
A25: 水脈 | C25: 0.1 | G25: 20 | J25: 10 | AA25: 0.25 | AB25: 0.25 | BG25: 5
A26: 戦場後 | G26: -15 | H26: -15 | I26: -15 | J26: -15 | K26: -15 | L26: 0 | M26: 0 | N26: -15 | O26: -15 | P26: 0 | Q26: 0 | R26: 0 | S26: -15 | T26: 0 | BF26: 20
A29: 道路1 | B29: 移動コスト-1（最低1）。建設コスト低。交易+小。 | C29: 0 | D29: 2 | G29: -10 | H29: -10 | I29: -10 | J29: -10 | K29: -10 | L29: 0 | M29: 0 | N29: -10 | O29: -10 | P29: 0 | Q29: 0 | R29: 0 | S29: -10 | T29: 0 | U29: 0 | V29: 0 | W29: 0 | X29: 0 | Y29: 0 | Z29: 0 | AA29: 0 | AB29: 0 | AC29: 0 | AS29: -30
A30: 道路2 | B30: 移動コスト1固定。交易+中。軍移動速度+。 | C30: 0 | D30: 3 | G30: -10 | H30: -10 | I30: -10 | J30: -10 | K30: -10 | L30: 0 | M30: 0 | N30: -10 | O30: -10 | P30: 0 | Q30: 0 | R30: 0 | S30: -10 | T30: 0 | U30: 0 | V30: 0 | W30: 0 | X30: 0 | Y30: 0 | Z30: 0 | AA30: 0 | AB30: 0 | AC30: 0 | AS30: -30
A31: 道路3 | B31: 移動コスト1固定。交易+大。補給効率+。軍事道路扱い。 | C31: 0 | D31: 4 | G31: -10 | H31: -10 | I31: -10 | J31: -10 | K31: -10 | L31: 0 | M31: 0 | N31: -10 | O31: -10 | P31: 0 | Q31: 0 | R31: 0 | S31: -10 | T31: 0 | U31: 0 | V31: 0 | W31: 0 | X31: 0 | Y31: 0 | Z31: 0 | AA31: 0 | AB31: 0 | AC31: 0 | AS31: -30
A32: 太陽の山 | B32: 太陽の光を宿す霊峰。勝利対象土地として使用する。
A33: 黄昏の樹 | B33: 黄昏の気配をまとった巨樹。勝利対象土地として使用する。
A34: 星の火口 | B34: 星光を宿す火口。勝利対象土地として使用する。
A35: 宇宙の海 | B35: 宇宙を映す海域。勝利対象土地として使用する。
A36: 酸の沼 | B36: 常設危険地帯。沼地,洞窟に重ねる環境レイヤー。 | BJ36: FALSE | BM36: 0 | BT36: 環境 | BV36: 0 | BW36: {"disasterId":"危険地帯:酸の沼","regionSize":12,"chance":0.18,"radius":1,"terrains":["沼地"],"underground":true,"color":"#A4C742"}
A37: 毒沼 | B37: 常設危険地帯。湿地,森に重ねる環境レイヤー。 | BJ37: FALSE | BM37: 0 | BT37: 環境 | BV37: 0 | BW37: {"disasterId":"危険地帯:毒沼","regionSize":12,"chance":0.18,"radius":1,"terrains":["湿地","森","森林"],"interiorForest":true,"color":"#6C9A3A"}
A38: 常霧の谷 | B38: 常設危険地帯。峡谷,湖に重ねる環境レイヤー。 | BJ38: FALSE | BM38: 0 | BT38: 環境 | BV38: 0 | BW38: {"disasterId":"危険地帯:常霧の谷","regionSize":12,"chance":0.18,"radius":1,"terrains":["峡谷","渓谷"],"near":["湖","河川"],"color":"#DCE7EB"}
A39: 噴気地帯 | B39: 常設危険地帯。火山に重ねる環境レイヤー。 | BJ39: FALSE | BM39: 0 | BT39: 環境 | BV39: 0 | BW39: {"disasterId":"危険地帯:噴気地帯","regionSize":12,"chance":0.18,"radius":1,"near":["火山","溶岩"],"color":"#CFB879"}
A40: 極寒地帯 | B40: 常設危険地帯。雪原,山岳に重ねる環境レイヤー。 | BJ40: FALSE | BM40: 0 | BT40: 環境 | BV40: 0 | BW40: {"disasterId":"危険地帯:極寒地帯","regionSize":12,"chance":0.18,"radius":1,"terrains":["雪原","雪山","氷原"],"minimumHeight":5,"color":"#83D9FA"}
A41: 瘴気地帯 | B41: 常設危険地帯。廃墟,洞窟に重ねる環境レイヤー。 | BJ41: FALSE | BM41: 0 | BT41: 環境 | BV41: 0 | BW41: {"disasterId":"危険地帯:瘴気地帯","regionSize":12,"chance":0.18,"radius":1,"terrains":["廃墟","遺跡","洞窟"],"underground":true,"deep":true,"color":"#A6BD48"}

Sheet 出現敵
A1: 出現地形 | B1: 種族名 | C1: チェック用 | D1: 好戦的 | E1: 種族 | F1: サブクラス | G1: Lv_Min | H1: Lv_Max | I1: 出現数 | J1: 備考 | K1: 武器 | L1: 副武器 | M1: 胴 | N1: 頭 | O1: 足 | P1: 装飾1 | Q1: 装飾2 | R1: 画像 | S1: 巣 | W1: ID | X1: 画像ファイル | Y1: 画像番号 | Z1: 画像サイズ連動 | AA1: 出現形態 | AB1: 集団数_Min | AC1: 集団数_Max | AD1: 編成人数 | AE1: 最低気温 | AF1: 最高気温 | AG1: 出現しやすい天候
A2: 1 | B2: 2 | C2: 3 | D2: 4 | E2: 5 | F2: 6 | G2: 7 | H2: 8 | I2: 9 | J2: 10 | K2: 11 | L2: 12 | M2: 13 | N2: 14 | O2: 15 | P2: 16 | Q2: 17 | R2: 18
A3: 平地 | B3: ホーク | C3: =LET( _xlpm.dOK,COUNTIF('クラス'!A:A,E3)>0, _xlpm.eOK,COUNTIF('クラス'!A:A,F3)>0, IF(_xlpm.dOK,"○","×") & IF(_xlpm.eOK,"○","×") ) -> ○× | D3: TRUE | E3: ホーク | G3: 2 | H3: 6 | R3: イーグル | S3: =IFERROR(VLOOKUP(B3,$U:$V,2,FALSE),"") -> 鳥系生物の巣 | U3: ホーク | V3: 鳥系生物の巣 | W3: 出現敵:平地:ホーク:5:8 | X3: ホーク・スネーク_ユニット集.webp | Y3: 1 | AD3: 1
A4: 平地 | B4: スネーク | C4: =LET( _xlpm.dOK,COUNTIF('クラス'!A:A,E4)>0, _xlpm.eOK,COUNTIF('クラス'!A:A,F4)>0, IF(_xlpm.dOK,"○","×") & IF(_xlpm.eOK,"○","×") ) -> ○× | E4: スネーク | G4: 1 | H4: 5 | R4: スネーク | S4: =IFERROR(VLOOKUP(B4,$U:$V,2,FALSE),"") -> 肉食生物の巣 | U4: スネーク | V4: 肉食生物の巣 | W4: 出現敵:平地:スネーク:4:7 | X4: ホーク・スネーク_ユニット集.webp | Y4: 7 | AD4: 1 | AE4: 0 | AF4: 45 | AG4: 雨/雷雨
A5: 平地 | B5: アンケグ | C5: =LET( _xlpm.dOK,COUNTIF('クラス'!A:A,E5)>0, _xlpm.eOK,COUNTIF('クラス'!A:A,F5)>0, IF(_xlpm.dOK,"○","×") & IF(_xlpm.eOK,"○","×") ) -> ×× | G5: 5 | H5: 10 | S5: =IFERROR(VLOOKUP(B5,$U:$V,2,FALSE),"") -> 虫系の巣 | U5: アンケグ | V5: 虫系の巣 | W5: 出現敵:平地:アンケグ:: | X5: アンケグ・スコーピオン_ユニット集.webp | Y5: 1 | AD5: 1
A6: 平地 | B6: ブレット | C6: =LET( _xlpm.dOK,COUNTIF('クラス'!A:A,E6)>0, _xlpm.eOK,COUNTIF('クラス'!A:A,F6)>0, IF(_xlpm.dOK,"○","×") & IF(_xlpm.eOK,"○","×") ) -> ×× | S6: =IFERROR(VLOOKUP(B6,$U:$V,2,FALSE),"") -> 地中生物の巣 | U6: ブレット | V6: 地中生物の巣 | W6: 出現敵:平地:ブレット:: | AD6: 1
A7: 平地 | B7: マンティコア | C7: =LET( _xlpm.dOK,COUNTIF('クラス'!A:A,E7)>0, _xlpm.eOK,COUNTIF('クラス'!A:A,F7)>0, IF(_xlpm.dOK,"○","×") & IF(_xlpm.eOK,"○","×") ) -> ○○ | D7: TRUE | E7: タイガー | F7: ホーク | G7: 5 | H7: 15 | R7: マンティコア | S7: =IFERROR(VLOOKUP(B7,$U:$V,2,FALSE),"") -> 肉食生物の巣 | U7: マンティコア | V7: 肉食生物の巣 | W7: 出現敵:平地:マンティコア:12:15 | X7: 魔獣_ユニット集2.webp | Y7: 1 | AD7: 1
A8: 平地 | B8: ディスプレイサービースト | C8: =LET( _xlpm.dOK,COUNTIF('クラス'!A:A,E8)>0, _xlpm.eOK,COUNTIF('クラス'!A:A,F8)>0, IF(_xlpm.dOK,"○","×") & IF(_xlpm.eOK,"○","×") ) -> ○○ | E8: ウルフ | F8: ゴースト | G8: 5 | H8: 15 | R8: ディスプレイサービースト | S8: =IFERROR(VLOOKUP(B8,$U:$V,2,FALSE),"") -> 肉食生物の巣 | U8: ディスプレイサービースト | V8: 肉食生物の巣 | W8: 出現敵:平地:ディスプレイサービースト:12:15 | X8: 魔獣_ユニット集2.webp | Y8: 6 | AD8: 1
A9: 平地 | B9: ワイバーン | C9: =LET( _xlpm.dOK,COUNTIF('クラス'!A:A,E9)>0, _xlpm.eOK,COUNTIF('クラス'!A:A,F9)>0, IF(_xlpm.dOK,"○","×") & IF(_xlpm.eOK,"○","×") ) -> ○× | D9: TRUE | E9: ワイバーン | G9: 15 | H9: 20 | R9: ワイバーン | S9: =IFERROR(VLOOKUP(B9,$U:$V,2,FALSE),"") -> 飛竜の巣 | U9: ワイバーン | V9: 飛竜の巣 | W9: 出現敵:平地:ワイバーン:15:20 | AD9: 1
C10: =LET( _xlpm.dOK,COUNTIF('クラス'!A:A,E10)>0, _xlpm.eOK,COUNTIF('クラス'!A:A,F10)>0, IF(_xlpm.dOK,"○","×") & IF(_xlpm.eOK,"○","×") ) -> ×× | S10: =IFERROR(VLOOKUP(B10,$U:$V,2,FALSE),"")
A11: 荒野 | B11: ウルフ | C11: =LET( _xlpm.dOK,COUNTIF('クラス'!A:A,E11)>0, _xlpm.eOK,COUNTIF('クラス'!A:A,F11)>0, IF(_xlpm.dOK,"○","×") & IF(_xlpm.eOK,"○","×") ) -> ○× | D11: TRUE | E11: ウルフ | G11: 3 | H11: 7 | R11: ファングウルフ | S11: =IFERROR(VLOOKUP(B11,$U:$V,2,FALSE),"") -> 肉食生物の巣 | U11: ウルフ | V11: 肉食生物の巣 | W11: 出現敵:荒野:ウルフ:5:8 | X11: 魔獣_ユニット集1.webp | Y11: 3 | AD11: 1
A12: 荒野 | B12: スネーク | C12: =LET( _xlpm.dOK,COUNTIF('クラス'!A:A,E12)>0, _xlpm.eOK,COUNTIF('クラス'!A:A,F12)>0, IF(_xlpm.dOK,"○","×") & IF(_xlpm.eOK,"○","×") ) -> ○× | E12: スネーク | G12: 1 | H12: 5 | R12: スネーク | S12: =IFERROR(VLOOKUP(B12,$U:$V,2,FALSE),"") -> 肉食生物の巣 | U12: スネーク | V12: 肉食生物の巣 | W12: 出現敵:荒野:スネーク:4:7 | X12: ホーク・スネーク_ユニット集.webp | Y12: 7 | AD12: 1 | AE12: 0 | AF12: 45 | AG12: 雨/雷雨
A13: 荒野 | B13: クロコダイル | C13: =LET( _xlpm.dOK,COUNTIF('クラス'!A:A,E13)>0, _xlpm.eOK,COUNTIF('クラス'!A:A,F13)>0, IF(_xlpm.dOK,"○","×") & IF(_xlpm.eOK,"○","×") ) -> ○× | D13: TRUE | E13: クロコダイル | G13: 4 | H13: 8 | S13: =IFERROR(VLOOKUP(B13,$U:$V,2,FALSE),"") -> 肉食生物の巣 | U13: クロコダイル | V13: 肉食生物の巣 | W13: 出現敵:荒野:クロコダイル:7:9 | X13: クロコダイル・タイガー_ユニット集.webp | Y13: 1 | AD13: 1 | AE13: 0 | AF13: 45 | AG13: 雨/雷雨
A14: 荒野 | B14: デザートワーム | C14: =LET( _xlpm.dOK,COUNTIF('クラス'!A:A,E14)>0, _xlpm.eOK,COUNTIF('クラス'!A:A,F14)>0, IF(_xlpm.dOK,"○","×") & IF(_xlpm.eOK,"○","×") ) -> ○× | E14: スネーク | G14: 5 | H14: 10 | S14: =IFERROR(VLOOKUP(B14,$U:$V,2,FALSE),"") -> 地中生物の巣 | U14: デザートワーム | V14: 地中生物の巣 | W14: 出現敵:荒野:デザートワーム:8:12 | X14: ワーム_ユニット集.webp | Y14: 2 | AD14: 1 | AE14: 0 | AF14: 45 | AG14: 雨/雷雨
A15: 荒野 | B15: マンティコア | C15: =LET( _xlpm.dOK,COUNTIF('クラス'!A:A,E15)>0, _xlpm.eOK,COUNTIF('クラス'!A:A,F15)>0, IF(_xlpm.dOK,"○","×") & IF(_xlpm.eOK,"○","×") ) -> ○○ | D15: TRUE | E15: タイガー | F15: ホーク | G15: 5 | H15: 15 | R15: マンティコア | S15: =IFERROR(VLOOKUP(B15,$U:$V,2,FALSE),"") -> 肉食生物の巣 | U15: マンティコア | V15: 肉食生物の巣 | W15: 出現敵:荒野:マンティコア:12:15 | X15: 魔獣_ユニット集2.webp | Y15: 1 | AD15: 1
A16: 荒野 | B16: ディスプレイサービースト | C16: =LET( _xlpm.dOK,COUNTIF('クラス'!A:A,E16)>0, _xlpm.eOK,COUNTIF('クラス'!A:A,F16)>0, IF(_xlpm.dOK,"○","×") & IF(_xlpm.eOK,"○","×") ) -> ○○ | E16: ウルフ | F16: ゴースト | G16: 5 | H16: 15 | R16: ディスプレイサービースト | S16: =IFERROR(VLOOKUP(B16,$U:$V,2,FALSE),"") -> 肉食生物の巣 | U16: ディスプレイサービースト | V16: 肉食生物の巣 | W16: 出現敵:荒野:ディスプレイサービースト:12:15 | X16: 魔獣_ユニット集2.webp | Y16: 6 | AD16: 1
A17: 荒野 | B17: ワイバーン | C17: =LET( _xlpm.dOK,COUNTIF('クラス'!A:A,E17)>0, _xlpm.eOK,COUNTIF('クラス'!A:A,F17)>0, IF(_xlpm.dOK,"○","×") & IF(_xlpm.eOK,"○","×") ) -> ○× | D17: TRUE | E17: ワイバーン | G17: 15 | H17: 20 | R17: ワイバーン | S17: =IFERROR(VLOOKUP(B17,$U:$V,2,FALSE),"") -> 飛竜の巣 | U17: ワイバーン | V17: 飛竜の巣 | W17: 出現敵:荒野:ワイバーン:15:20 | AD17: 1
C18: =LET( _xlpm.dOK,COUNTIF('クラス'!A:A,E18)>0, _xlpm.eOK,COUNTIF('クラス'!A:A,F18)>0, IF(_xlpm.dOK,"○","×") & IF(_xlpm.eOK,"○","×") ) -> ×× | S18: =IFERROR(VLOOKUP(B18,$U:$V,2,FALSE),"")
A19: 砂漠 | B19: マミー | C19: =LET( _xlpm.dOK,COUNTIF('クラス'!A:A,E19)>0, _xlpm.eOK,COUNTIF('クラス'!A:A,F19)>0, IF(_xlpm.dOK,"○","×") & IF(_xlpm.eOK,"○","×") ) -> ×× | S19: =IFERROR(VLOOKUP(B19,$U:$V,2,FALSE),"") -> 死霊の巣 | U19: マミー | V19: 死霊の巣 | W19: 出現敵:砂漠:マミー:: | AD19: 1
A20: 砂漠 | B20: ラミア | C20: =LET( _xlpm.dOK,COUNTIF('クラス'!A:A,E20)>0, _xlpm.eOK,COUNTIF('クラス'!A:A,F20)>0, IF(_xlpm.dOK,"○","×") & IF(_xlpm.eOK,"○","×") ) -> ×× | S20: =IFERROR(VLOOKUP(B20,$U:$V,2,FALSE),"") -> 毒生成物の巣 | U20: ラミア | V20: 毒生成物の巣 | W20: 出現敵:砂漠:ラミア:: | AD20: 1
A21: 砂漠 | B21: ブルードラゴン | C21: =LET( _xlpm.dOK,COUNTIF('クラス'!A:A,E21)>0, _xlpm.eOK,COUNTIF('クラス'!A:A,F21)>0, IF(_xlpm.dOK,"○","×") & IF(_xlpm.eOK,"○","×") ) -> ×× | S21: =IFERROR(VLOOKUP(B21,$U:$V,2,FALSE),"") -> 飛竜の巣 | U21: ブルードラゴン | V21: 飛竜の巣 | W21: 出現敵:砂漠:ブルードラゴン:: | AD21: 1
A22: 砂漠 | B22: パープルワーム | C22: =LET( _xlpm.dOK,COUNTIF('クラス'!A:A,E22)>0, _xlpm.eOK,COUNTIF('クラス'!A:A,F22)>0, IF(_xlpm.dOK,"○","×") & IF(_xlpm.eOK,"○","×") ) -> ×× | R22: パープルワーム | S22: =IFERROR(VLOOKUP(B22,$U:$V,2,FALSE),"") -> 地中生物の巣 | U22: パープルワーム | V22: 地中生物の巣 | W22: 出現敵:砂漠:パープルワーム:: | X22: ワーム_ユニット集.webp | Y22: 3 | AD22: 1
A23: 砂漠 | B23: ジャイアントスコーピオン | C23: =LET( _xlpm.dOK,COUNTIF('クラス'!A:A,E23)>0, _xlpm.eOK,COUNTIF('クラス'!A:A,F23)>0, IF(_xlpm.dOK,"○","×") & IF(_xlpm.eOK,"○","×") ) -> ×× | G23: 5 | H23: 10 | R23: スコーピオン | S23: =IFERROR(VLOOKUP(B23,$U:$V,2,FALSE),"") -> 虫系の巣 | U23: ジャイアントスコーピオン | V23: 虫系の巣 | W23: 出現敵:砂漠:ジャイアントスコーピオン:: | X23: アンケグ・スコーピオン_ユニット集.webp | Y23: 7 | AD23: 1
A24: 砂漠 | B24: スフィンクス | C24: =LET( _xlpm.dOK,COUNTIF('クラス'!A:A,E24)>0, _xlpm.eOK,COUNTIF('クラス'!A:A,F24)>0, IF(_xlpm.dOK,"○","×") & IF(_xlpm.eOK,"○","×") ) -> ×× | S24: =IFERROR(VLOOKUP(B24,$U:$V,2,FALSE),"") -> 肉食生物の巣 | U24: スフィンクス | V24: 肉食生物の巣 | W24: 出現敵:砂漠:スフィンクス:: | X24: 魔獣_ユニット集2.webp | Y24: 5 | AD24: 1
A25: 砂漠 | B25: サンドエレメンタル | C25: =LET( _xlpm.dOK,COUNTIF('クラス'!A:A,E25)>0, _xlpm.eOK,COUNTIF('クラス'!A:A,F25)>0, IF(_xlpm.dOK,"○","×") & IF(_xlpm.eOK,"○","×") ) -> ×× | S25: =IFERROR(VLOOKUP(B25,$U:$V,2,FALSE),"") -> 土の輪 | U25: サンドエレメンタル | V25: 土の輪 | W25: 出現敵:砂漠:サンドエレメンタル:: | AD25: 1
A26: 砂漠 | B26: デザートワーム | C26: =LET( _xlpm.dOK,COUNTIF('クラス'!A:A,E26)>0, _xlpm.eOK,COUNTIF('クラス'!A:A,F26)>0, IF(_xlpm.dOK,"○","×") & IF(_xlpm.eOK,"○","×") ) -> ×× | G26: 5 | H26: 10 | R26: デザートワーム | S26: =IFERROR(VLOOKUP(B26,$U:$V,2,FALSE),"") -> 地中生物の巣 | U26: デザートワーム | V26: 地中生物の巣 | W26: 出現敵:砂漠:デザートワーム:: | X26: ワーム_ユニット集.webp | Y26: 2 | AD26: 1
A27: 砂漠 | B27: デザートレイス | C27: =LET( _xlpm.dOK,COUNTIF('クラス'!A:A,E27)>0, _xlpm.eOK,COUNTIF('クラス'!A:A,F27)>0, IF(_xlpm.dOK,"○","×") & IF(_xlpm.eOK,"○","×") ) -> ×× | S27: =IFERROR(VLOOKUP(B27,$U:$V,2,FALSE),"") -> 死霊の巣 | U27: デザートレイス | V27: 死霊の巣 | W27: 出現敵:砂漠:デザートレイス:: | AD27: 1
C28: =LET( _xlpm.dOK,COUNTIF('クラス'!A:A,E28)>0, _xlpm.eOK,COUNTIF('クラス'!A:A,F28)>0, IF(_xlpm.dOK,"○","×") & IF(_xlpm.eOK,"○","×") ) -> ×× | S28: =IFERROR(VLOOKUP(B28,$U:$V,2,FALSE),"")
C29: =LET( _xlpm.dOK,COUNTIF('クラス'!A:A,E29)>0, _xlpm.eOK,COUNTIF('クラス'!A:A,F29)>0, IF(_xlpm.dOK,"○","×") & IF(_xlpm.eOK,"○","×") ) -> ×× | S29: =IFERROR(VLOOKUP(B29,$U:$V,2,FALSE),"") | U29: ドライアド | V29: 植物生物の巣
A30: 森 | B30: ドライアド | C30: =LET( _xlpm.dOK,COUNTIF('クラス'!A:A,E30)>0, _xlpm.eOK,COUNTIF('クラス'!A:A,F30)>0, IF(_xlpm.dOK,"○","×") & IF(_xlpm.eOK,"○","×") ) -> ×× | S30: =IFERROR(VLOOKUP(B30,$U:$V,2,FALSE),"") -> 植物生物の巣 | U30: トレント | V30: 植物生物の巣 | W30: 出現敵:森:ドライアド:: | AD30: 1
A31: 森 | B31: トレント | C31: =LET( _xlpm.dOK,COUNTIF('クラス'!A:A,E31)>0, _xlpm.eOK,COUNTIF('クラス'!A:A,F31)>0, IF(_xlpm.dOK,"○","×") & IF(_xlpm.eOK,"○","×") ) -> ×× | R31: トレント | S31: =IFERROR(VLOOKUP(B31,$U:$V,2,FALSE),"") -> 植物生物の巣 | U31: アウルベア | V31: 肉食生物の巣 | W31: 出現敵:森:トレント:: | AD31: 1
A32: 森 | B32: アウルベア | C32: =LET( _xlpm.dOK,COUNTIF('クラス'!A:A,E32)>0, _xlpm.eOK,COUNTIF('クラス'!A:A,F32)>0, IF(_xlpm.dOK,"○","×") & IF(_xlpm.eOK,"○","×") ) -> ○○ | D32: TRUE | E32: ベア | F32: ウィンドアニマル | G32: 15 | H32: 25 | R32: アウルベア | S32: =IFERROR(VLOOKUP(B32,$U:$V,2,FALSE),"") -> 肉食生物の巣 | U32: グリーンハグ | V32: 毒生成物の巣 | W32: 出現敵:森:アウルベア:15:25 | X32: 魔獣_ユニット集2.webp | Y32: 4 | AD32: 1
A33: 森 | B33: グリーンハグ | C33: =LET( _xlpm.dOK,COUNTIF('クラス'!A:A,E33)>0, _xlpm.eOK,COUNTIF('クラス'!A:A,F33)>0, IF(_xlpm.dOK,"○","×") & IF(_xlpm.eOK,"○","×") ) -> ×× | S33: =IFERROR(VLOOKUP(B33,$U:$V,2,FALSE),"") -> 毒生成物の巣 | U33: シャンブリングマウンド | V33: 植物生物の巣 | W33: 出現敵:森:グリーンハグ:: | AD33: 1
A34: 森 | B34: シャンブリングマウンド | C34: =LET( _xlpm.dOK,COUNTIF('クラス'!A:A,E34)>0, _xlpm.eOK,COUNTIF('クラス'!A:A,F34)>0, IF(_xlpm.dOK,"○","×") & IF(_xlpm.eOK,"○","×") ) -> ×× | S34: =IFERROR(VLOOKUP(B34,$U:$V,2,FALSE),"") -> 植物生物の巣 | U34: レシー | V34: 植物生物の巣 | W34: 出現敵:森:シャンブリングマウンド:: | AD34: 1
A35: 森 | B35: レシー | C35: =LET( _xlpm.dOK,COUNTIF('クラス'!A:A,E35)>0, _xlpm.eOK,COUNTIF('クラス'!A:A,F35)>0, IF(_xlpm.dOK,"○","×") & IF(_xlpm.eOK,"○","×") ) -> ×× | S35: =IFERROR(VLOOKUP(B35,$U:$V,2,FALSE),"") -> 植物生物の巣 | U35: ニンフ | V35: 植物生物の巣 | W35: 出現敵:森:レシー:: | AD35: 1
A36: 森 | B36: ニンフ | C36: =LET( _xlpm.dOK,COUNTIF('クラス'!A:A,E36)>0, _xlpm.eOK,COUNTIF('クラス'!A:A,F36)>0, IF(_xlpm.dOK,"○","×") & IF(_xlpm.eOK,"○","×") ) -> ×× | S36: =IFERROR(VLOOKUP(B36,$U:$V,2,FALSE),"") -> 植物生物の巣 | U36: フェアリードラゴン | V36: 風の輪 | W36: 出現敵:森:ニンフ:: | AD36: 1
A37: 森 | B37: フェアリードラゴン | C37: =LET( _xlpm.dOK,COUNTIF('クラス'!A:A,E37)>0, _xlpm.eOK,COUNTIF('クラス'!A:A,F37)>0, IF(_xlpm.dOK,"○","×") & IF(_xlpm.eOK,"○","×") ) -> ×× | S37: =IFERROR(VLOOKUP(B37,$U:$V,2,FALSE),"") -> 風の輪 | U37: タイガー | V37: 肉食生物の巣 | W37: 出現敵:森:フェアリードラゴン:: | AD37: 1
A38: 森 | B38: タイガー | C38: =LET( _xlpm.dOK,COUNTIF('クラス'!A:A,E38)>0, _xlpm.eOK,COUNTIF('クラス'!A:A,F38)>0, IF(_xlpm.dOK,"○","×") & IF(_xlpm.eOK,"○","×") ) -> ○× | D38: TRUE | E38: タイガー | G38: 5 | H38: 10 | R38: タイガー | S38: =IFERROR(VLOOKUP(B38,$U:$V,2,FALSE),"") -> 肉食生物の巣 | U38: ウルフ | V38: 肉食生物の巣 | W38: 出現敵:森:タイガー:9:15 | X38: クロコダイル・タイガー_ユニット集.webp | Y38: 7 | AD38: 1
A39: 森 | B39: ウルフ | C39: =LET( _xlpm.dOK,COUNTIF('クラス'!A:A,E39)>0, _xlpm.eOK,COUNTIF('クラス'!A:A,F39)>0, IF(_xlpm.dOK,"○","×") & IF(_xlpm.eOK,"○","×") ) -> ○× | E39: ウルフ | G39: 3 | H39: 7 | R39: ファングウルフ | S39: =IFERROR(VLOOKUP(B39,$U:$V,2,FALSE),"") -> 肉食生物の巣 | W39: 出現敵:森:ウルフ:9:15 | X39: 魔獣_ユニット集1.webp | Y39: 3 | AD39: 1
C40: =LET( _xlpm.dOK,COUNTIF('クラス'!A:A,E40)>0, _xlpm.eOK,COUNTIF('クラス'!A:A,F40)>0, IF(_xlpm.dOK,"○","×") & IF(_xlpm.eOK,"○","×") ) -> ×× | S40: =IFERROR(VLOOKUP(B40,$U:$V,2,FALSE),"") | U40: ブラックドラゴン | V40: 飛竜の巣
A41: 沼地 | B41: ブラックドラゴン | C41: =LET( _xlpm.dOK,COUNTIF('クラス'!A:A,E41)>0, _xlpm.eOK,COUNTIF('クラス'!A:A,F41)>0, IF(_xlpm.dOK,"○","×") & IF(_xlpm.eOK,"○","×") ) -> ×× | S41: =IFERROR(VLOOKUP(B41,$U:$V,2,FALSE),"") -> 飛竜の巣 | U41: シャンブリングマウンド | V41: 植物生物の巣 | W41: 出現敵:沼地:ブラックドラゴン:: | AD41: 1
A42: 沼地 | B42: シャンブリングマウンド | C42: =LET( _xlpm.dOK,COUNTIF('クラス'!A:A,E42)>0, _xlpm.eOK,COUNTIF('クラス'!A:A,F42)>0, IF(_xlpm.dOK,"○","×") & IF(_xlpm.eOK,"○","×") ) -> ×× | S42: =IFERROR(VLOOKUP(B42,$U:$V,2,FALSE),"") -> 植物生物の巣 | U42: ウィルオウィスプ | V42: 闇の輪 | W42: 出現敵:沼地:シャンブリングマウンド:: | AD42: 1
A43: 沼地 | B43: ウィルオウィスプ | C43: =LET( _xlpm.dOK,COUNTIF('クラス'!A:A,E43)>0, _xlpm.eOK,COUNTIF('クラス'!A:A,F43)>0, IF(_xlpm.dOK,"○","×") & IF(_xlpm.eOK,"○","×") ) -> ×× | S43: =IFERROR(VLOOKUP(B43,$U:$V,2,FALSE),"") -> 闇の輪 | U43: トロル | V43: 肉食生物の巣 | W43: 出現敵:沼地:ウィルオウィスプ:: | AD43: 1
A44: 沼地 | B44: トロル | C44: =LET( _xlpm.dOK,COUNTIF('クラス'!A:A,E44)>0, _xlpm.eOK,COUNTIF('クラス'!A:A,F44)>0, IF(_xlpm.dOK,"○","×") & IF(_xlpm.eOK,"○","×") ) -> ×× | S44: =IFERROR(VLOOKUP(B44,$U:$V,2,FALSE),"") -> 肉食生物の巣 | U44: ハイドラ | V44: 肉食生物の巣 | W44: 出現敵:沼地:トロル:: | AD44: 1
A45: 沼地 | B45: ハイドラ | C45: =LET( _xlpm.dOK,COUNTIF('クラス'!A:A,E45)>0, _xlpm.eOK,COUNTIF('クラス'!A:A,F45)>0, IF(_xlpm.dOK,"○","×") & IF(_xlpm.eOK,"○","×") ) -> ×× | S45: =IFERROR(VLOOKUP(B45,$U:$V,2,FALSE),"") -> 肉食生物の巣 | U45: マッドゴーレム | V45: 地中生物の巣 | W45: 出現敵:沼地:ハイドラ:: | X45: 魔獣_ユニット集2.webp | Y45: 8 | AD45: 1
A46: 沼地 | B46: マッドゴーレム | C46: =LET( _xlpm.dOK,COUNTIF('クラス'!A:A,E46)>0, _xlpm.eOK,COUNTIF('クラス'!A:A,F46)>0, IF(_xlpm.dOK,"○","×") & IF(_xlpm.eOK,"○","×") ) -> ×× | S46: =IFERROR(VLOOKUP(B46,$U:$V,2,FALSE),"") -> 地中生物の巣 | U46: スワンプドラゴン | V46: 飛竜の巣 | W46: 出現敵:沼地:マッドゴーレム:: | AD46: 1
A47: 沼地 | B47: スワンプドラゴン | C47: =LET( _xlpm.dOK,COUNTIF('クラス'!A:A,E47)>0, _xlpm.eOK,COUNTIF('クラス'!A:A,F47)>0, IF(_xlpm.dOK,"○","×") & IF(_xlpm.eOK,"○","×") ) -> ×× | S47: =IFERROR(VLOOKUP(B47,$U:$V,2,FALSE),"") -> 飛竜の巣 | W47: 出現敵:沼地:スワンプドラゴン:: | AD47: 1
C48: =LET( _xlpm.dOK,COUNTIF('クラス'!A:A,E48)>0, _xlpm.eOK,COUNTIF('クラス'!A:A,F48)>0, IF(_xlpm.dOK,"○","×") & IF(_xlpm.eOK,"○","×") ) -> ×× | S48: =IFERROR(VLOOKUP(B48,$U:$V,2,FALSE),"") | U48: グリフォン | V48: 鳥系生物の巣
C49: =LET( _xlpm.dOK,COUNTIF('クラス'!A:A,E49)>0, _xlpm.eOK,COUNTIF('クラス'!A:A,F49)>0, IF(_xlpm.dOK,"○","×") & IF(_xlpm.eOK,"○","×") ) -> ×× | S49: =IFERROR(VLOOKUP(B49,$U:$V,2,FALSE),"") | U49: ホーク | V49: 鳥系生物の巣
A50: 丘陵 | B50: グリフォン | C50: =LET( _xlpm.dOK,COUNTIF('クラス'!A:A,E50)>0, _xlpm.eOK,COUNTIF('クラス'!A:A,F50)>0, IF(_xlpm.dOK,"○","×") & IF(_xlpm.eOK,"○","×") ) -> ○○ | D50: TRUE | E50: タイガー | F50: ホーク | G50: 5 | H50: 15 | R50: グリフォン | S50: =IFERROR(VLOOKUP(B50,$U:$V,2,FALSE),"") -> 鳥系生物の巣 | U50: アースエレメンタル | V50: 土の輪 | W50: 出現敵:丘陵:グリフォン:8:12 | X50: 魔獣_ユニット集2.webp | Y50: 3 | AD50: 1
A51: 丘陵 | B51: ホーク | C51: =LET( _xlpm.dOK,COUNTIF('クラス'!A:A,E51)>0, _xlpm.eOK,COUNTIF('クラス'!A:A,F51)>0, IF(_xlpm.dOK,"○","×") & IF(_xlpm.eOK,"○","×") ) -> ○× | E51: ホーク | G51: 2 | H51: 6 | I51: 1~2 | R51: ホーク | S51: =IFERROR(VLOOKUP(B51,$U:$V,2,FALSE),"") -> 鳥系生物の巣 | U51: キメラ | V51: 肉食生物の巣 | W51: 出現敵:丘陵:ホーク:10:15 | X51: ホーク・スネーク_ユニット集.webp | Y51: 1 | AD51: 1
A52: 丘陵 | B52: アースエレメンタル | C52: =LET( _xlpm.dOK,COUNTIF('クラス'!A:A,E52)>0, _xlpm.eOK,COUNTIF('クラス'!A:A,F52)>0, IF(_xlpm.dOK,"○","×") & IF(_xlpm.eOK,"○","×") ) -> ○× | E52: アースエレメンタル | G52: 5 | H52: 15 | R52: 地の精霊 | S52: =IFERROR(VLOOKUP(B52,$U:$V,2,FALSE),"") -> 土の輪 | U52: ブレット | V52: 地中生物の巣 | W52: 出現敵:丘陵:アースエレメンタル:7:12 | X52: エレメンタル_ユニット集2.webp | Y52: 1 | Z52: TRUE | AD52: 1
A53: 丘陵 | B53: キメラ | C53: =LET( _xlpm.dOK,COUNTIF('クラス'!A:A,E53)>0, _xlpm.eOK,COUNTIF('クラス'!A:A,F53)>0, IF(_xlpm.dOK,"○","×") & IF(_xlpm.eOK,"○","×") ) -> ○○ | E53: タイガー | F53: スネーク | G53: 5 | H53: 15 | R53: キメラ | S53: =IFERROR(VLOOKUP(B53,$U:$V,2,FALSE),"") -> 肉食生物の巣 | U53: ヒルジャイアント | V53: 地中生物の巣 | W53: 出現敵:丘陵:キメラ:14:18 | X53: 魔獣_ユニット集2.webp | Y53: 2 | AD53: 1
A54: 丘陵 | B54: ブレット | C54: =LET( _xlpm.dOK,COUNTIF('クラス'!A:A,E54)>0, _xlpm.eOK,COUNTIF('クラス'!A:A,F54)>0, IF(_xlpm.dOK,"○","×") & IF(_xlpm.eOK,"○","×") ) -> ×× | S54: =IFERROR(VLOOKUP(B54,$U:$V,2,FALSE),"") -> 地中生物の巣 | U54: マンティコア | V54: 肉食生物の巣 | W54: 出現敵:丘陵:ブレット:: | AD54: 1
A55: 丘陵 | B55: ヒルジャイアント | C55: =LET( _xlpm.dOK,COUNTIF('クラス'!A:A,E55)>0, _xlpm.eOK,COUNTIF('クラス'!A:A,F55)>0, IF(_xlpm.dOK,"○","×") & IF(_xlpm.eOK,"○","×") ) -> ×× | S55: =IFERROR(VLOOKUP(B55,$U:$V,2,FALSE),"") -> 地中生物の巣 | U55: ワイバーン | V55: 飛竜の巣 | W55: 出現敵:丘陵:ヒルジャイアント:: | AD55: 1
A56: 丘陵 | B56: マンティコア | C56: =LET( _xlpm.dOK,COUNTIF('クラス'!A:A,E56)>0, _xlpm.eOK,COUNTIF('クラス'!A:A,F56)>0, IF(_xlpm.dOK,"○","×") & IF(_xlpm.eOK,"○","×") ) -> ×× | S56: =IFERROR(VLOOKUP(B56,$U:$V,2,FALSE),"") -> 肉食生物の巣 | W56: 出現敵:丘陵:マンティコア:: | X56: 魔獣_ユニット集2.webp | Y56: 1 | AD56: 1
A57: 丘陵 | B57: ワイバーン | C57: =LET( _xlpm.dOK,COUNTIF('クラス'!A:A,E57)>0, _xlpm.eOK,COUNTIF('クラス'!A:A,F57)>0, IF(_xlpm.dOK,"○","×") & IF(_xlpm.eOK,"○","×") ) -> ○× | D57: TRUE | E57: ワイバーン | G57: 15 | H57: 20 | I57: 2~4 | R57: ワイバーン | S57: =IFERROR(VLOOKUP(B57,$U:$V,2,FALSE),"") -> 飛竜の巣 | U57: サンダーバード | V57: 風の輪 | W57: 出現敵:丘陵:ワイバーン:15:20 | AD57: 1
C58: =LET( _xlpm.dOK,COUNTIF('クラス'!A:A,E58)>0, _xlpm.eOK,COUNTIF('クラス'!A:A,F58)>0, IF(_xlpm.dOK,"○","×") & IF(_xlpm.eOK,"○","×") ) -> ×× | S58: =IFERROR(VLOOKUP(B58,$U:$V,2,FALSE),"") | U58: アースエレメンタル | V58: 土の輪
A59: 山岳 | B59: サンダーバード | C59: =LET( _xlpm.dOK,COUNTIF('クラス'!A:A,E59)>0, _xlpm.eOK,COUNTIF('クラス'!A:A,F59)>0, IF(_xlpm.dOK,"○","×") & IF(_xlpm.eOK,"○","×") ) -> ○○ | E59: ホーク | F59: スパークアニマル | G59: 10 | H59: 15 | R59: ホーク | S59: =IFERROR(VLOOKUP(B59,$U:$V,2,FALSE),"") -> 風の輪 | U59: ロックベア | V59: 肉食生物の巣 | W59: 出現敵:山岳:サンダーバード:15:25 | AD59: 1
A60: 山岳 | B60: アースエレメンタル | C60: =LET( _xlpm.dOK,COUNTIF('クラス'!A:A,E60)>0, _xlpm.eOK,COUNTIF('クラス'!A:A,F60)>0, IF(_xlpm.dOK,"○","×") & IF(_xlpm.eOK,"○","×") ) -> ○× | E60: アースエレメンタル | G60: 15 | H60: 20 | I60: 1~4 | R60: 地の精霊 | S60: =IFERROR(VLOOKUP(B60,$U:$V,2,FALSE),"") -> 土の輪 | U60: ストーンジャイアント | V60: 地中生物の巣 | W60: 出現敵:山岳:アースエレメンタル:15:20 | X60: エレメンタル_ユニット集2.webp | Y60: 1 | Z60: TRUE | AD60: 1
A61: 山岳 | B61: ロックベア | C61: =LET( _xlpm.dOK,COUNTIF('クラス'!A:A,E61)>0, _xlpm.eOK,COUNTIF('クラス'!A:A,F61)>0, IF(_xlpm.dOK,"○","×") & IF(_xlpm.eOK,"○","×") ) -> ○○ | D61: TRUE | E61: ベア | F61: アースエレメンタル | G61: 25 | H61: 30 | R61: ラッシュベア | S61: =IFERROR(VLOOKUP(B61,$U:$V,2,FALSE),"") -> 肉食生物の巣 | U61: フロストジャイアント | V61: 水の輪 | W61: 出現敵:山岳:ロックベア:25:30 | AD61: 1
A62: 山岳 | B62: ストーンジャイアント | C62: =LET( _xlpm.dOK,COUNTIF('クラス'!A:A,E62)>0, _xlpm.eOK,COUNTIF('クラス'!A:A,F62)>0, IF(_xlpm.dOK,"○","×") & IF(_xlpm.eOK,"○","×") ) -> ×× | S62: =IFERROR(VLOOKUP(B62,$U:$V,2,FALSE),"") -> 地中生物の巣 | U62: ローパー | V62: 地中生物の巣 | W62: 出現敵:山岳:ストーンジャイアント:: | AD62: 1
A63: 山岳 | B63: フロストジャイアント | C63: =LET( _xlpm.dOK,COUNTIF('クラス'!A:A,E63)>0, _xlpm.eOK,COUNTIF('クラス'!A:A,F63)>0, IF(_xlpm.dOK,"○","×") & IF(_xlpm.eOK,"○","×") ) -> ×× | S63: =IFERROR(VLOOKUP(B63,$U:$V,2,FALSE),"") -> 水の輪 | U63: レッドドラゴン | V63: 飛竜の巣 | W63: 出現敵:山岳:フロストジャイアント:: | AD63: 1
A64: 山岳 | B64: ローパー | C64: =LET( _xlpm.dOK,COUNTIF('クラス'!A:A,E64)>0, _xlpm.eOK,COUNTIF('クラス'!A:A,F64)>0, IF(_xlpm.dOK,"○","×") & IF(_xlpm.eOK,"○","×") ) -> ×× | S64: =IFERROR(VLOOKUP(B64,$U:$V,2,FALSE),"") -> 地中生物の巣 | U64: ロック | V64: 鳥系生物の巣 | W64: 出現敵:山岳:ローパー:: | AD64: 1
A65: 山岳 | B65: レッドドラゴン | C65: =LET( _xlpm.dOK,COUNTIF('クラス'!A:A,E65)>0, _xlpm.eOK,COUNTIF('クラス'!A:A,F65)>0, IF(_xlpm.dOK,"○","×") & IF(_xlpm.eOK,"○","×") ) -> ×× | S65: =IFERROR(VLOOKUP(B65,$U:$V,2,FALSE),"") -> 飛竜の巣 | U65: バシリスク | V65: 肉食生物の巣 | W65: 出現敵:山岳:レッドドラゴン:: | AD65: 1
A66: 山岳 | B66: ロック | C66: =LET( _xlpm.dOK,COUNTIF('クラス'!A:A,E66)>0, _xlpm.eOK,COUNTIF('クラス'!A:A,F66)>0, IF(_xlpm.dOK,"○","×") & IF(_xlpm.eOK,"○","×") ) -> ×× | S66: =IFERROR(VLOOKUP(B66,$U:$V,2,FALSE),"") -> 鳥系生物の巣 | W66: 出現敵:山岳:ロック:: | AD66: 1
A67: 山岳 | B67: バシリスク | C67: =LET( _xlpm.dOK,COUNTIF('クラス'!A:A,E67)>0, _xlpm.eOK,COUNTIF('クラス'!A:A,F67)>0, IF(_xlpm.dOK,"○","×") & IF(_xlpm.eOK,"○","×") ) -> ×× | S67: =IFERROR(VLOOKUP(B67,$U:$V,2,FALSE),"") -> 肉食生物の巣 | U67: ローパー | V67: 地中生物の巣 | W67: 出現敵:山岳:バシリスク:: | X67: 魔獣_ユニット集2.webp | Y67: 7 | AD67: 1
C68: =LET( _xlpm.dOK,COUNTIF('クラス'!A:A,E68)>0, _xlpm.eOK,COUNTIF('クラス'!A:A,F68)>0, IF(_xlpm.dOK,"○","×") & IF(_xlpm.eOK,"○","×") ) -> ×× | S68: =IFERROR(VLOOKUP(B68,$U:$V,2,FALSE),"") | U68: ワイバーン | V68: 飛竜の巣
C69: =LET( _xlpm.dOK,COUNTIF('クラス'!A:A,E69)>0, _xlpm.eOK,COUNTIF('クラス'!A:A,F69)>0, IF(_xlpm.dOK,"○","×") & IF(_xlpm.eOK,"○","×") ) -> ×× | S69: =IFERROR(VLOOKUP(B69,$U:$V,2,FALSE),"") | U69: マンティコア | V69: 肉食生物の巣
A70: 峡谷 | B70: ローパー | C70: =LET( _xlpm.dOK,COUNTIF('クラス'!A:A,E70)>0, _xlpm.eOK,COUNTIF('クラス'!A:A,F70)>0, IF(_xlpm.dOK,"○","×") & IF(_xlpm.eOK,"○","×") ) -> ×× | S70: =IFERROR(VLOOKUP(B70,$U:$V,2,FALSE),"") -> 地中生物の巣 | U70: ストーンジャイアント | V70: 地中生物の巣 | W70: 出現敵:峡谷:ローパー:: | AD70: 1
A71: 峡谷 | B71: ワイバーン | C71: =LET( _xlpm.dOK,COUNTIF('クラス'!A:A,E71)>0, _xlpm.eOK,COUNTIF('クラス'!A:A,F71)>0, IF(_xlpm.dOK,"○","×") & IF(_xlpm.eOK,"○","×") ) -> ×× | S71: =IFERROR(VLOOKUP(B71,$U:$V,2,FALSE),"") -> 飛竜の巣 | U71: ハーピー | V71: 鳥系生物の巣 | W71: 出現敵:峡谷:ワイバーン:: | AD71: 1
A72: 峡谷 | B72: マンティコア | C72: =LET( _xlpm.dOK,COUNTIF('クラス'!A:A,E72)>0, _xlpm.eOK,COUNTIF('クラス'!A:A,F72)>0, IF(_xlpm.dOK,"○","×") & IF(_xlpm.eOK,"○","×") ) -> ×× | S72: =IFERROR(VLOOKUP(B72,$U:$V,2,FALSE),"") -> 肉食生物の巣 | W72: 出現敵:峡谷:マンティコア:: | X72: 魔獣_ユニット集2.webp | Y72: 1 | AD72: 1
A73: 峡谷 | B73: ストーンジャイアント | C73: =LET( _xlpm.dOK,COUNTIF('クラス'!A:A,E73)>0, _xlpm.eOK,COUNTIF('クラス'!A:A,F73)>0, IF(_xlpm.dOK,"○","×") & IF(_xlpm.eOK,"○","×") ) -> ×× | S73: =IFERROR(VLOOKUP(B73,$U:$V,2,FALSE),"") -> 地中生物の巣 | U73: ビホルダー | V73: 闇の輪 | W73: 出現敵:峡谷:ストーンジャイアント:: | AD73: 1
A74: 峡谷 | B74: ハーピー | C74: =LET( _xlpm.dOK,COUNTIF('クラス'!A:A,E74)>0, _xlpm.eOK,COUNTIF('クラス'!A:A,F74)>0, IF(_xlpm.dOK,"○","×") & IF(_xlpm.eOK,"○","×") ) -> ×× | S74: =IFERROR(VLOOKUP(B74,$U:$V,2,FALSE),"") -> 鳥系生物の巣 | U74: マインドフレイヤー | V74: 闇の輪 | W74: 出現敵:峡谷:ハーピー:: | AD74: 1
C75: =LET( _xlpm.dOK,COUNTIF('クラス'!A:A,E75)>0, _xlpm.eOK,COUNTIF('クラス'!A:A,F75)>0, IF(_xlpm.dOK,"○","×") & IF(_xlpm.eOK,"○","×") ) -> ×× | S75: =IFERROR(VLOOKUP(B75,$U:$V,2,FALSE),"") | U75: アンケグ | V75: 虫系の巣
A76: 洞窟 | B76: ビホルダー | C76: =LET( _xlpm.dOK,COUNTIF('クラス'!A:A,E76)>0, _xlpm.eOK,COUNTIF('クラス'!A:A,F76)>0, IF(_xlpm.dOK,"○","×") & IF(_xlpm.eOK,"○","×") ) -> ×× | S76: =IFERROR(VLOOKUP(B76,$U:$V,2,FALSE),"") -> 闇の輪 | U76: ローパー | V76: 地中生物の巣 | W76: 出現敵:洞窟:ビホルダー:: | AA76: 単独 | AB76: 1 | AC76: 1 | AD76: 1
A77: 洞窟 | B77: マインドフレイヤー | C77: =LET( _xlpm.dOK,COUNTIF('クラス'!A:A,E77)>0, _xlpm.eOK,COUNTIF('クラス'!A:A,F77)>0, IF(_xlpm.dOK,"○","×") & IF(_xlpm.eOK,"○","×") ) -> ×× | S77: =IFERROR(VLOOKUP(B77,$U:$V,2,FALSE),"") -> 闇の輪 | U77: バシリスク | V77: 肉食生物の巣 | W77: 出現敵:洞窟:マインドフレイヤー:: | AA77: 小集団 | AB77: 2 | AC77: 3 | AD77: 1
A78: 洞窟 | B78: アンケグ | C78: =LET( _xlpm.dOK,COUNTIF('クラス'!A:A,E78)>0, _xlpm.eOK,COUNTIF('クラス'!A:A,F78)>0, IF(_xlpm.dOK,"○","×") & IF(_xlpm.eOK,"○","×") ) -> ×× | G78: 5 | H78: 10 | S78: =IFERROR(VLOOKUP(B78,$U:$V,2,FALSE),"") -> 虫系の巣 | U78: パープルワーム | V78: 地中生物の巣 | W78: 出現敵:洞窟:アンケグ:: | X78: アンケグ・スコーピオン_ユニット集.webp | Y78: 1 | AA78: 単独 | AB78: 1 | AC78: 1 | AD78: 1
A79: 洞窟 | B79: ローパー | C79: =LET( _xlpm.dOK,COUNTIF('クラス'!A:A,E79)>0, _xlpm.eOK,COUNTIF('クラス'!A:A,F79)>0, IF(_xlpm.dOK,"○","×") & IF(_xlpm.eOK,"○","×") ) -> ×× | S79: =IFERROR(VLOOKUP(B79,$U:$V,2,FALSE),"") -> 地中生物の巣 | W79: 出現敵:洞窟:ローパー:: | AA79: 単独 | AB79: 1 | AC79: 1 | AD79: 1
A80: 洞窟 | B80: バシリスク | C80: =LET( _xlpm.dOK,COUNTIF('クラス'!A:A,E80)>0, _xlpm.eOK,COUNTIF('クラス'!A:A,F80)>0, IF(_xlpm.dOK,"○","×") & IF(_xlpm.eOK,"○","×") ) -> ×× | R80: バシリスク | S80: =IFERROR(VLOOKUP(B80,$U:$V,2,FALSE),"") -> 肉食生物の巣 | U80: ウォーターエレメンタル | V80: 水の輪 | W80: 出現敵:洞窟:バシリスク:: | X80: 魔獣_ユニット集2.webp | Y80: 7 | AA80: 単独 | AB80: 1 | AC80: 1 | AD80: 1
A81: 洞窟 | B81: パープルワーム | C81: =LET( _xlpm.dOK,COUNTIF('クラス'!A:A,E81)>0, _xlpm.eOK,COUNTIF('クラス'!A:A,F81)>0, IF(_xlpm.dOK,"○","×") & IF(_xlpm.eOK,"○","×") ) -> ×× | R81: パープルワーム | S81: =IFERROR(VLOOKUP(B81,$U:$V,2,FALSE),"") -> 地中生物の巣 | U81: ポイズンスネーク | V81: 毒生成物の巣 | W81: 出現敵:洞窟:パープルワーム:: | X81: ワーム_ユニット集.webp | Y81: 3 | AA81: 単独 | AB81: 1 | AC81: 1 | AD81: 1
C82: =LET( _xlpm.dOK,COUNTIF('クラス'!A:A,E82)>0, _xlpm.eOK,COUNTIF('クラス'!A:A,F82)>0, IF(_xlpm.dOK,"○","×") & IF(_xlpm.eOK,"○","×") ) -> ×× | S82: =IFERROR(VLOOKUP(B82,$U:$V,2,FALSE),"")
C83: =LET( _xlpm.dOK,COUNTIF('クラス'!A:A,E83)>0, _xlpm.eOK,COUNTIF('クラス'!A:A,F83)>0, IF(_xlpm.dOK,"○","×") & IF(_xlpm.eOK,"○","×") ) -> ×× | S83: =IFERROR(VLOOKUP(B83,$U:$V,2,FALSE),"") | U83: ウォーターエレメンタル | V83: 水の輪
A84: 河川 | B84: ウォーターエレメンタル | C84: =LET( _xlpm.dOK,COUNTIF('クラス'!A:A,E84)>0, _xlpm.eOK,COUNTIF('クラス'!A:A,F84)>0, IF(_xlpm.dOK,"○","×") & IF(_xlpm.eOK,"○","×") ) -> ○× | E84: ウォーターエレメンタル | G84: 5 | H84: 15 | R84: 水の精霊 | S84: =IFERROR(VLOOKUP(B84,$U:$V,2,FALSE),"") -> 水の輪 | U84: シーサーペント | V84: 肉食生物の巣 | W84: 出現敵:河川:ウォーターエレメンタル:5:10 | X84: エレメンタル_ユニット集3.webp | Y84: 9 | Z84: TRUE | AD84: 1
A85: 河川 | B85: ポイズンスネーク | C85: =LET( _xlpm.dOK,COUNTIF('クラス'!A:A,E85)>0, _xlpm.eOK,COUNTIF('クラス'!A:A,F85)>0, IF(_xlpm.dOK,"○","×") & IF(_xlpm.eOK,"○","×") ) -> ○○ | D85: TRUE | E85: スネーク | F85: ポイズンアニマル | G85: 8 | H85: 13 | R85: スネーク | S85: =IFERROR(VLOOKUP(B85,$U:$V,2,FALSE),"") -> 毒生成物の巣 | W85: 出現敵:河川:ポイズンスネーク:7:10 | X85: ホーク・スネーク_ユニット集.webp | Y85: 8 | AD85: 1 | AE85: 0 | AF85: 45 | AG85: 雨/雷雨
C86: =LET( _xlpm.dOK,COUNTIF('クラス'!A:A,E86)>0, _xlpm.eOK,COUNTIF('クラス'!A:A,F86)>0, IF(_xlpm.dOK,"○","×") & IF(_xlpm.eOK,"○","×") ) -> ×× | S86: =IFERROR(VLOOKUP(B86,$U:$V,2,FALSE),"") | U86: シーサーペント | V86: 肉食生物の巣
A87: 湖 | B87: ウォーターエレメンタル | C87: =LET( _xlpm.dOK,COUNTIF('クラス'!A:A,E87)>0, _xlpm.eOK,COUNTIF('クラス'!A:A,F87)>0, IF(_xlpm.dOK,"○","×") & IF(_xlpm.eOK,"○","×") ) -> ○× | E87: ウォーターエレメンタル | G87: 15 | H87: 30 | R87: 水の精霊 | S87: =IFERROR(VLOOKUP(B87,$U:$V,2,FALSE),"") -> 水の輪 | U87: ウォーターエレメンタル | V87: 水の輪 | W87: 出現敵:湖:ウォーターエレメンタル:15:30 | X87: エレメンタル_ユニット集3.webp | Y87: 9 | Z87: TRUE | AD87: 1
A88: 湖 | B88: シーサーペント | C88: =LET( _xlpm.dOK,COUNTIF('クラス'!A:A,E88)>0, _xlpm.eOK,COUNTIF('クラス'!A:A,F88)>0, IF(_xlpm.dOK,"○","×") & IF(_xlpm.eOK,"○","×") ) -> ○○ | D88: TRUE | E88: スネーク | F88: シーアニマル | G88: 8 | H88: 13 | S88: =IFERROR(VLOOKUP(B88,$U:$V,2,FALSE),"") -> 肉食生物の巣 | W88: 出現敵:湖:シーサーペント:15:20 | AD88: 1 | AE88: 0 | AF88: 45 | AG88: 雨/雷雨
C89: =LET( _xlpm.dOK,COUNTIF('クラス'!A:A,E89)>0, _xlpm.eOK,COUNTIF('クラス'!A:A,F89)>0, IF(_xlpm.dOK,"○","×") & IF(_xlpm.eOK,"○","×") ) -> ×× | S89: =IFERROR(VLOOKUP(B89,$U:$V,2,FALSE),"") | U89: レッドドラゴン | V89: 飛竜の巣
A90: 海 | B90: シーサーペント | C90: =LET( _xlpm.dOK,COUNTIF('クラス'!A:A,E90)>0, _xlpm.eOK,COUNTIF('クラス'!A:A,F90)>0, IF(_xlpm.dOK,"○","×") & IF(_xlpm.eOK,"○","×") ) -> ○○ | E90: スネーク | F90: シーアニマル | G90: 8 | H90: 13 | S90: =IFERROR(VLOOKUP(B90,$U:$V,2,FALSE),"") -> 肉食生物の巣 | U90: ファイアエレメンタル | V90: 炎の輪 | W90: 出現敵:海:シーサーペント:5:20 | AD90: 1 | AE90: 0 | AF90: 45 | AG90: 雨/雷雨
A91: 海 | B91: ウォーターエレメンタル | C91: =LET( _xlpm.dOK,COUNTIF('クラス'!A:A,E91)>0, _xlpm.eOK,COUNTIF('クラス'!A:A,F91)>0, IF(_xlpm.dOK,"○","×") & IF(_xlpm.eOK,"○","×") ) -> ○× | E91: ウォーターエレメンタル | G91: 15 | H91: 30 | R91: 水の精霊 | S91: =IFERROR(VLOOKUP(B91,$U:$V,2,FALSE),"") -> 水の輪 | U91: サラマンダー | V91: 炎の輪 | W91: 出現敵:海:ウォーターエレメンタル:15:30 | X91: エレメンタル_ユニット集3.webp | Y91: 9 | Z91: TRUE | AD91: 1
C92: =LET( _xlpm.dOK,COUNTIF('クラス'!A:A,E92)>0, _xlpm.eOK,COUNTIF('クラス'!A:A,F92)>0, IF(_xlpm.dOK,"○","×") & IF(_xlpm.eOK,"○","×") ) -> ×× | S92: =IFERROR(VLOOKUP(B92,$U:$V,2,FALSE),"")
C93: =LET( _xlpm.dOK,COUNTIF('クラス'!A:A,E93)>0, _xlpm.eOK,COUNTIF('クラス'!A:A,F93)>0, IF(_xlpm.dOK,"○","×") & IF(_xlpm.eOK,"○","×") ) -> ×× | S93: =IFERROR(VLOOKUP(B93,$U:$V,2,FALSE),"") | U93: ファイアエレメンタル | V93: 炎の輪
A94: 火山 | B94: レッドドラゴン | C94: =LET( _xlpm.dOK,COUNTIF('クラス'!A:A,E94)>0, _xlpm.eOK,COUNTIF('クラス'!A:A,F94)>0, IF(_xlpm.dOK,"○","×") & IF(_xlpm.eOK,"○","×") ) -> ×× | S94: =IFERROR(VLOOKUP(B94,$U:$V,2,FALSE),"") -> 飛竜の巣 | U94: マグマエレメンタル | V94: 炎の輪 | W94: 出現敵:火山:レッドドラゴン:: | AD94: 1
A95: 火山 | B95: ファイアエレメンタル | C95: =LET( _xlpm.dOK,COUNTIF('クラス'!A:A,E95)>0, _xlpm.eOK,COUNTIF('クラス'!A:A,F95)>0, IF(_xlpm.dOK,"○","×") & IF(_xlpm.eOK,"○","×") ) -> ○× | E95: フレイムエレメンタル | G95: 15 | H95: 30 | R95: 炎の精霊 | S95: =IFERROR(VLOOKUP(B95,$U:$V,2,FALSE),"") -> 炎の輪 | U95: ラヴァスライム | V95: 毒生成物の巣 | W95: 出現敵:火山:ファイアエレメンタル:15:30 | X95: エレメンタル_ユニット集1.webp | Y95: 1 | Z95: TRUE | AD95: 1 | AE95: 15 | AF95: 60 | AG95: 晴れ
A96: 火山 | B96: サラマンダー | C96: =LET( _xlpm.dOK,COUNTIF('クラス'!A:A,E96)>0, _xlpm.eOK,COUNTIF('クラス'!A:A,F96)>0, IF(_xlpm.dOK,"○","×") & IF(_xlpm.eOK,"○","×") ) -> ×× | S96: =IFERROR(VLOOKUP(B96,$U:$V,2,FALSE),"") -> 炎の輪 | W96: 出現敵:火山:サラマンダー:: | AD96: 1
C97: =LET( _xlpm.dOK,COUNTIF('クラス'!A:A,E97)>0, _xlpm.eOK,COUNTIF('クラス'!A:A,F97)>0, IF(_xlpm.dOK,"○","×") & IF(_xlpm.eOK,"○","×") ) -> ×× | S97: =IFERROR(VLOOKUP(B97,$U:$V,2,FALSE),"") | U97: フロストジャイアント | V97: 水の輪
C98: =LET( _xlpm.dOK,COUNTIF('クラス'!A:A,E98)>0, _xlpm.eOK,COUNTIF('クラス'!A:A,F98)>0, IF(_xlpm.dOK,"○","×") & IF(_xlpm.eOK,"○","×") ) -> ×× | S98: =IFERROR(VLOOKUP(B98,$U:$V,2,FALSE),"") | U98: イエティ | V98: 肉食生物の巣
A99: 溶岩 | B99: ファイアエレメンタル | C99: =LET( _xlpm.dOK,COUNTIF('クラス'!A:A,E99)>0, _xlpm.eOK,COUNTIF('クラス'!A:A,F99)>0, IF(_xlpm.dOK,"○","×") & IF(_xlpm.eOK,"○","×") ) -> ○× | E99: フレイムエレメンタル | G99: 5 | H99: 15 | R99: 炎の精霊 | S99: =IFERROR(VLOOKUP(B99,$U:$V,2,FALSE),"") -> 炎の輪 | U99: ウィンターウルフ | V99: 肉食生物の巣 | W99: 出現敵:溶岩:ファイアエレメンタル:10:15 | X99: エレメンタル_ユニット集1.webp | Y99: 1 | Z99: TRUE | AD99: 1 | AE99: 15 | AF99: 60 | AG99: 晴れ
A100: 溶岩 | B100: マグマエレメンタル | C100: =LET( _xlpm.dOK,COUNTIF('クラス'!A:A,E100)>0, _xlpm.eOK,COUNTIF('クラス'!A:A,F100)>0, IF(_xlpm.dOK,"○","×") & IF(_xlpm.eOK,"○","×") ) -> ×× | S100: =IFERROR(VLOOKUP(B100,$U:$V,2,FALSE),"") -> 炎の輪 | U100: フロストエレメンタル | V100: 水の輪 | W100: 出現敵:溶岩:マグマエレメンタル:: | AD100: 1
...

Sheet 召喚モンスターリスト
A1: 名称 | B1: 分類 | C1: クラス構成 | D1: 総Lv | E1: 備考 | F1: 武器 | G1: 副武器 | H1: 胴 | I1: 頭 | J1: 足 | K1: 装飾1 | L1: 装飾2 | M1: 必要資材 | N1: 維持素材
A2: ゾンビ | B2: アンデッド | C2: ゾンビ_3 | D2: 3
A3: スケルトン | B3: アンデッド | C3: スケルトン_6 | D3: 6 | E3: 召喚時に武器候補からランダム1個 | F3: 剣 / 槍 / 棍棒（ランダム・common）
A4: ゴースト | B4: アンデッド | C4: ゴースト_10 | D4: 10
A5: グール | B5: アンデッド | C5: ゾンビ_10 グール_2 | D5: 12
A6: ワイト | B6: アンデッド | C6: ゾンビ_10 ワイト_4 | D6: 14 | F6: 長剣_C | G6: 弓_C | H6: 鎧_C | J6: 重靴_C
A7: レヴナント | B7: アンデッド | C7: ゾンビ_10 レヴナント_6 | D7: 16
A8: レイス | B8: アンデッド | C8: ゴースト_10 レイス_8 | D8: 18
A9: デュラハン | B9: アンデッド | C9: ゾンビ_10 デュラハン_10 | D9: 20 | F9: 長剣_U | G9: 盾_C | H9: 鎧_U | J9: 重靴_C
A10: バンシー | B10: アンデッド | C10: ゴースト_10 バンシー_10 | D10: 20
A11: ガスト | B11: アンデッド | C11: ゾンビ_10 グール_10 ガスト_3 | D11: 23
A12: リッチ | B12: アンデッド | C12: スケルトン_10 リッチ_10 ウィザード_3 | D12: 23 | E12: 魔法系強個体 | F12: 杖_U | H12: 法衣_U
A13: ドゥームゾンビ | B13: アンデッド | C13: ゾンビ_10 レヴナント_10 ドゥームゾンビ_5 | D13: 25
A14: ギャザード・グラッジ | B14: アンデッド | C14: ゴースト_10 レイス_10 ギャザード・グラッジ_7 | D14: 27
A15: 蒼炎のデュラハン | B15: アンデッド | C15: ゾンビ_10 デュラハン_10 蒼炎のデュラハン_10 | D15: 30 | F15: 長剣_R | G15: 盾_U | H15: 鎧_U | J15: 重靴_U
A16: レムレ | B16: デヴィル | C16: デヴィル_3 | D16: 3 | E16: D&D / Pathfinder系モチーフ。最下級デヴィル・壁役
A17: インプ | B17: デヴィル | C17: デヴィル_5 シーフ_1 | D17: 6 | E17: D&D系モチーフ。小型飛行・斥候型 | F17: 短剣_C | H17: 服_C | J17: 靴_C
A18: スパインド・デヴィル | B18: デヴィル | C18: デヴィル_5 ホーク_4 | D18: 9 | E18: D&D系モチーフ。飛行・棘射撃型 | F18: 槍_C | H18: 服_C | J18: 靴_C
A19: ヘルハウンド | B19: デヴィル | C19: ウルフ_7 デヴィル_5 | D19: 12 | E19: D&D / Pathfinder系モチーフ。犬型フィーンド
A20: ナイトメア | B20: デヴィル | C20: ホース_8 デヴィル_7 | D20: 15 | E20: D&D / Pathfinder系モチーフ。魔界の馬型フィーンド
A21: ビアデッド・デヴィル | B21: デヴィル | C21: デヴィル_10 ファイター_8 | D21: 18 | E21: D&D系モチーフ。近接・長柄武器型 | F21: 槍_U | H21: 鎧_U | I21: 兜_U | J21: 重靴_U
A22: バーブド・デヴィル | B22: デヴィル | C22: デヴィル_10 カマキリ_6 スカーミッシャー_5 | D22: 21 | E22: D&D系モチーフ。棘・拘束近接型 | F22: 槍_U | H22: 鎧_U | J22: 重靴_U
A23: ボーン・デヴィル | B23: デヴィル | C23: デヴィル_10 スケルトン_10 スピアマスター_4 | D23: 24 | E23: D&D系モチーフ。骨格・毒尾・長柄型 | F23: 槍_U | H23: 鎧_U | I23: 兜_U | J23: 重靴_U
A24: エリニュス | B24: デヴィル | C24: デヴィル_10 アーチャー_10 ナイト_7 | D24: 27 | E24: D&D / Pathfinder系モチーフ。武装・弓主体の上位デヴィル | F24: 弓_R | G24: 長剣_U | H24: 鎧_U | I24: 兜_U | J24: 重靴_U
A25: アイス・デヴィル | B25: デヴィル | C25: デヴィル_10 フロストエレメンタル_10 スピアマスター_10 | D25: 30 | E25: D&D系モチーフ。氷・槍主体 | F25: 槍_R | H25: 鎧_U | I25: 兜_U | J25: 重靴_U
A26: コントラクト・デヴィル | B26: デヴィル | C26: デヴィル_10 バード_10 ウィザード_10 シーフ_3 | D26: 33 | E26: Pathfinder系モチーフ。契約・魅了・精神操作型 | F26: 短剣_R | H26: 服_U | I26: 帽子_U | J26: 靴_U
A27: ヘレシー・デヴィル | B27: デヴィル | C27: デヴィル_10 ウィザード_10 ワードキャスター_10 クレリック_5 | D27: 35 | E27: Pathfinder系モチーフ。信仰妨害・魔法型 | F27: 杖_R | H27: 法衣_U | I27: 冠_U | J27: 靴_U
A28: カッシシアン | B28: セレスチャル | C28: エンジェル_3 ウィザード_3 | D28: 6 | E28: Pathfinder系モチーフ。小型の案内・索敵・簡易魔法補助型 | F28: 杖_C | H28: 服_C | I28: 帽子_C | J28: 靴_C
A29: クルビ | B29: セレスチャル | C29: エンジェル_3 アーチャー_6 | D29: 9 | E29: Pathfinder系モチーフ。弓・聖域防衛型 | F29: 弓_C | H29: 服_C | J29: 靴_C
A30: エンジェルズ | B30: セレスチャル | C30: エンジェル_5 エンジェルズ_5 | D30: 10 | E30: 本作天使階級。バード系の歌・祝福・支援型 | F30: 短剣_C | G30: 弓_C | H30: 服_C | I30: 帽子_C | J30: 靴_C
A31: イオファナイト | B31: セレスチャル | C31: エンジェル_4 ガーディアン_4 フレイムブレード_4 | D31: 12 | E31: Pathfinder系モチーフ。炎・光・防御型 | F31: 長剣_C | G31: 盾_C | H31: 鎧_C | I31: 兜_C | J31: 重靴_C
A32: アークエンジェルズ | B32: セレスチャル | C32: エンジェル_5 アークエンジェルズ_8 パラディン_2 | D32: 15 | E32: 本作天使階級。ナイト系の武装前衛型 | F32: 長剣_C | G32: 盾_C | H32: 鎧_C | I32: 兜_C | J32: 重靴_C
A33: エレリム | B33: セレスチャル | C33: エンジェル_8 スピアマスター_10 | D33: 18 | E33: Pathfinder系モチーフ。槍主体の戦闘型 | F33: 槍_U | H33: 鎧_U | I33: 兜_U | J33: 重靴_U
A34: プリンシパリティ | B34: セレスチャル | C34: プリンシパリティ_10 エンジェル_8 アークエンジェル_3 | D34: 21 | E34: 本作天使階級。コマンダー系の指揮・味方強化型 | F34: 長剣_U | G34: 盾_U | H34: 鎧_U | I34: 兜_U | J34: 重靴_U
A35: バリッセ | B35: セレスチャル | C35: エンジェル_10 ハイクレリック_8 ワードキャスター_6 | D35: 24 | E35: Pathfinder系モチーフ。解除・弱体・信仰補助型 | F35: 杖_U | H35: 法衣_U | I35: 冠_U | J35: 靴_U
A36: モナディック・デーヴァ | B36: セレスチャル | C36: エンジェル_10 パラディン_10 クレリック_7 | D36: 27 | E36: Pathfinder系モチーフ。魂・守護系上位天使 | F36: 棍棒_R | G36: 盾_U | H36: 鎧_U | I36: 兜_U | J36: 重靴_U
A37: パワード | B37: セレスチャル | C37: パワード_10 パラディン_10 アークエンジェル_8 | D37: 28 | E37: 本作天使階級。パラディン系の聖戦士・重前衛型 | F37: 長剣_U | G37: 盾_U | H37: 鎧_U | I37: 兜_U | J37: 重靴_U
A38: モヴァニック・デーヴァ | B38: セレスチャル | C38: エンジェル_10 ガーディアン_10 ソードマスター_10 | D38: 30 | E38: Pathfinder系モチーフ。天界軍の前衛・守護型 | F38: 長剣_R | G38: 盾_U | H38: 鎧_U | I38: 兜_U | J38: 重靴_U
A39: デュナミス | B39: セレスチャル | C39: デュナミス_10 モンク_10 エンジェル_10 | D39: 35 | E39: 本作天使階級。モンク系の高機動・近接格闘型 | H39: 服_R | J39: 靴_U
A43: フレイムエレメンタル | B43: エレメンタル | C43: フレイムエレメンタル_10 | D43: 10 | E43: 火属性・基礎種
A44: アークフレイムエレメンタル | B44: エレメンタル | C44: フレイムエレメンタル_10 アークフレイムエレメンタル_10 | D44: 20 | E44: 火属性・上位種
A45: グレーターフレイムエレメンタル | B45: エレメンタル | C45: フレイムエレメンタル_10 アークフレイムエレメンタル_10 グレーターフレイムエレメンタル_10 | D45: 30 | E45: 火属性・上位種
A46: フロストエレメンタル | B46: エレメンタル | C46: フロストエレメンタル_10 | D46: 10 | E46: 氷属性・基礎種
A47: アークフロストエレメンタル | B47: エレメンタル | C47: フロストエレメンタル_10 アークフロストエレメンタル_10 | D47: 20 | E47: 氷属性・上位種
A48: グレーターフロストエレメンタル | B48: エレメンタル | C48: フロストエレメンタル_10 アークフロストエレメンタル_10 グレーターフロストエレメンタル_10 | D48: 30 | E48: 氷属性・上位種
A49: ウォーターエレメンタル | B49: エレメンタル | C49: ウォーターエレメンタル_10 | D49: 10 | E49: 水属性・基礎種
A50: アークウォーターエレメンタル | B50: エレメンタル | C50: ウォーターエレメンタル_10 アークウォーターエレメンタル_10 | D50: 20 | E50: 水属性・上位種
A51: グレーターウォーターエレメンタル | B51: エレメンタル | C51: ウォーターエレメンタル_10 アークウォーターエレメンタル_10 グレーターウォーターエレメンタル_10 | D51: 30 | E51: 水属性・上位種
A52: エアエレメンタル | B52: エレメンタル | C52: エアエレメンタル_10 | D52: 10 | E52: 風属性・基礎種
A53: アークエアエレメンタル | B53: エレメンタル | C53: エアエレメンタル_10 アークエアエレメンタル_10 | D53: 20 | E53: 風属性・上位種
A54: グレーターエアエレメンタル | B54: エレメンタル | C54: エアエレメンタル_10 アークエアエレメンタル_10 グレーターエアエレメンタル_10 | D54: 30 | E54: 風属性・上位種
... A57: グレーターアースエレメンタル | B57: エレメンタル | C57: アースエレメンタル_10 アークアースエレメンタル_10 グレーターアースエレメンタル_10 | D57: 30 | E57: 土属性・上位種
A58: フレイムソルジャー | B58: エレメンタル | C58: フレイムエレメンタル_10 フェンサー_5 | D58: 15 | E58: 火属性エレメンタルの中間兵士。Lv10基礎種とLv20アーク種の間を埋める近接型 | F58: 長剣_C | H58: 服_C | J58: 靴_C
A59: フロストソルジャー | B59: エレメンタル | C59: フロストエレメンタル_10 ナイト_5 | D59: 15 | E59: 氷属性エレメンタルの中間兵士。Lv10基礎種とLv20アーク種の間を埋める防御型 | F59: 長剣_C | G59: 盾_C | H59: 鎧_C | J59: 重靴_C
A60: ウィンドソルジャー | B60: エレメンタル | C60: エアエレメンタル_10 フェンサー_5 | D60: 15 | E60: 風属性エレメンタルの中間兵士。Lv10基礎種とLv20アーク種の間を埋める高速近接型 | F60: 長剣_C | H60: 服_C | J60: 靴_C
A61: アースソルジャー | B61: エレメンタル | C61: アースエレメンタル_10 ナイト_5 | D61: 15 | E61: 土属性エレメンタルの中間兵士。Lv10基礎種とLv20アーク種の間を埋める重前衛型 | F61: 長剣_C | G61: 盾_C | H61: 鎧_C | J61: 重靴_C
A62: ウォーターソルジャー | B62: エレメンタル | C62: ウォーターエレメンタル_10 ドルイド_5 | D62: 15 | E62: 水属性エレメンタルの中間兵士。Lv10基礎種とLv20アーク種の間を埋める術兵・支援型 | F62: 杖_C | H62: 法衣_C | J62: 靴_C
A63: アークフレイムソルジャー | B63: エレメンタル | C63: フレイムエレメンタル_10 アークフレイムエレメンタル_10 フレイムブレード_5 | D63: 25 | E63: 火属性エレメンタルの上位兵士。Lv20アーク種とLv30グレーター種の間を埋める属性剣士型 | F63: 長剣_U | H63: 服_U | J63: 靴_U
A64: アークフロストソルジャー | B64: エレメンタル | C64: フロストエレメンタル_10 アークフロストエレメンタル_10 フロストブレード_5 | D64: 25 | E64: 氷属性エレメンタルの上位兵士。Lv20アーク種とLv30グレーター種の間を埋める属性前衛型 | F64: 長剣_U | G64: 盾_U | H64: 鎧_U | J64: 重靴_U
A65: アークウィンドソルジャー | B65: エレメンタル | C65: エアエレメンタル_10 アークエアエレメンタル_10 ウィンドブレード_5 | D65: 25 | E65: 風属性エレメンタルの上位兵士。Lv20アーク種とLv30グレーター種の間を埋める属性剣士型 | F65: 長剣_U | H65: 服_U | J65: 靴_U
A66: アークアースソルジャー | B66: エレメンタル | C66: アースエレメンタル_10 アークアースエレメンタル_10 アースブレード_5 | D66: 25 | E66: 土属性エレメンタルの上位兵士。Lv20アーク種とLv30グレーター種の間を埋める重装属性前衛型 | F66: 長剣_U | G66: 盾_U | H66: 鎧_U | J66: 重靴_U
A67: アークウォーターソルジャー | B67: エレメンタル | C67: ウォーターエレメンタル_10 アークウォーターエレメンタル_10 アクアドルイド_5 | D67: 25 | E67: 水属性エレメンタルの上位兵士。Lv20アーク種とLv30グレーター種の間を埋める上位術兵・支援型 | F67: 杖_U | H67: 法衣_U | J67: 靴_U
A69: ペガサス | B69: セレスチャル | C69: ホース_6 幻獣_3 | D69: 9 | E69: D&D / Pathfinder系モチーフ。飛行馬型セレスチャル
A70: クアトル | B70: セレスチャル | C70: スネーク_8 神獣_7 | D70: 15 | E70: D&D系モチーフ。翼ある蛇型セレスチャル
A71: ユニコーン | B71: セレスチャル | C71: ホース_10 幻獣_6 クレリック_5 | D71: 21 | E71: D&D / Pathfinder系モチーフ。聖獣・回復支援型

Sheet モンスター合成
A1: 素材 | B1: 合成結果 | C1: ボーナスクラス | D1: 獲得スキル | E1: スキル備考 | F1: 状態 | G1: 備考 | J1: 元種 | K1: 派生クラス | L1: 派生結果 | M1: 状態 | N1: 備考 | P1: 予定クラス | Q1: 分類 | R1: 親系統 | S1: 役割 | T1: スキル方針 | U1: 状態 | V1: 備考
A2: ホース_1,デヴィル_1 | B2: バイコーン | C2: 幻獣,エヴォリューション・ホーン | D2: 呪角 | E2: 角攻撃に呪い系の追加効果を与える攻撃。角そのものの性能はエヴォリューション・ホーン側を利用する。 | F2: 確定 | G2: ユーザー指定。ボーナスクラスはクラス原本未追加。獲得スキル「呪角」は仮案 | J2: ウルフ | K2: ムーンアニマル | L2: 月ウルフ | M2: 確定 | N2: Notion画像生成・参照管理｜整理版 | P2: 幻獣 | Q2: 上位種族クラス | S2: 通常動物を超えた伝説・神話級の獣をまとめる親系統 | T2: 仮スキル: 幻獣の身体(P・新規) / 幻獣の咆哮(A・新規) / 魔法の守り(A・既存) / 反応(既存) / 超常感覚(P・新規) / 幻獣覚醒(AまたはP・新規)。既存スキルを優先再利用。 | U2: 分類仕様確定・スキル仮案 | V2: フェンリル、ケルベロス、グリフォン、マンティコア、キメラ、スフィンクス、バシリスク、ハイドラ、フェニックス、ユニコーン等
A3: ホース_1,エンジェル_1 | B3: ユニコーン | C3: 幻獣 | D3: 浄化の角 | E3: 角による攻撃または接触で、不浄や状態異常を解除する支援寄りスキル。攻撃型か回復型かは後で調整。 | F3: 候補 | G3: 既存候補 | J3: ウルフ | K3: フロストアニマル | L3: 氷ウルフ | M3: 確定 | N3: Notion画像生成・参照管理｜整理版 | P3: 神獣 | Q3: 上位種族派生 | R3: 幻獣 | S3: 神聖・守護・加護寄りの上位系統 | T3: 仮スキル: 奇跡の祝福(A・既存) / 神威(P・新規) / 浄化(A・新規) / 神聖攻撃(A・新規) / 神獣の加護(P・新規) / 神獣の威光(P・新規)。 | U3: 分類仕様確定・スキル仮案 | V3: 青龍、白虎、朱雀、玄武、麒麟、白沢、応龍等
A4: ウルフ_1,デヴィル_1 | B4: ヘルハウンド | F4: 候補 | G4: 既存候補 | J4: ウルフ | L4: 影ウルフ | M4: 確定 | N4: 派生結果はNotion確定。対応する派生クラス名は未設定 | P4: 凶獣 | Q4: 上位種族派生 | R4: 幻獣 | S4: 災厄・凶性・攻撃寄りの上位系統 | T4: 仮スキル: 悪魔の威圧(P・既存) / 大鬼の咆哮(A・既存) / 恐怖の囁き(A・既存) / 捕食(A・新規) / 狂暴化(AまたはP・新規) / 凶獣の本能(P・新規)。 | U4: 分類仕様確定・スキル仮案 | V4: 饕餮、窮奇、檮杌、混沌、ケルベロス等
A5: スネーク_1,デヴィル_1 | B5: ナイトメアサーペント等 | F5: 未定 | G5: 名称要検討 | J5: ホース | K5: ムーンアニマル | L5: 月ホース | M5: 確定 | N5: ユニコーン/バイコーンは2体合成側で管理 | P5: 妖獣 | Q5: 上位種族派生 | R5: 幻獣 | S5: 妖怪化・怪異化した獣系統 | T5: 仮スキル: 妖気(P・新規) / 幻惑(A・新規) / 変身(A・新規) / 隠形(AまたはP・新規) / 呪い(A・新規) / 妖獣の気配(P・新規)。既存の幻覚効果体系を再利用する。 | U5: 分類仕様確定・スキル仮案 | V5: 九尾狐、鵺、鬼車、相柳等
A6: ホーク_1,デヴィル_1 | B6: 悪魔系飛行獣 | F6: 未定 | G6: 合成先未定 | J6: ホーク | K6: スパークアニマル | L6: 雷ホーク | M6: 確定 | N6: Notion画像生成・参照管理｜整理版 | P6: マルチヘッド | Q6: 身体特性クラス | S6: 頭部を使う攻撃の回数を増加し、1ヒット威力を低下 | T6: 仮能力: 多頭攻撃補正(P) / 頭部強化分割(P) / 必要なら多頭感知(P)。頭部攻撃回数増加＋1ヒット威力減衰。強化攻撃の上昇量は攻撃回数で分割。 | U6: 挙動仕様確定・能力名仮案 | V6: 攻撃回数、威力減衰率、端数処理は未確定。ケルベロス、ハイドラ、鬼車、相柳等
A7: タイガー_1,ホーク_1,サソリ_1 | B7: マンティコア | C7: 幻獣 | D7: 毒棘射出 | E7: 尾の毒棘を遠距離へ射出する攻撃。尾・毒系の既存能力を土台にし、マンティコア固有の遠隔攻撃として扱う候補。 | F7: 候補 | G7: 仮レシピ。出現敵ではタイガー＋ホーク。尾要素としてクラス原本登録済みのサソリを追加 | J7: ホーク | K7: ウィンドアニマル | L7: 風ホーク | M7: 確定 | N7: Notion画像生成・参照管理｜整理版 | P7: マルチアーム | Q7: 身体特性クラス | S7: 腕を使う攻撃の回数を増加し、1ヒット威力を低下 | T7: 仮能力: 多腕攻撃補正(P) / 腕部強化分割(P) / 必要なら多武器制御(P)。腕部攻撃回数増加＋1ヒット威力減衰。強化攻撃の上昇量は攻撃回数で分割。 | U7: 挙動仕様確定・能力名仮案 | V7: 腕部攻撃の判定方法、攻撃回数、威力減衰率、端数処理は未確定
A8: ウルフ_1,ゴースト_1 | B8: ディスプレイサービースト | D8: 転位残像 | E8: 実体位置をずらした残像で狙いを外させる回避・認識阻害能力。幻覚/命中低下系の既存処理を再利用する候補。 | F8: 候補 | G8: 出現敵シートの種族＋サブクラス構成から転記 | J8: ホーク | L8: 光ホーク | M8: 確定 | N8: 派生結果はNotion確定。対応する派生クラス名は未設定
A9: ライオン_1,ホーク_1 | B9: グリフォン | C9: 幻獣 | D9: 急降下強襲 | E9: 飛行状態から高速で接近し、爪または体当たりで強襲する攻撃。翼・爪・突撃系の既存能力を組み合わせる候補。 | F9: 候補 | G9: 仮レシピ。Notionの魔獣・混成獣系。クラス原本にライオン未登録 | J9: スネーク | K9: ポイズンアニマル | L9: 毒スネーク | M9: 確定 | N9: Notion画像生成・参照管理｜整理版
A10: タイガー_1,スネーク_1,ゴート_1 | B10: キメラ | C10: 幻獣 | D10: 三獣連撃 | E10: 獅子・山羊・蛇など複数の身体部位を連続して使う複合攻撃。攻撃回数や各部位補正は後で調整し、単純な倍率増加にはしない。 | F10: 候補 | G10: 仮レシピ。出現敵ではタイガー＋スネーク。第三素材ゴートはクラス原本未登録 | J10: スネーク | L10: 影スネーク | M10: 確定 | N10: 派生結果はNotion確定。対応する派生クラス名は未設定
A11: ベア_1,鳥系_1 | B11: アウルベア | D11: 梟熊の抱擁 | E11: 爪で掴み、熊の腕力で対象を拘束する近接技。拘束系の既存処理を再利用し、継続中の追加攻撃可否は後で決める。 | F11: 候補 | G11: ユーザー確定: 素材はベア1体＋鳥系1体。鳥系は現行ホーク/オウルを許可。合成結果はアウルベア、候補状態は維持。 | J11: スネーク | K11: シーアニマル | L11: 水スネーク | M11: 確定 | N11: Notion画像生成・参照管理｜整理版
A12: ライオン_1,エンジェル_1 | B12: スフィンクス | C12: 幻獣 | D12: 謎掛けの呪縛 | E12: 対象に精神・看破系の判定を要求し、失敗時に幻覚や行動阻害を与える妨害スキル。 | F12: 候補 | G12: 仮レシピ。Notionの魔獣・混成獣系。ライオンはクラス原本未登録 | J12: クロコダイル | K12: シーアニマル | L12: 水クロコダイル | M12: 確定 | N12: Notion画像生成・参照管理｜整理版
A13: リザード_1,スネーク_1 | B13: バシリスク | C13: 幻獣,魔眼 | D13: 石化の魔眼 | E13: 視線攻撃で石化を付与または蓄積する。既存の石化耐性体系に接続する想定。 | F13: 候補 | G13: 仮レシピ。Notionの魔獣・混成獣系。数量は体構成のみで扱い、巨大化目的では増やさない。リザードはクラス原本未登録 | J13: クロコダイル | K13: ストーンアニマル | L13: 地クロコダイル | M13: 確定 | N13: Notion画像生成・参照管理｜整理版
A14: スネーク_3,ドレイク_1 | B14: ハイドラ | C14: 幻獣,マルチヘッド | D14: 首再生 | E14: 候補案: 首の個別損耗は管理しない。マルチヘッドによる複数回攻撃は常時維持し、「首再生」はHP再生能力として扱う案。軍隊相当/軍勢級の特殊モンスター扱いも後で検討する。 | F14: 候補 | G14: 仮レシピ。スネーク3体は巨大化ではなく多頭構成を表す暫定数量。ハイドラを軍隊相当/軍勢級の特殊モンスターとして扱う案は保留候補。首数の個別管理はしない方向で検討。 | J14: クロコダイル | K14: ポイズンアニマル | L14: 毒クロコダイル | M14: 確定 | N14: Notion画像生成・参照管理｜整理版
A15: ドレイク_1,ホーク_1 | B15: ワイバーン | D15: 毒尾急襲 | E15: 飛行接近から尾針を突き刺し、毒効果を与える攻撃。翼・尾針・毒の既存能力を組み合わせる候補。 | F15: 候補 | G15: 仮レシピ。Notionではドラゴンとワイバーンは別素体・作業保留のため正式仕様ではない | J15: タイガー | K15: スパークアニマル | L15: 雷タイガー | M15: 確定 | N15: Notion画像生成・参照管理｜整理版
A16: アンケグ_1,アースエレメンタル_1 | B16: ブレット | D16: 地中強襲 | E16: 地中から接近して足元から奇襲する攻撃。地中移動そのものが未実装なら、先制/命中補正付きの突撃として暫定表現する。 | F16: 候補 | G16: 仮レシピ。出現敵に存在。巨大化目的の複数個体消費は使わず1体ずつで暫定化。アンケグはクラス原本未登録 | J16: タイガー | K16: ストーンアニマル | L16: 地タイガー | M16: 確定 | N16: Notion画像生成・参照管理｜整理版
A17: リザード_1,フレイムエレメンタル_1 | B17: サラマンダー | D17: 炎熱皮膚 | E17: 全身の高熱により近接接触した相手へ炎ダメージまたは炎状態を返すパッシブ。通常の炎攻撃はフレイム系能力へ任せる。 | F17: 候補 | G17: 仮レシピ。出現敵に存在。リザードはクラス原本未登録 | J17: タイガー | K17: ソルアニマル | L17: 太陽タイガー | M17: 確定 | N17: Notion画像生成・参照管理｜整理版
A18: ベア_1,フロストアニマル_1 | B18: イエティ | D18: 凍気の咆哮 | E18: 冷気を伴う咆哮で周囲を妨害する範囲技。咆哮系処理と氷属性を組み合わせ、鈍化などの追加効果は後で調整する。 | F18: 候補 | G18: 仮レシピ。巨大化はクラス側で扱うため、ベア複数消費はしない | J18: ベア | L18: 影ベア | M18: 確定 | N18: 派生結果はNotion確定。対応する派生クラス名は未設定
J19: ボア | K19: ストーンアニマル | L19: 地ボア | M19: 確定 | N19: Notion画像生成・参照管理｜整理版
A20: ゴースト_1,デヴィル_1 | B20: ビホルダー | C20: 魔眼 | D20: 中央眼の反魔法 | E20: 中央眼の正面範囲に反魔法効果を展開する。個別の眼攻撃は魔眼クラス側へ任せる。 | F20: 候補 | G20: Notion旧「魔法生物」に存在。素材構成は仮。魔眼はクラス原本登録済み | J20: ボア | K20: ポイズンアニマル | L20: 毒ボア | M20: 確定 | N20: Notion画像生成・参照管理｜整理版
A21: ホーク_1,フレイムエレメンタル_1 | B21: フェニックス | C21: 幻獣 | D21: 転生 | E21: 戦闘不能時に一定条件で復活する固有能力。復活HP・発動遅延・回数制限は後で決定。 | F21: 候補 | G21: Notion旧「魔法生物」に存在。炎の鳥として仮レシピ化 | J21: ボア | K21: フレイムアニマル | L21: 炎ボア | M21: 確定 | N21: Notion画像生成・参照管理｜整理版
A22: ウルフ_3,デヴィル_1 | B22: ケルベロス | C22: 幻獣,凶獣,マルチヘッド | D22: 冥府の番犬 | E22: 隠密・霊体系の発見や敵の離脱阻止を行う番犬系能力。三頭攻撃自体はマルチヘッド側で処理する。 | F22: 候補 | G22: Notion旧「魔法生物」に存在。ウルフ3体は巨大化ではなく三頭構成を表す暫定数量 | J22: フォックス | K22: フレイムアニマル | L22: 炎フォックス | M22: 確定 | N22: Notion画像生成・参照管理｜整理版。その他派生は未確定
A23: スネーク_1,ストーンゴーレム_1 | B23: ストーンワーム | F23: 候補 | G23: Notion旧「魔法生物」に存在。素材構成は新規仮案 | J23: ベア | K23: ウィンドアニマル | L23: アウルベア | M23: 候補 | N23: 出現敵シート由来。Notion確定6種セット外のため候補
A24: ゴブリン_1,ホーク_1 | B24: 天狗 | F24: 候補 | G24: 妖怪系の新規仮案。ゴブリン・ホークはクラス原本登録済み | J24: ホーク | K24: スパークアニマル | L24: サンダーバード | M24: 候補 | N24: 出現敵シート由来。同じ派生クラスの確定結果「雷ホーク」と競合
A25: ゴブリン_1,ウォーターエレメンタル_1 | B25: 河童 | F25: 候補 | G25: 妖怪系の新規仮案。水棲の人型怪異として暫定 | J25: ベア | K25: アースエレメンタル | L25: ロックベア | M25: 候補 | N25: 出現敵シート由来
A26: クモ_1,ゴースト_1 | B26: 絡新婦 | F26: 候補 | G26: 妖怪系の新規仮案。クモ・ゴーストはクラス原本登録済み | J26: スネーク | K26: ポイズンアニマル | L26: ポイズンスネーク | M26: 候補 | N26: 出現敵シート由来。同じ派生クラスの確定結果「毒スネーク」と競合
A27: ゴースト_1,フレイムエレメンタル_1 | B27: 鬼火 | F27: 候補 | G27: 怪異系の新規仮案。霊体＋炎の構成 | J27: スネーク | K27: シーアニマル | L27: シーサーペント | M27: 候補 | N27: 出現敵シート由来。同じ派生クラスの確定結果「水スネーク」と競合
A28: ゴースト_1,フロストエレメンタル_1 | B28: 雪女 | F28: 候補 | G28: 妖怪系の新規仮案。霊体＋氷の構成 | J28: ライオン | K28: フレイムアニマル | M28: 確定 | N28: Notion通常動物表。派生結果名はNotion未記載のため未設定
A29: モンキー_1,タイガー_1,スネーク_1 | B29: 鵺 | C29: 幻獣,妖獣 | D29: 鵺の鳴声 | E29: 鳴声による音＋精神系の範囲妨害。既存の咆哮・恐怖系処理を再利用する想定。 | F29: 候補 | G29: 妖怪系の新規仮案。複合獣構成。モンキーはクラス原本未登録 | J29: ライオン | K29: ソルアニマル | M29: 確定 | N29: Notion通常動物表。派生結果名はNotion未記載のため未設定
A30: スケルトン_1,ゴースト_1 | B30: がしゃどくろ | F30: 候補 | G30: 怪異系の新規仮案。巨大化そのものは数量で表さずクラス側で扱う | J30: ライオン | K30: ストーンアニマル | M30: 確定 | N30: Notion通常動物表。派生結果名はNotion未記載のため未設定
A31: フォックス_1,ゴースト_1 | B31: 妖狐 | C31: 幻獣,妖獣 | F31: 候補 | G31: 妖怪系の新規仮案。フォックスは派生表には存在するがクラス原本未登録 | J31: ライノセラス | K31: ストーンアニマル | M31: 確定 | N31: Notion通常動物表。派生結果名はNotion未記載のため未設定
A32: ボア_1,ウルフ_1,デヴィル_1 | B32: 饕餮 | C32: 幻獣,凶獣 | D32: 貪食 | E32: 対象や死体を捕食してHP回復または一時強化を得る。死体システムとの連携を想定。 | F32: 候補 | G32: 四凶候補。貪食・強欲の怪物というモチーフから、ボア＋ウルフ＋デヴィルで仮構成 | J32: ライノセラス | K32: スパークアニマル | M32: 確定 | N32: Notion通常動物表。派生結果名はNotion未記載のため未設定
A33: タイガー_1,ホーク_1,デヴィル_1 | B33: 窮奇 | C33: 幻獣,凶獣 | D33: 凶風襲撃 | E33: 翼による高速接近と虎系の爪撃を組み合わせる強化攻撃。風属性を固定するかは後で決定。 | F33: 候補 | G33: 四凶候補。虎に翼を持つ描写を元にしたゲーム向け仮構成 | J33: ライノセラス | K33: フロストアニマル | M33: 確定 | N33: Notion通常動物表。派生結果名はNotion未記載のため未設定
A34: タイガー_1,ボア_1,ゴブリン_1 | B34: 檮杌 | C34: 幻獣,凶獣 | D34: 不屈の凶性 | E34: HP低下時に攻撃・精神耐性・怯み耐性などを強化する瀕死時パッシブ。発動閾値は未定。 | F34: 候補 | G34: 四凶候補。虎の足・猪の牙・人面という描写を元にしたゲーム向け仮構成 | J34: エレファント | K34: ストーンアニマル | M34: 確定 | N34: Notion通常動物表。派生結果名はNotion未記載のため未設定
A35: スライム_1,エアエレメンタル_1,デヴィル_1 | B35: 混沌 | C35: 幻獣,凶獣 | D35: 無貌の混沌 | E35: 姿の認識を妨げ、命中・看破・幻覚系へ干渉する能力。ランダムではなく固定効果として設計する。 | F35: 候補 | G35: 四凶候補。無貌・翼を持つ異形/混沌のモチーフから作ったゲーム向け仮構成 | J35: エレファント | K35: シーアニマル | M35: 確定 | N35: Notion通常動物表。派生結果名はNotion未記載のため未設定
A36: ドレイク_1,シーアニマル_1,ウィンドアニマル_1 | B36: 青龍 | C36: 幻獣,神獣 | D36: 青龍の雨 | E36: 周囲に雨を発生させ、水系強化・炎抑制などを行う支援能力。天候未接続なら範囲バフ/デバフ化する。 | F36: 候補 | G36: 四神候補。龍＋水＋風で東方の神獣として仮構成 | J36: エレファント | K36: スパークアニマル | M36: 確定 | N36: Notion通常動物表。派生結果名はNotion未記載のため未設定
A37: タイガー_1,エンジェル_1 | B37: 白虎 | C37: 幻獣,神獣 | D37: 白虎の破邪 | E37: 牙・爪攻撃に魔族やアンデッドなどへの対不浄効果を加える攻撃スキル。 | F37: 候補 | G37: 四神候補。虎を基礎に神獣性を加えた仮構成。金属系クラスは現行原本にないため未使用 | J37: オウル | K37: ウィンドアニマル | M37: 確定 | N37: Notion通常動物表。派生結果名はNotion未記載のため未設定
A38: ホーク_1,フレイムエレメンタル_1,ソルアニマル_1 | B38: 朱雀 | C38: 幻獣,神獣 | D38: 朱雀再生 | E38: 炎をまとい継続的にHPを回復する再生能力。フェニックスの転生とは異なり完全復活はしない。 | F38: 候補 | G38: 四神候補。鳥＋炎＋太陽の仮構成 | J38: オウル | K38: ムーンアニマル | M38: 確定 | N38: Notion通常動物表。派生結果名はNotion未記載のため未設定
A39: タートル_1,スネーク_1,シーアニマル_1 | B39: 玄武 | C39: 幻獣,神獣 | D39: 玄武結界 | E39: 自身または周囲の味方に物理/魔法ガードや耐性を付与する防御結界。 | F39: 候補 | G39: 四神候補。亀＋蛇＋水の仮構成。タートルは派生表にはあるがクラス原本未登録 | J39: オウル | K39: エンジェル | M39: 確定 | N39: Notion通常動物表。派生結果名はNotion未記載のため未設定
A40: ゴート_1,エンジェル_1 | B40: 白沢 | C40: 幻獣,神獣,魔眼 | D40: 万物看破 | E40: 看破・索敵を大きく高め、幻覚・隠密・罠などを見抜く情報系パッシブ。 | F40: 候補 | G40: 東方霊獣候補。知識・見通す性質をゲーム向けに魔眼ボーナスクラスで仮表現。ゴートはクラス原本未登録 | J40: キャメル | K40: ストーンアニマル | M40: 確定 | N40: Notion通常動物表。派生結果名はNotion未記載のため未設定
A41: ディア_1,ホース_1,エンジェル_1 | B41: 麒麟 | C41: 幻獣,神獣 | D41: 瑞兆 | E41: 周囲の味方へ士気・精神耐性・状態異常耐性などを与える支援オーラ。 | F41: 候補 | G41: 東方霊獣候補。鹿・馬系の神獣として仮構成。ディアはクラス原本未登録 | J41: キャメル | K41: フレイムアニマル | M41: 確定 | N41: Notion通常動物表。派生結果名はNotion未記載のため未設定
A42: フォックス_1,ムーンアニマル_1,ゴースト_1 | B42: 九尾狐 | C42: 幻獣,妖獣,エヴォリューション・テイル | D42: 九尾幻界 | E42: 広範囲へ幻覚・認識阻害を与える妖術。九尾そのものはテイル系クラスで表現する。 | F42: 候補 | G42: 妖怪・霊獣候補。多尾は数量増加ではなく尾系ボーナスクラスで表現。フォックスはクラス原本未登録 | J42: キャメル | K42: ウィンドアニマル | M42: 確定 | N42: Notion通常動物表。派生結果名はNotion未記載のため未設定
A43: ドレイク_1,エンジェル_1,エアエレメンタル_1 | B43: 応龍 | C43: 幻獣,神獣,エヴォリューション・ウィング | D43: 応龍の豪雨 | E43: 強い雨や水流で広範囲を制圧する攻撃寄り能力。青龍の雨より攻撃性能を重視する。 | F43: 候補 | G43: 東方龍種候補。翼ある龍として仮構成。翼はボーナスクラスで表現 | J43: ディア | K43: ウィンドアニマル | M43: 確定 | N43: Notion通常動物表。派生結果名はNotion未記載のため未設定
... A46: ウルフ_1,フロストアニマル_1,ムーンアニマル_1 | B46: フェンリル | C46: 幻獣 | D46: 終末の牙 | E46: 牙を使う高威力の強化攻撃。防御・ガード突破寄りで、氷や月などの属性は属性進化クラス側に任せる。 | F46: 候補 | G46: 仮レシピ。既存のウルフ＋フロストアニマル→氷ウルフと競合しないよう、ムーンアニマルを追加した3素材合成候補。固有スキル「終末の牙」も仮案 | J46: タートル | K46: シーアニマル | M46: 確定 | N46: Notion通常動物表。派生結果名はNotion未記載のため未設定
J47: タートル | K47: ストーンアニマル | M47: 確定 | N47: Notion通常動物表。派生結果名はNotion未記載のため未設定
J48: タートル | K48: フロストアニマル | M48: 確定 | N48: Notion通常動物表。派生結果名はNotion未記載のため未設定
J49: クラブ | K49: シーアニマル | M49: 確定 | N49: Notion通常動物表。派生結果名はNotion未記載のため未設定
J50: クラブ | K50: フロストアニマル | M50: 確定 | N50: Notion通常動物表。派生結果名はNotion未記載のため未設定
J51: クラブ | K51: ポイズンアニマル | M51: 確定 | N51: Notion通常動物表。派生結果名はNotion未記載のため未設定
J52: スクイード | K52: シーアニマル | M52: 確定 | N52: Notion通常動物表。派生結果名はNotion未記載のため未設定
J53: スクイード | K53: ポイズンアニマル | M53: 確定 | N53: Notion通常動物表。派生結果名はNotion未記載のため未設定
J54: スクイード | K54: デヴィル | M54: 確定 | N54: Notion通常動物表。派生結果名はNotion未記載のため未設定
J55: スラッグ | K55: ポイズンアニマル | M55: 確定 | N55: Notion通常動物表。派生結果名はNotion未記載のため未設定
J56: スラッグ | K56: ストーンアニマル | M56: 確定 | N56: Notion通常動物表。派生結果名はNotion未記載のため未設定
J57: スラッグ | K57: デヴィル | M57: 確定 | N57: Notion通常動物表。派生結果名はNotion未記載のため未設定
J58: ラビット | K58: ウィンドアニマル | M58: 確定 | N58: 2026-10-10生成修正メモ
... J60: ラビット | K60: エンジェル | M60: 確定 | N60: 2026-10-10生成修正メモ。アルミラージ風の外見
J61: アルマジロ | M61: 未設定 | N61: Notion動物系。派生未設定
J62: レイブン | M62: 未設定 | N62: Notion一般生物の追加候補
J63: バット | M63: 未設定 | N63: Notion一般生物の追加候補
J64: ラット | M64: 未設定 | N64: Notion一般生物の追加候補
J65: リザード | M65: 未設定 | N65: Notion一般生物の追加候補
J66: ゴリラ | M66: 未設定 | N66: Notion追加候補。今回は後回し
J67: モンキー | M67: 未設定 | N67: Notion追加候補。今回は後回し
J68: アンケグ | M68: 未設定 | N68: Notion昆虫系採用対象。派生未設定
J69: スコーピオン | M69: 未設定 | N69: Notion昆虫系採用対象。派生未設定
J70: スパイダー | M70: 未設定 | N70: Notion昆虫系採用対象。派生未設定
J71: センティピード | M71: 未設定 | N71: Notion昆虫系採用対象。派生未設定
J72: カブトムシ | M72: 未設定 | N72: 旧ビートルを分割して採用
... J81: ビートル | M81: 未設定 | N81: Notion旧虫系名称。現行はカブトムシ/クワガタへ分割
J82: デザートワーム | K82: ポイズンアニマル | L82: パープルワーム | M82: 候補 | N82: Notion昆虫・甲殻・地中生物旧一覧。パープルワームはデザートワーム系の上位・毒派生候補として扱う。固有スキル候補: 丸呑み（大型の口で対象を捕食・拘束し、即死ではなく拘束・継続ダメージ方向で設計）。
J83: パープルワーム | M83: 未設定 | N83: Notion昆虫・甲殻・地中生物旧一覧
J84: ケイブワーム | M84: 未設定 | N84: Notion昆虫・甲殻・地中生物旧一覧
J85: サンドリーチ | M85: 未設定 | N85: Notion昆虫・甲殻・地中生物旧一覧

Sheet 災害
A1: カテゴリ名 | B1: 効果 | C1: ID | D1: 基本発生率 | E1: 初期判定ターン数 | F1: 影響半径 | G1: 溶岩最大進行マス | H1: 溶岩停止率 | I1: 溶岩方向維持角度 | J1: 周囲産出倍率 | K1: 効果継続ターン | L1: 人口減少最小 | M1: 人口減少最大 | N1: 治安減少 | O1: 対象地形 | P1: 対象種別 | Q1: 最大HP割合ダメージ | R1: 敵生成 | S1: アンデッド発生補正 | T1: アイコン | U1: 画像ファイル | V1: 画像番号 | W1: 有効 | X1: 同一マス待機ターン | Y1: 実装メモ | Z1: 移動時最大HP割合ダメージ | AA1: 滞在ダメージ倍率 | AB1: ダメージ属性 | AC1: ダメージ威力 | AD1: 移動時ダメージ威力 | AE1: 被害範囲方式 | AF1: ランダム被害マス数 | AG1: ランダム被害基準マス数 | AH1: 発生方法 | AI1: 発生条件 | AJ1: 必要継続ターン | AK1: 常設危険地帯 | AL1: 危険地帯効果 | AM1: 地形災害処理 | AN1: 攻撃発生属性 | AO1: 威力軽減 | AP1: 地形耐久 | AQ1: 地形被害倍率 | AR1: 高度低下 | AS1: 撤去AP | AT1: 変化後地形 | AU1: 発生猶予ターン | AV1: 災害詳細設定
A2: 災害種別 | B2: 説明
A3: 山火事 | B3: 通過時は炎威力20、発生時/毎ターンの滞在時は炎威力60で通常ダメージ計算。防御・炎耐性・盾/障壁を適用する。 | C3: 災害:山火事 | D3: 0.012 | F3: 1 | J3: 0.5 | K3: 2 | N3: 5 | O3: 森林,森 | P3: terrain | Q3: 0 | R3: FALSE | S3: FALSE | T3: 火 | U3: 自然災害_アイコン一覧.webp | V3: 1 | W3: TRUE | X3: 4 | Y3: 炎の威力ダメージと通過/滞在3倍を実装。HP割合なし。火炎地への恒久変化は未対応。 | Z3: 0 | AA3: 3 | AB3: 炎 | AC3: 20 | AD3: 20 | AH3: 条件付き,魔法 | AI3: 乾燥 | AJ3: 2
A4: 洪水 | B4: 川と海近辺の土地から収穫量が半減し、都市にダメージ | C4: 災害:洪水 | D4: 0.01 | F4: 1 | J4: 0.5 | K4: 2 | N4: 4 | O4: 河川,海,湖,湿地,沼 | P4: terrain | Q4: 0 | R4: FALSE | S4: FALSE | T4: 水 | U4: 自然災害_アイコン一覧.webp | V4: 2 | W4: TRUE | X4: 4 | Y4: 水流の打撃威力20（暫定）。現行に水耐性がないため打撃耐性を使用。HP割合なし。産出/治安は従来通り。 | Z4: 0 | AA4: 1 | AB4: 打撃 | AC4: 20 | AD4: 0 | AE4: 全域 | AF4: 0 | AH4: 条件付き,魔法 | AI4: 豪雨 | AJ4: 2
A5: 干ばつ | B5: 農地の資源生産が低下する | C5: 災害:干ばつ | D5: 0.01 | F5: 2 | J5: 0.5 | K5: 3 | N5: 3 | O5: 平地,草原,荒野,砂漠 | P5: terrain | Q5: 0 | R5: FALSE | S5: FALSE | T5: 乾 | U5: 自然災害_アイコン一覧.webp | V5: 3 | W5: TRUE | X5: 4 | Y5: 産出/治安/HP割合被害/追加個体は実装済み。説明文の移動・地形変化等の専用効果は別途対応。 | Z5: 0 | AA5: 1 | AH5: 条件付き,魔法 | AI5: 乾燥 | AJ5: 3
A6: 暴風 | B6: 飛行ユニットの移動コストが3倍 射撃の命中が-25% | C6: 災害:暴風 | D6: 0.008 | F6: 2 | J6: 0.8 | K6: 2 | N6: 2 | P6: terrain | Q6: 0 | R6: FALSE | S6: FALSE | T6: 風 | U6: 自然災害_アイコン一覧.webp | V6: 4 | W6: TRUE | X6: 4 | Y6: 産出/治安/HP割合被害/追加個体は実装済み。説明文の移動・地形変化等の専用効果は別途対応。 | Z6: 0 | AA6: 1 | AH6: 条件付き,魔法 | AI6: 強風 | AJ6: 1
A7: 地震 | B7: 範囲内の岩地・山地が断崖へ変化する5%か土砂崩れ10%が起きる可能性 洞窟が10%で崩落。スキルの場合は威力/200毎に起きる倍率がかかる。 | C7: 災害:地震 | D7: 0.006 | F7: 1 | J7: 0.7 | K7: 1 | N7: 7 | O7: 山,岩,丘 | P7: terrain | Q7: 0 | R7: FALSE | S7: FALSE | T7: 震 | U7: 自然災害_アイコン一覧.webp | V7: 5 | W7: TRUE | X7: 4 | Y7: 打撃威力40（暫定）の通常ダメージ計算へ移行。HP割合なし。地形変化等の専用効果は別途。 | Z7: 0 | AA7: 1 | AB7: 打撃 | AC7: 80 | AD7: 0 | AE7: 全域 | AF7: 0 | AH7: 自然,魔法 | AJ7: 0
A8: 落雷嵐 | B8: 毎ターン範囲内3マスにつき1発。自然の落雷威力は湿度65〜100に応じ140〜250、魔法由来は200。端数は余り÷3の確率で1発追加。 | C8: 災害:落雷嵐 | D8: 0.006 | F8: 1 | J8: 0.9 | K8: 1 | N8: 3 | P8: terrain | Q8: 0 | R8: FALSE | S8: FALSE | T8: 雷 | U8: 自然災害_アイコン一覧.webp | V8: 6 | W8: TRUE | X8: 4 | Y8: 威力範囲/魔法威力は災害詳細設定。湿度から確定計算して保存し、同じターンの再抽選をしない。 | Z8: 0 | AA8: 1 | AB8: 雷 | AC8: 140 | AD8: 0 | AE8: ランダム | AF8: 0 | AG8: 3 | AH8: 条件付き,魔法 | AI8: 雷雨 | AJ8: 1 | AV8: {"powerRange":{"minimum":140,"maximum":250,"humidityMinimum":65,"humidityMaximum":100},"magicPower":200}
A9: 大寒波 | B9: 雪原・氷原が拡大し移動コスト2倍 | C9: 災害:大寒波 | D9: 0.006 | F9: 2 | J9: 0.7 | K9: 2 | N9: 3 | O9: 雪,氷,山 | P9: terrain | Q9: 0 | R9: FALSE | S9: FALSE | T9: 冷 | U9: 自然災害_アイコン一覧.webp | V9: 7 | W9: TRUE | X9: 4 | Y9: 産出/治安/HP割合被害/追加個体は実装済み。説明文の移動・地形変化等の専用効果は別途対応。 | Z9: 0 | AA9: 1 | AH9: 条件付き,魔法 | AI9: 寒冷 | AJ9: 2
A10: 熱波 | B10: 平地の生産量が半減 | C10: 災害:熱波 | D10: 0.006 | F10: 2 | J10: 0.5 | K10: 2 | N10: 3 | O10: 平地,草原,荒野,砂漠 | P10: terrain | Q10: 0 | R10: FALSE | S10: FALSE | T10: 熱 | U10: 自然災害_アイコン一覧.webp | V10: 8 | W10: TRUE | X10: 4 | Y10: 産出/治安/HP割合被害/追加個体は実装済み。説明文の移動・地形変化等の専用効果は別途対応。 | Z10: 0 | AA10: 1 | AH10: 条件付き,魔法 | AI10: 高温 | AJ10: 2
A11: 火山噴火 | B11: 溶岩地が発生し周囲に120ダメージ | C11: 災害:火山噴火 | D11: 0.01 | E11: 1 | F11: 1 | G11: 3 | H11: 0.35 | I11: 38 | J11: 0.5 | K11: 2 | L11: 1 | M11: 3 | N11: 10 | P11: terrain | Q11: 0 | R11: FALSE | S11: FALSE | T11: 噴 | U11: 自然災害_アイコン一覧.webp | V11: 9 | W11: TRUE | X11: 4 | Y11: 専用火山システムを使用。その他の列は共通災害用。 | Z11: 0 | AA11: 1 | AH11: 専用処理,魔法 | AJ11: 0
A12: 土砂崩れ | B12: 山地周辺が通行不可になる | C12: 災害:土砂崩れ | D12: 0.008 | F12: 1 | J12: 0.6 | K12: 1 | N12: 5 | O12: 山,岩,丘 | P12: terrain | Q12: 0 | R12: FALSE | S12: FALSE | T12: 崩 | U12: 自然災害_アイコン一覧.webp | V12: 10 | W12: TRUE | X12: 4 | Y12: 打撃威力40（暫定）の通常ダメージ計算へ移行。HP割合なし。地形変化等の専用効果は別途。 | Z12: 0 | AA12: 1 | AB12: 打撃 | AC12: 80 | AD12: 0 | AE12: 全域 | AF12: 0 | AH12: 条件付き,魔法 | AI12: 豪雨 | AJ12: 2
A15: 災害種別 | B15: 説明
A16: 闇侵食 | B16: 呪域が拡大し精神低下 | C16: 災害:闇侵食 | D16: 0.004 | F16: 1 | J16: 0.7 | K16: 3 | N16: 5 | O16: 死の霧,呪 | P16: terrain | Q16: 0 | R16: FALSE | S16: TRUE | T16: 闇 | V16: 0 | W16: TRUE | X16: 4 | Y16: 産出/治安/HP割合被害/追加個体は実装済み。説明文の移動・地形変化等の専用効果は別途対応。 | Z16: 0 | AA16: 1 | AH16: 条件付き,魔法 | AI16: 不浄 | AJ16: 1
A17: 聖光暴発 | B17: 光属性ダメージが定期発生 | C17: 災害:聖光暴発 | D17: 0.003 | F17: 1 | J17: 0.9 | K17: 1 | N17: 2 | P17: terrain | Q17: 0 | R17: FALSE | S17: FALSE | T17: 聖 | V17: 0 | W17: TRUE | X17: 4 | Y17: 光威力40（暫定）の通常ダメージ計算へ移行。HP割合なし。地形変化等の専用効果は別途。 | Z17: 0 | AA17: 1 | AB17: 光 | AC17: 40 | AD17: 0 | AE17: 全域 | AF17: 0 | AH17: イベント,魔法 | AJ17: 0
A18: 重力異常 | B18: 移動力コスト倍・飛行不可 | C18: 災害:重力異常 | D18: 0.003 | F18: 1 | J18: 0.8 | K18: 2 | N18: 2 | P18: terrain | Q18: 0 | R18: FALSE | S18: FALSE | T18: 重 | V18: 0 | W18: TRUE | X18: 4 | Y18: 産出/治安/HP割合被害/追加個体は実装済み。説明文の移動・地形変化等の専用効果は別途対応。 | Z18: 0 | AA18: 1 | AH18: イベント,魔法 | AJ18: 0
A19: 時間歪曲 | B19: APの自然回復量がランダムで75%~125%になる | C19: 災害:時間歪曲 | D19: 0.003 | F19: 1 | J19: 0.9 | K19: 2 | N19: 1 | P19: terrain | Q19: 0 | R19: FALSE | S19: FALSE | T19: 時 | V19: 0 | W19: TRUE | X19: 4 | Y19: 産出/治安/HP割合被害/追加個体は実装済み。説明文の移動・地形変化等の専用効果は別途対応。 | Z19: 0 | AA19: 1 | AH19: イベント,魔法 | AJ19: 0
A20: 空間歪曲 | B20: 移動コストがランダムで50%~150%になる 射程がランダムで50%~150%になる | C20: 災害:空間歪曲 | D20: 0.003 | F20: 1 | J20: 0.9 | K20: 2 | N20: 1 | P20: terrain | Q20: 0 | R20: FALSE | S20: FALSE | T20: 空 | V20: 0 | W20: TRUE | X20: 4 | Y20: 産出/治安/HP割合被害/追加個体は実装済み。説明文の移動・地形変化等の専用効果は別途対応。 | Z20: 0 | AA20: 1 | AH20: イベント,魔法 | AJ20: 0
A21: 魂嵐 | B21: 精神ダメージが20~40継続発生 | C21: 災害:魂嵐 | D21: 0.004 | F21: 1 | J21: 0.8 | K21: 2 | N21: 4 | O21: 死の霧,呪 | P21: terrain | Q21: 0 | R21: FALSE | S21: TRUE | T21: 魂 | V21: 0 | W21: TRUE | X21: 4 | Y21: 精神威力30（暫定）の通常ダメージ計算へ移行。HP割合なし。地形変化等の専用効果は別途。 | Z21: 0 | AA21: 1 | AB21: 精神 | AC21: 30 | AD21: 0 | AE21: 全域 | AF21: 0 | AH21: 条件付き,魔法 | AI21: 不浄 | AJ21: 1
A22: 瘴気 | B22: 地形にいると毒20~50ダメージ | C22: 災害:瘴気 | D22: 0.005 | F22: 1 | J22: 0.7 | K22: 2 | N22: 4 | O22: 沼,湿地,死の霧 | P22: terrain | Q22: 0 | R22: FALSE | S22: FALSE | T22: 瘴 | U22: 自然災害_アイコン一覧.webp | V22: 11 | W22: TRUE | X22: 4 | Y22: 毒威力20（暫定）の通常ダメージ計算へ移行。HP割合なし。地形変化等の専用効果は別途。 | Z22: 0 | AA22: 1 | AB22: 毒 | AC22: 20 | AD22: 0 | AE22: 全域 | AF22: 0 | AH22: 条件付き,魔法 | AI22: 不浄 | AJ22: 1
A25: 災害種別 | B25: 説明
A26: 疫病 | B26: 人口減少・戦闘力低下 | C26: 災害:疫病 | D26: 0.005 | F26: 0 | J26: 0.8 | K26: 3 | N26: 6 | P26: settlement | Q26: 0 | R26: FALSE | S26: FALSE | T26: 病 | U26: 自然災害_アイコン一覧.webp | V26: 12 | W26: TRUE | X26: 4 | Y26: 産出/治安/HP割合被害/追加個体は実装済み。説明文の移動・地形変化等の専用効果は別途対応。 | Z26: 0 | AA26: 1 | AH26: 条件イベント,魔法 | AJ26: 0
A27: 反乱 | B27: 幸福度が不満になると発生。一定地域で敵対勢力が発生。レベルは都市レベルによる | C27: 災害:反乱 | D27: 0.003 | F27: 0 | J27: 0.8 | K27: 2 | N27: 8 | P27: settlement | Q27: 0 | R27: FALSE | S27: FALSE | T27: 乱 | V27: 0 | W27: TRUE | X27: 4 | Y27: 産出/治安/HP割合被害/追加個体は実装済み。説明文の移動・地形変化等の専用効果は別途対応。 | Z27: 0 | AA27: 1 | AH27: 条件イベント,魔法 | AJ27: 0
A28: 飢饉 | B28: 食料不足で発生 指揮が大幅低下、行動成功率-25% | C28: 災害:飢饉 | D28: 0.005 | F28: 0 | J28: 0.6 | K28: 3 | N28: 6 | P28: settlement | Q28: 0 | R28: FALSE | S28: FALSE | T28: 飢 | V28: 0 | W28: TRUE | X28: 4 | Y28: 産出/治安/HP割合被害/追加個体は実装済み。説明文の移動・地形変化等の専用効果は別途対応。 | Z28: 0 | AA28: 1 | AH28: 条件イベント,魔法 | AJ28: 0
A29: 資源枯渇 | B29: 資源不足で発生。町の壁の耐久が半減する。 | C29: 災害:資源枯渇 | D29: 0.004 | F29: 0 | J29: 0.5 | K29: 3 | N29: 2 | P29: settlement | Q29: 0 | R29: FALSE | S29: FALSE | T29: 枯 | V29: 0 | W29: TRUE | X29: 4 | Y29: 産出/治安/HP割合被害/追加個体は実装済み。説明文の移動・地形変化等の専用効果は別途対応。 | Z29: 0 | AA29: 1 | AH29: 条件イベント,魔法 | AJ29: 0
A30: 信仰崩壊 | B30: 士気低下・聖系弱体 | C30: 災害:信仰崩壊 | D30: 0.003 | F30: 0 | J30: 0.9 | K30: 3 | N30: 5 | P30: settlement | Q30: 0 | R30: FALSE | S30: FALSE | T30: 信 | V30: 0 | W30: TRUE | X30: 4 | Y30: 産出/治安/HP割合被害/追加個体は実装済み。説明文の移動・地形変化等の専用効果は別途対応。 | Z30: 0 | AA30: 1 | AH30: 条件イベント,魔法 | AJ30: 0
A31: 経済恐慌 | B31: 収入減少 | C31: 災害:経済恐慌 | D31: 0.003 | F31: 0 | J31: 0.7 | K31: 3 | N31: 3 | P31: settlement | Q31: 0 | R31: FALSE | S31: FALSE | T31: 恐 | V31: 0 | W31: TRUE | X31: 4 | Y31: 産出/治安/HP割合被害/追加個体は実装済み。説明文の移動・地形変化等の専用効果は別途対応。 | Z31: 0 | AA31: 1 | AH31: 条件イベント,魔法 | AJ31: 0
A32: 魔獣暴走 | B32: 野外動物ユニットが増加 | C32: 災害:魔獣暴走 | D32: 0.004 | F32: 1 | J32: 1 | K32: 1 | N32: 4 | P32: terrain | Q32: 0 | R32: TRUE | S32: FALSE | T32: 獣 | V32: 0 | W32: TRUE | X32: 4 | Y32: 産出/治安/HP割合被害/追加個体は実装済み。説明文の移動・地形変化等の専用効果は別途対応。 | Z32: 0 | AA32: 1 | AH32: イベント,魔法 | AJ32: 0
A34: 流星落下 | B34: 高威力範囲ダメージ | C34: 災害:流星落下 | D34: 0.002 | F34: 1 | J34: 0.5 | K34: 1 | N34: 8 | P34: terrain | Q34: 0 | R34: FALSE | S34: FALSE | T34: 星 | V34: 0 | W34: TRUE | X34: 4 | Y34: 打撃威力100（暫定）の通常ダメージ計算へ移行。HP割合なし。地形変化等の専用効果は別途。 | Z34: 0 | AA34: 1 | AB34: 打撃 | AC34: 100 | AD34: 0 | AE34: 全域 | AF34: 0 | AH34: 自然,魔法 | AJ34: 0
A36: 酸の沼 | B36: 侵入/滞在時に酸被害。暫定で毒耐性を共用。 | C36: 危険地帯:酸の沼 | D36: 0 | F36: 1 | J36: 1 | K36: 1 | N36: 0 | O36: 沼地,洞窟 | P36: terrain | Q36: 0 | R36: FALSE | S36: FALSE | T36: 酸 | W36: TRUE | X36: 0 | Y36: 常設環境レイヤー。配置密度・威力は暫定。酸は既存の毒耐性を共用。 | Z36: 0 | AA36: 1 | AB36: 毒 | AC36: 20 | AD36: 20 | AE36: 全域 | AH36: 常設 | AJ36: 0 | AK36: TRUE | AL36: {"color":"#A4C742","contact":true,"acid":true}
A37: 毒沼 | B37: 滞在で毒を受ける。 | C37: 危険地帯:毒沼 | D37: 0 | F37: 1 | J37: 1 | K37: 1 | N37: 0 | O37: 湿地,森 | P37: terrain | Q37: 0 | R37: FALSE | S37: FALSE | T37: 毒 | W37: TRUE | X37: 0 | Y37: 常設環境レイヤー。配置密度・威力は暫定。酸は既存の毒耐性を共用。 | Z37: 0 | AA37: 1 | AB37: 毒 | AC37: 0 | AD37: 0 | AE37: 全域 | AH37: 常設 | AJ37: 0 | AK37: TRUE | AL37: {"color":"#6C9A3A","contact":true,"poisonPower":10,"poisonTurns":3}
A38: 常霧の谷 | B38: 内外・霧越しの索敵にペナルティ。 | C38: 危険地帯:常霧の谷 | D38: 0 | F38: 1 | J38: 1 | K38: 1 | N38: 0 | O38: 峡谷,湖 | P38: terrain | Q38: 0 | R38: FALSE | S38: FALSE | T38: 霧 | W38: TRUE | X38: 0 | Y38: 常設環境レイヤー。配置密度・威力は暫定。酸は既存の毒耐性を共用。 | Z38: 0 | AA38: 1 | AC38: 0 | AD38: 0 | AE38: 全域 | AH38: 常設 | AJ38: 0 | AK38: TRUE | AL38: {"color":"#DCE7EB","fog":true,"windSuppressTurns":3}
A39: 噴気地帯 | B39: 熱・有毒ガスによる被害。 | C39: 危険地帯:噴気地帯 | D39: 0 | F39: 1 | J39: 1 | K39: 1 | N39: 0 | O39: 火山 | P39: terrain | Q39: 0 | R39: FALSE | S39: FALSE | T39: 煙 | W39: TRUE | X39: 0 | Y39: 常設環境レイヤー。配置密度・威力は暫定。酸は既存の毒耐性を共用。 | Z39: 0 | AA39: 1 | AB39: 炎 | AC39: 15 | AD39: 0 | AE39: 全域 | AH39: 常設 | AJ39: 0 | AK39: TRUE | AL39: {"color":"#CFB879","poisonPower":8,"poisonTurns":3}
A40: 極寒地帯 | B40: 冷気ダメージ・移動負担。 | C40: 危険地帯:極寒地帯 | D40: 0 | F40: 1 | J40: 1 | K40: 1 | N40: 0 | O40: 雪原,山岳 | P40: terrain | Q40: 0 | R40: FALSE | S40: FALSE | T40: 寒 | W40: TRUE | X40: 0 | Y40: 常設環境レイヤー。配置密度・威力は暫定。酸は既存の毒耐性を共用。 | Z40: 0 | AA40: 1 | AB40: 氷 | AC40: 15 | AD40: 0 | AE40: 全域 | AH40: 常設 | AJ40: 0 | AK40: TRUE | AL40: {"color":"#83D9FA","movementMultiplier":1.5}
A41: 瘴気地帯 | B41: 回復阻害・不浄が蓄積。 | C41: 危険地帯:瘴気地帯 | D41: 0 | F41: 1 | J41: 1 | K41: 1 | N41: 0 | O41: 廃墟,洞窟 | P41: terrain | Q41: 0 | R41: FALSE | S41: FALSE | T41: 瘴 | W41: TRUE | X41: 0 | Y41: 常設環境レイヤー。配置密度・威力は暫定。酸は既存の毒耐性を共用。 | Z41: 0 | AA41: 1 | AC41: 0 | AD41: 0 | AE41: 全域 | AH41: 常設 | AJ41: 0 | AK41: TRUE | AL41: {"color":"#A6BD48","recoveryMultiplier":0.5,"purificationLoss":1,"windSuppressTurns":3}
A42: 丘陵崩壊 | B42: 強い攻撃で耐久を削り、高度低下と落石を予告する。 | C42: 地形災害:丘陵崩壊 | D42: 0 | F42: 0 | J42: 1 | O42: 丘陵 | P42: terrain | Q42: 0 | R42: FALSE | S42: FALSE | W42: TRUE | AH42: 攻撃 | AK42: FALSE | AM42: 地形破壊 | AN42: 物理/打撃 | AO42: 200 | AP42: 500 | AQ42: 1 | AR42: 1
A43: 山岳崩壊 | B43: 山岳・岩場の耐久が0になると高度低下と落石を予告する。 | C43: 地形災害:山岳崩壊 | D43: 0 | F43: 0 | J43: 1 | O43: 山岳/岩場 | P43: terrain | Q43: 0 | R43: FALSE | S43: FALSE | W43: TRUE | AH43: 攻撃 | AK43: FALSE | AM43: 地形破壊 | AN43: 物理/打撃 | AO43: 200 | AP43: 1000 | AQ43: 1 | AR43: 1
A44: 洞窟落盤 | B44: 岩壁の耐久が0になると通路に変わり、隣接通路への落石を予告する。 | C44: 地形災害:洞窟落盤 | D44: 0 | F44: 0 | J44: 1 | O44: 岩壁 | P44: terrain | Q44: 0 | R44: FALSE | S44: FALSE | W44: TRUE | AH44: 攻撃 | AK44: FALSE | AM44: 地形破壊 | AN44: 物理/打撃 | AO44: 50 | AP44: 200 | AQ44: 1 | AR44: 0 | AT44: 洞窟
A45: 落石 | B45: 猶予後に通常の防御・耐性で被害を計算し、瓦礫を残す。 | C45: 地形災害:落石 | D45: 0 | F45: 0 | J45: 1 | P45: terrain | Q45: 0 | R45: FALSE | S45: FALSE | W45: TRUE | AB45: 打撃 | AC45: 80 | AH45: 攻撃 | AK45: FALSE | AM45: 落石 | AN45: 物理/打撃 | AU45: 1
A46: 瓦礫 | B46: 進入と射線を遮る。攻撃または隣接して撤去し、耐久0で消える。 | C46: 地形災害:瓦礫 | D46: 0 | F46: 0 | J46: 1 | P46: terrain | Q46: 0 | R46: FALSE | S46: FALSE | W46: TRUE | AH46: 攻撃 | AK46: FALSE | AM46: 瓦礫 | AN46: 物理/打撃 | AO46: 0 | AP46: 100 | AQ46: 1 | AS46: 20
A47: 砂嵐 | B47: 砂漠・荒野で索敵と視界、射撃命中にペナルティ。 | C47: 災害:砂嵐 | D47: 0.008 | F47: 2 | J47: 0.7 | K47: 3 | N47: 3 | O47: 砂漠/荒野 | P47: terrain | Q47: 0 | R47: FALSE | S47: FALSE | U47: 自然災害_アイコン一覧.webp | V47: 4 | W47: TRUE | X47: 8 | Z47: 0 | AA47: 1 | AD47: 0 | AH47: 条件付き,魔法 | AI47: 乾燥 | AJ47: 1 | AK47: FALSE | AV47: {"visionPenalty":1,"scoutPenalty":25,"rangedAccuracyMultiplier":0.75}
A48: 雪崩 | B48: 雪山の斜面を低い方へ進み、打撃被害と瓦礫を残す。 | C48: 災害:雪崩 | D48: 0.004 | F48: 0 | J48: 0.7 | K48: 3 | N48: 3 | O48: 雪山/雪原/山岳 | P48: terrain | Q48: 0 | R48: FALSE | S48: FALSE | U48: 自然災害_アイコン一覧.webp | V48: 10 | W48: TRUE | X48: 8 | Z48: 0 | AA48: 1 | AB48: 打撃 | AC48: 80 | AD48: 0 | AH48: 条件付き,魔法 | AI48: 寒冷 | AJ48: 1 | AK48: FALSE | AV48: {"movement":"downhill","stepsPerTurn":1,"minimumHeight":2,"rubbleDurability":100}
A49: 竜巻 | B49: 打撃・切断の複合被害。怯み耐性で軽減した判定値に応じて外側へ吹き飛ばす。 | C49: 災害:竜巻 | D49: 0.003 | F49: 1 | J49: 0.7 | K49: 3 | N49: 3 | O49: 平地/草原/荒野 | P49: terrain | Q49: 0 | R49: FALSE | S49: FALSE | U49: 自然災害_アイコン一覧.webp | V49: 4 | W49: TRUE | X49: 8 | Z49: 0 | AA49: 1 | AB49: 打撃/切断 | AC49: 140 | AD49: 0 | AH49: 条件付き,魔法 | AI49: 強風 | AJ49: 1 | AK49: FALSE | AV49: {"movement":"drift","stepsPerTurn":1,"damageComponents":[{"element":"打撃","weight":1},{"element":"切断","weight":1}],"knockback":{"resistanceKey":"怯み耐性","powerPerTile":50,"maximumDistance":3}}
A50: 台風 | B50: 温暖な海で発生し移動。暖かい海で発達し、陸地・冷たい海では衰弱する。範囲内を豪雨にし、洪水・土砂崩れ・暴風の条件に接続する。範囲内外・横断の索敵と視界に霧と同じペナルティ。 台風威力を防御で軽減し移動・飛行を低下（中心最大、外縁半分、飛行2倍）。直接HP被害なし。 地域の風向へ毎T最大60度ずつ進路を寄せる。 | C50: 災害:台風 | D50: 0.003 | F50: 1 | J50: 0.7 | K50: 5 | N50: 3 | O50: 海 | P50: terrain | Q50: 0 | R50: FALSE | S50: FALSE | U50: 自然災害_アイコン一覧.webp | V50: 4 | W50: TRUE | X50: 8 | Z50: 0 | AA50: 1 | AD50: 0 | AH50: 条件付き,魔法 | AI50: 豪雨 | AJ50: 1 | AK50: FALSE | AV50: {"movement":"drift","stepsPerTurn":1,"minimumClimateTemperature":20,"weather":"豪雨","weatherHumidity":100,"rangedAccuracyMultiplier":0.75,"maximumRadius":4,"radiusGrowthPerTurn":1,"fogPenalty":true,"radiusDecayPerTurn":1,"movementImpediment":{"power":100,"reductionPerPower":0.005,"edgeMultiplier":0.5,"flightMultiplier":2,"maximumReduction":0.9},"followWind":true,"windTurnSteps":1}
A51: 津波 | B51: 近海の地震を条件に沿岸で発生。低地へ進み、打撃被害を与える。影響範囲内の完成施設にも威力に応じたHP被害を与え、拠点の防御・打撃耐性・災害耐性で軽減する。施設HP0は損壊し、修理で復旧する。 | C51: 災害:津波 | D51: 0.05 | F51: 1 | J51: 0.7 | K51: 4 | N51: 3 | O51: 海 | P51: terrain | Q51: 0 | R51: FALSE | S51: FALSE | U51: 自然災害_アイコン一覧.webp | V51: 2 | W51: TRUE | X51: 8 | Z51: 0 | AA51: 1 | AB51: 打撃 | AC51: 200 | AD51: 0 | AH51: 自然,魔法 | AJ51: 1 | AK51: FALSE | AV51: {"movement":"coast","stepsPerTurn":1,"maximumHeight":1,"triggerDisaster":"災害:地震","triggerRadius":6,"facilityDamageMultiplier":1}

Sheet 都市基本データ
A1: データ分類 | B1: 地図表示優先度 | C1: 分類 | D1: 詳細 | E1: 対応技能 | F1: 表示名 | G1: ユニット種別 | H1: 必要軍事Lv | I1: 人口消費 | J1: HP倍率 | K1: 攻撃回数 | L1: 簡易行動限定 | M1: 表示順 | N1: 収入倍率 | O1: 維持食料
A2: 都市名 | C2: 基本情報 | D2: 都市の名称
A3: 都市規模 | C3: 基本情報 | D3: 人口規模段階（小都市・中都市・大都市など）。上限人口や建設可能施設数に影響
A4: 鍛冶Lv | C4: 研究Lv | D4: 作成できる武具などに影響、建設にもかかわってる | E4: 技術
A5: 魔法Lv | C5: 研究Lv | D5: 魔法研究・結界・魔導兵器の水準。魔法系兵種や防衛魔法に影響 | E5: 魔術
A6: 信仰Lv | C6: 研究Lv | D6: 神殿規模や宗教影響力。不死対策・祝福効果・士気補正に影響 | E6: 信仰
A7: 軍事Lv | C7: 研究Lv | D7: 兵舎・防壁・兵器開発の水準。徴兵上限・防衛力・上位兵種解放に影響 | E7: 指揮
A8: 経済Lv | C8: 研究Lv | D8: 技術発展・住民意識の高さ。幸福度・開発効率・反乱抑制に影響 | E8: 統治
A9: 人口 | C9: 人口 | D9: 都市の総人口。税収・徴兵可能人数の基礎
A10: 保有可能人数 | C10: 人口 | D10: 安定する人口数、多すぎたり少なすぎるとペナルティ
A11: 労働人口 | C11: 人口 | D11: 生産に従事可能な人数。資源生産量に影響
A12: 徴兵率 | C12: 軍事 | D12: 人口に対する兵役割合。軍事力↑ 治安↓ 幸福↓
A13: 冒険者率 | C13: 軍事/外部 | D13: 都市外活動人口割合。ダンジョン攻略や外征イベント発生率に影響
A14: 指揮
A15: ヒーロー | C15: 表示しない | D15: 英雄の発生率。
A16: 軍隊 | C16: 表示しない | D16: 軍隊の所持可能率
A17: イベント設定 | C17: 運営 | D17: 祭り・宗教儀式・徴兵強化などの都市方針設定
A18: 道路発展数 | C18: インフラ | D18: 他都市接続数や道路整備度。貿易力・補給力・軍移動速度に影響
A19: 治安 | C19: 安定度 | D19: 犯罪・反乱発生率に影響。低いと災害・暴動発生
A20: 幸福度 | C20: 安定度 | D20: 市民の不満がどのくらいあるか。高いと指揮にボーナス。低いと指揮にペナルティ
A21: 環境安定度 | C21: 環境 | D21: 自然災害発生率や資源回復速度に影響
A22: 回復 | C22: 治癒力 | D22: 自陣営内でのHP回復量
A23: 浄化 | D23: アンデッドが発生しにくくなる。弱体化する。
A24: 穢れ | D24: アンデッドが発生しやすくなる。強化される。
A26: 道路発展数
A28: 生産力
A29: 穀物 | B29: 12 | C29: 食料 | D29: 主食資源。人口維持の基礎 | E29: 農業
A30: 野菜 | B30: 13 | C30: 食料 | D30: 食料多様性補正。幸福度に影響 | E30: 農業
A31: 肉 | B31: 14 | C31: 食料 | D31: 兵士向け高栄養資源。軍維持効率に影響 | E31: 農業
A32: 魚 | B32: 15 | C32: 食料 | D32: 沿岸都市補正資源。食料安定性に影響 | E32: 漁業
A33: 木材 | B33: 10 | C33: 木材 | D33: 建設・兵器材料の基礎資源 | E33: 林業
A34: 黒木 | B34: 9 | C34: 木材 | D34: 高級建築・特殊兵装用素材 | E34: 林業
A35: 特木 | B35: 8 | C35: 木材 | D35: 魔法装備や特別施設用素材 | E35: 林業
A36: 石材 | B36: 11 | C36: 石材 | D36: 城壁・建築物の基礎資源 | E36: 工業
A37: 鉄 | B37: 4 | C37: 金属 | D37: 通常武器防具の基礎素材 | E37: 工業
A38: 銀鉄 | B38: 3 | C38: 金属 | D38: 対魔装備や上位兵装素材 | E38: 工業
A39: 青金鋼 | B39: 2 | C39: 金属 | D39: 高級兵装・重装兵解放素材 | E39: 工業
A40: 赤黒鋼 | B40: 1 | C40: 金属 | D40: 最上級武器・特殊兵器用素材 | E40: 工業
... A43: 宝石 | B43: 5 | C43: 宝石 | D43: 魔法触媒・上級装備素材・交易高額品 | E43: 工業
A44: 死体 | B44: 17 | C44: 特殊資源 | D44: アンデッドの増加に必要
A45: 魂 | B45: 16 | C45: 特殊資源 | D45: 特殊な種族の増加に必要 | O45: FALSE
A46: 死人
A47: 合計死亡数
A48: 誕生
A49: 合計誕生数
A50: normal | C50: ユニット作成 | D50: ネームドキャラクター用の通常ユニット | F50: ヒーローユニット | G50: ヒーロー | H50: 1 | I50: 0 | J50: 1 | K50: 1 | L50: FALSE | M50: 1
A51: army | C51: ユニット作成 | D51: モブ兵士3人分をまとめた軍隊ユニット | F51: 軍隊ユニット | G51: 軍隊 | H51: 1 | I51: 3 | J51: 2 | K51: 3 | L51: TRUE | M51: 2
A52: elite_army | C52: ユニット作成 | D52: 高研究Lvで作成できる強化軍隊ユニット | F52: 強化軍隊ユニット | G52: 精鋭軍隊 | H52: 3 | I52: 5 | J52: 3 | K52: 5 | L52: TRUE | M52: 3
A53: 1 | C53: 経済Lv倍率 | D53: 経済Lv1の資源収入倍率 | N53: 1
A54: 2 | C54: 経済Lv倍率 | D54: 経済Lv2の資源収入倍率 | N54: 1.15
A55: 3 | C55: 経済Lv倍率 | D55: 経済Lv3の資源収入倍率 | N55: 1.3
A56: 4 | C56: 経済Lv倍率 | D56: 経済Lv4の資源収入倍率 | N56: 1.5
A57: 地質調査Lv | C57: 研究Lv | D57: 地質調査による調査済みマスの発見解禁 | E57: 技術
A58: 生態調査Lv | C58: 研究Lv | D58: 生態調査による調査済みマスの発見解禁 | E58: 技術
A59: 地下探索Lv | C59: 研究Lv | D59: 地下探索による調査済みマスの発見解禁 | E59: 技術
A60: 調査Lv | C60: 研究Lv | D60: 調査カテゴリ共通。地質・生態の発見対象はそれぞれの研究IDで判定。 | E60: 技術
A61: 保存食 | B61: 18 | C61: 食料 | D61: 通常食料を加工した軽量な携帯食料。通常食料5→保存食1、保存食1は通常食料5相当（初期値）。魂・死体は加工・代用の対象外。倍率と加工条件はconfig/v39-carried-food.jsonのpreservedFoodで調整。 | E61: 農業 | O61: TRUE

Sheet 都市
